Workbook

Sheet Outstanding_checkout
A1: ID | B1: Date | C1: Name | D1: Email | E1: Equipment Description | F1: Duplicate | G1: Equipment ID | H1: Expected Return Date | I1: Checked out by | J1: Checked in by | K1: Returned Date | L1: Notes
A2: 911546290 | B2: 44805 | C2: =IF(ISBLANK(A2),"Name",IF(ISNA(VLOOKUP(A2,'Master List'!A:C,2,FALSE)), "Not Found", VLOOKUP(A2,'Master List'!A:C,2,FALSE))) -> Amilcar Castillo Ortiz | D2: =IF(ISBLANK(A2), "Email",IF(ISNA(VLOOKUP(A2,'Master List'!A:C,3,FALSE)), "Not Found", VLOOKUP(A2,'Master List'!A:C,3,FALSE))) -> amilco@sfsu.edu | E2: VGA > HDMI Adapter | F2: =IF(OR(A2="",E2="","",A2="?",E2="?"),"duplicate?",IF(COUNTIFS($A:A,A2,E:E,E2)>1,"yes","no")) -> no | G2: NA | H2: 45282 | K2: =IF(J2="","Date",IF(J2<>"",IF(K2="Date",NOW(),K2),"")) -> Date
A3: 922886247 | B3: 44805 | C3: =IF(ISBLANK(A3),"Name",IF(ISNA(VLOOKUP(A3,'Master List'!A:C,2,FALSE)), "Not Found", VLOOKUP(A3,'Master List'!A:C,2,FALSE))) -> Belinda Reyes | D3: =IF(ISBLANK(A3), "Email",IF(ISNA(VLOOKUP(A3,'Master List'!A:C,3,FALSE)), "Not Found", VLOOKUP(A3,'Master List'!A:C,3,FALSE))) -> belinda.reyes124@gmail.com | E3: ? | F3: =IF(OR(A3="",E3="","",A3="?",E3="?"),"duplicate?",IF(COUNTIFS($A:A,A3,E:E,E3)>1,"yes","no")) -> duplicate? | G3: N/A | H3: 45282 | K3: =IF(J3="","Date",IF(J3<>"",IF(K3="Date",NOW(),K3),"")) -> Date
A4: 909749144 | B4: 44805 | C4: =IF(ISBLANK(A4),"Name",IF(ISNA(VLOOKUP(A4,'Master List'!A:C,2,FALSE)), "Not Found", VLOOKUP(A4,'Master List'!A:C,2,FALSE))) -> Erica Maciel | D4: =IF(ISBLANK(A4), "Email",IF(ISNA(VLOOKUP(A4,'Master List'!A:C,3,FALSE)), "Not Found", VLOOKUP(A4,'Master List'!A:C,3,FALSE))) -> emaciel@sfsu.edu | E4: VGA > USB-C Adapter Adapter | F4: =IF(OR(A4="",E4="","",A4="?",E4="?"),"duplicate?",IF(COUNTIFS($A:A,A4,E:E,E4)>1,"yes","no")) -> no | G4: N/A | H4: 45282 | K4: =IF(J4="","Date",IF(J4<>"",IF(K4="Date",NOW(),K4),"")) -> Date
A5: 909749144 | B5: 44805 | C5: =IF(ISBLANK(A5),"Name",IF(ISNA(VLOOKUP(A5,'Master List'!A:C,2,FALSE)), "Not Found", VLOOKUP(A5,'Master List'!A:C,2,FALSE))) -> Erica Maciel | D5: =IF(ISBLANK(A5), "Email",IF(ISNA(VLOOKUP(A5,'Master List'!A:C,3,FALSE)), "Not Found", VLOOKUP(A5,'Master List'!A:C,3,FALSE))) -> emaciel@sfsu.edu | E5: VGA > HDMI Adapter Adapter | F5: =IF(OR(A5="",E5="","",A5="?",E5="?"),"duplicate?",IF(COUNTIFS($A:A,A5,E:E,E5)>1,"yes","no")) -> no | G5: NA | H5: 45282 | K5: =IF(J5="","Date",IF(J5<>"",IF(K5="Date",NOW(),K5),"")) -> Date
A6: 918830723 | B6: 44805 | C6: =IF(ISBLANK(A6),"Name",IF(ISNA(VLOOKUP(A6,'Master List'!A:C,2,FALSE)), "Not Found", VLOOKUP(A6,'Master List'!A:C,2,FALSE))) -> Jesus Solorio | D6: =IF(ISBLANK(A6), "Email",IF(ISNA(VLOOKUP(A6,'Master List'!A:C,3,FALSE)), "Not Found", VLOOKUP(A6,'Master List'!A:C,3,FALSE))) -> jesussolorio@sfsu.edu | E6: VGA > USB-C Adapter Adapter | F6: =IF(OR(A6="",E6="","",A6="?",E6="?"),"duplicate?",IF(COUNTIFS($A:A,A6,E:E,E6)>1,"yes","no")) -> no | G6: NA | H6: 45282 | K6: =IF(J6="","Date",IF(J6<>"",IF(K6="Date",NOW(),K6),"")) -> Date
A7: 901118496 | B7: 44805 | C7: =IF(ISBLANK(A7),"Name",IF(ISNA(VLOOKUP(A7,'Master List'!A:C,2,FALSE)), "Not Found", VLOOKUP(A7,'Master List'!A:C,2,FALSE))) -> Marilyn Smulyan | D7: =IF(ISBLANK(A7), "Email",IF(ISNA(VLOOKUP(A7,'Master List'!A:C,3,FALSE)), "Not Found", VLOOKUP(A7,'Master List'!A:C,3,FALSE))) -> msmulyan@sfsu.edu | E7: VGA > USB-C Adapter Adapter | F7: =IF(OR(A7="",E7="","",A7="?",E7="?"),"duplicate?",IF(COUNTIFS($A:A,A7,E:E,E7)>1,"yes","no")) -> no | G7: NA | H7: 45283 | K7: =IF(J7="","Date",IF(J7<>"",IF(K7="Date",NOW(),K7),"")) -> Date
A8: 915081692 | B8: 44805 | C8: =IF(ISBLANK(A8),"Name",IF(ISNA(VLOOKUP(A8,'Master List'!A:C,2,FALSE)), "Not Found", VLOOKUP(A8,'Master List'!A:C,2,FALSE))) -> Nereyda Valdez | D8: =IF(ISBLANK(A8), "Email",IF(ISNA(VLOOKUP(A8,'Master List'!A:C,3,FALSE)), "Not Found", VLOOKUP(A8,'Master List'!A:C,3,FALSE))) -> nmonteci@sfsu.edu | E8: HDMI > MDP Adapter Adapter | F8: =IF(OR(A8="",E8="","",A8="?",E8="?"),"duplicate?",IF(COUNTIFS($A:A,A8,E:E,E8)>1,"yes","no")) -> no | G8: NA | H8: 45282 | K8: =IF(J8="","Date",IF(J8<>"",IF(K8="Date",NOW(),K8),"")) -> Date
A9: 901130898 | B9: 44805 | C9: =IF(ISBLANK(A9),"Name",IF(ISNA(VLOOKUP(A9,'Master List'!A:C,2,FALSE)), "Not Found", VLOOKUP(A9,'Master List'!A:C,2,FALSE))) -> Patricia Van Velsor | D9: =IF(ISBLANK(A9), "Email",IF(ISNA(VLOOKUP(A9,'Master List'!A:C,3,FALSE)), "Not Found", VLOOKUP(A9,'Master List'!A:C,3,FALSE))) -> pvanvels@sfsu.edu | E9: VGA > USB-C Adapter Adapter | F9: =IF(OR(A9="",E9="","",A9="?",E9="?"),"duplicate?",IF(COUNTIFS($A:A,A9,E:E,E9)>1,"yes","no")) -> no | G9: NA | H9: 45282 | K9: =IF(J9="","Date",IF(J9<>"",IF(K9="Date",NOW(),K9),"")) -> Date
A10: 918103178 | B10: 44805 | C10: =IF(ISBLANK(A10),"Name",IF(ISNA(VLOOKUP(A10,'Master List'!A:C,2,FALSE)), "Not Found", VLOOKUP(A10,'Master List'!A:C,2,FALSE))) -> Veronica Rabelo | D10: =IF(ISBLANK(A10), "Email",IF(ISNA(VLOOKUP(A10,'Master List'!A:C,3,FALSE)), "Not Found", VLOOKUP(A10,'Master List'!A:C,3,FALSE))) -> rabelo@sfsu.edu | E10: HDMI > USB-C Adapter | F10: =IF(OR(A10="",E10="","",A10="?",E10="?"),"duplicate?",IF(COUNTIFS($A:A,A10,E:E,E10)>1,"yes","no")) -> no | G10: NA | H10: 45282 | K10: =IF(J10="","Date",IF(J10<>"",IF(K10="Date",NOW(),K10),"")) -> Date
A11: 900018215 | B11: 44805 | C11: =IF(ISBLANK(A11),"Name",IF(ISNA(VLOOKUP(A11,'Master List'!A:C,2,FALSE)), "Not Found", VLOOKUP(A11,'Master List'!A:C,2,FALSE))) -> Vivian Chavez | D11: =IF(ISBLANK(A11), "Email",IF(ISNA(VLOOKUP(A11,'Master List'!A:C,3,FALSE)), "Not Found", VLOOKUP(A11,'Master List'!A:C,3,FALSE))) -> vchavez@sfsu.edu | E11: Mac Power Adapter (USB-C) | F11: =IF(OR(A11="",E11="","",A11="?",E11="?"),"duplicate?",IF(COUNTIFS($A:A,A11,E:E,E11)>1,"yes","no")) -> no | G11: N/A | H11: Indefinite | K11: =IF(J11="","Date",IF(J11<>"",IF(K11="Date",NOW(),K11),"")) -> Date
A12: 917117336 | B12: 44806 | C12: =IF(ISBLANK(A12),"Name",IF(ISNA(VLOOKUP(A12,'Master List'!A:C,2,FALSE)), "Not Found", VLOOKUP(A12,'Master List'!A:C,2,FALSE))) -> Bruna Mota | D12: =IF(ISBLANK(A12), "Email",IF(ISNA(VLOOKUP(A12,'Master List'!A:C,3,FALSE)), "Not Found", VLOOKUP(A12,'Master List'!A:C,3,FALSE))) -> bmota@mail.sfsu.edu | E12: VGA > USB-C Adapter Adapter | F12: =IF(OR(A12="",E12="","",A12="?",E12="?"),"duplicate?",IF(COUNTIFS($A:A,A12,E:E,E12)>1,"yes","no")) -> no | G12: NA | H12: 45282 | K12: =IF(J12="","Date",IF(J12<>"",IF(K12="Date",NOW(),K12),"")) -> Date
A13: 916467726 | B13: 44806 | C13: =IF(ISBLANK(A13),"Name",IF(ISNA(VLOOKUP(A13,'Master List'!A:C,2,FALSE)), "Not Found", VLOOKUP(A13,'Master List'!A:C,2,FALSE))) -> Edwin Ochong | D13: =IF(ISBLANK(A13), "Email",IF(ISNA(VLOOKUP(A13,'Master List'!A:C,3,FALSE)), "Not Found", VLOOKUP(A13,'Master List'!A:C,3,FALSE))) -> edochong@yahoo.com | E13: HDMI > USB-C Adapter | F13: =IF(OR(A13="",E13="","",A13="?",E13="?"),"duplicate?",IF(COUNTIFS($A:A,A13,E:E,E13)>1,"yes","no")) -> no | G13: NA | H13: 45282 | K13: =IF(J13="","Date",IF(J13<>"",IF(K13="Date",NOW(),K13),"")) -> Date
A14: 912461828 | B14: 44810 | C14: =IF(ISBLANK(A14),"Name",IF(ISNA(VLOOKUP(A14,'Master List'!A:C,2,FALSE)), "Not Found", VLOOKUP(A14,'Master List'!A:C,2,FALSE))) -> Asharee Brown | D14: =IF(ISBLANK(A14), "Email",IF(ISNA(VLOOKUP(A14,'Master List'!A:C,3,FALSE)), "Not Found", VLOOKUP(A14,'Master List'!A:C,3,FALSE))) -> asbrown@sfsu.edu | E14: VGA > USB-C Adapter Adapter | F14: =IF(OR(A14="",E14="","",A14="?",E14="?"),"duplicate?",IF(COUNTIFS($A:A,A14,E:E,E14)>1,"yes","no")) -> no | H14: 45282 | K14: =IF(J14="","Date",IF(J14<>"",IF(K14="Date",NOW(),K14),"")) -> Date
A15: 912461828 | B15: 44810 | C15: =IF(ISBLANK(A15),"Name",IF(ISNA(VLOOKUP(A15,'Master List'!A:C,2,FALSE)), "Not Found", VLOOKUP(A15,'Master List'!A:C,2,FALSE))) -> Asharee Brown | D15: =IF(ISBLANK(A15), "Email",IF(ISNA(VLOOKUP(A15,'Master List'!A:C,3,FALSE)), "Not Found", VLOOKUP(A15,'Master List'!A:C,3,FALSE))) -> asbrown@sfsu.edu | E15: HDMI > USB-C Adapter | F15: =IF(OR(A15="",E15="","",A15="?",E15="?"),"duplicate?",IF(COUNTIFS($A:A,A15,E:E,E15)>1,"yes","no")) -> no | G15: NA | H15: 45282 | K15: =IF(J15="","Date",IF(J15<>"",IF(K15="Date",NOW(),K15),"")) -> Date
A16: 900045866 | B16: 44810 | C16: =IF(ISBLANK(A16),"Name",IF(ISNA(VLOOKUP(A16,'Master List'!A:C,2,FALSE)), "Not Found", VLOOKUP(A16,'Master List'!A:C,2,FALSE))) -> Elane Feng | D16: =IF(ISBLANK(A16), "Email",IF(ISNA(VLOOKUP(A16,'Master List'!A:C,3,FALSE)), "Not Found", VLOOKUP(A16,'Master List'!A:C,3,FALSE))) -> efeng@sfsu.edu | E16: Mac Power Adapter (USB-C) | F16: =IF(OR(A16="",E16="","",A16="?",E16="?"),"duplicate?",IF(COUNTIFS($A:A,A16,E:E,E16)>1,"yes","no")) -> no | G16: NA | H16: 45282 | K16: =IF(J16="","Date",IF(J16<>"",IF(K16="Date",NOW(),K16),"")) -> Date
A17: 906999384 | B17: 44810 | C17: =IF(ISBLANK(A17),"Name",IF(ISNA(VLOOKUP(A17,'Master List'!A:C,2,FALSE)), "Not Found", VLOOKUP(A17,'Master List'!A:C,2,FALSE))) -> Gail Baugh | D17: =IF(ISBLANK(A17), "Email",IF(ISNA(VLOOKUP(A17,'Master List'!A:C,3,FALSE)), "Not Found", VLOOKUP(A17,'Master List'!A:C,3,FALSE))) -> gailbaugh@sfsu.edu | E17: HDMI > USB-C Adapter | F17: =IF(OR(A17="",E17="","",A17="?",E17="?"),"duplicate?",IF(COUNTIFS($A:A,A17,E:E,E17)>1,"yes","no")) -> no | G17: NA | H17: 45282 | K17: =IF(J17="","Date",IF(J17<>"",IF(K17="Date",NOW(),K17),"")) -> Date
A18: 900015524 | B18: 44810 | C18: =IF(ISBLANK(A18),"Name",IF(ISNA(VLOOKUP(A18,'Master List'!A:C,2,FALSE)), "Not Found", VLOOKUP(A18,'Master List'!A:C,2,FALSE))) -> George Gassner | D18: =IF(ISBLANK(A18), "Email",IF(ISNA(VLOOKUP(A18,'Master List'!A:C,3,FALSE)), "Not Found", VLOOKUP(A18,'Master List'!A:C,3,FALSE))) -> gassner@sfsu.edu | E18: Webcam (Logi 720p) | F18: =IF(OR(A18="",E18="","",A18="?",E18="?"),"duplicate?",IF(COUNTIFS($A:A,A18,E:E,E18)>1,"yes","no")) -> no | H18: 45282 | K18: =IF(J18="","Date",IF(J18<>"",IF(K18="Date",NOW(),K18),"")) -> Date
A19: 908492564 | B19: 44810 | C19: =IF(ISBLANK(A19),"Name",IF(ISNA(VLOOKUP(A19,'Master List'!A:C,2,FALSE)), "Not Found", VLOOKUP(A19,'Master List'!A:C,2,FALSE))) -> Julietta Hua | D19: =IF(ISBLANK(A19), "Email",IF(ISNA(VLOOKUP(A19,'Master List'!A:C,3,FALSE)), "Not Found", VLOOKUP(A19,'Master List'!A:C,3,FALSE))) -> jyhua@sfsu.edu | E19: Multiport adapter (USB-C hub) (USB-C hub) | F19: =IF(OR(A19="",E19="","",A19="?",E19="?"),"duplicate?",IF(COUNTIFS($A:A,A19,E:E,E19)>1,"yes","no")) -> no | G19: NA | H19: 45282 | K19: =IF(J19="","Date",IF(J19<>"",IF(K19="Date",NOW(),K19),"")) -> Date
A20: 902476632 | B20: 44810 | C20: =IF(ISBLANK(A20),"Name",IF(ISNA(VLOOKUP(A20,'Master List'!A:C,2,FALSE)), "Not Found", VLOOKUP(A20,'Master List'!A:C,2,FALSE))) -> Matt Pico | D20: =IF(ISBLANK(A20), "Email",IF(ISNA(VLOOKUP(A20,'Master List'!A:C,3,FALSE)), "Not Found", VLOOKUP(A20,'Master List'!A:C,3,FALSE))) -> mpico@sfsu.edu | E20: HDMI > USB-C Adapter | F20: =IF(OR(A20="",E20="","",A20="?",E20="?"),"duplicate?",IF(COUNTIFS($A:A,A20,E:E,E20)>1,"yes","no")) -> no | G20: NA | H20: 45282 | K20: =IF(J20="","Date",IF(J20<>"",IF(K20="Date",NOW(),K20),"")) -> Date
A21: 918328884 | B21: 44810 | C21: =IF(ISBLANK(A21),"Name",IF(ISNA(VLOOKUP(A21,'Master List'!A:C,2,FALSE)), "Not Found", VLOOKUP(A21,'Master List'!A:C,2,FALSE))) -> Menaal Alowdi | D21: =IF(ISBLANK(A21), "Email",IF(ISNA(VLOOKUP(A21,'Master List'!A:C,3,FALSE)), "Not Found", VLOOKUP(A21,'Master List'!A:C,3,FALSE))) -> malowdi@mail.sfsu.edu | E21: HDMI > USB-C Adapter | F21: =IF(OR(A21="",E21="","",A21="?",E21="?"),"duplicate?",IF(COUNTIFS($A:A,A21,E:E,E21)>1,"yes","no")) -> no | G21: NA | H21: 45282 | K21: =IF(J21="","Date",IF(J21<>"",IF(K21="Date",NOW(),K21),"")) -> Date
A22: 909186933 | B22: 44810 | C22: =IF(ISBLANK(A22),"Name",IF(ISNA(VLOOKUP(A22,'Master List'!A:C,2,FALSE)), "Not Found", VLOOKUP(A22,'Master List'!A:C,2,FALSE))) -> Mahmood Monshipouri | D22: =IF(ISBLANK(A22), "Email",IF(ISNA(VLOOKUP(A22,'Master List'!A:C,3,FALSE)), "Not Found", VLOOKUP(A22,'Master List'!A:C,3,FALSE))) -> mmonship@sfsu.edu | E22: HDMI > USB-C Adapter | F22: =IF(OR(A22="",E22="","",A22="?",E22="?"),"duplicate?",IF(COUNTIFS($A:A,A22,E:E,E22)>1,"yes","no")) -> no | G22: NA | H22: 45282 | K22: =IF(J22="","Date",IF(J22<>"",IF(K22="Date",NOW(),K22),"")) -> Date
A23: 917253199 | B23: 44810 | C23: =IF(ISBLANK(A23),"Name",IF(ISNA(VLOOKUP(A23,'Master List'!A:C,2,FALSE)), "Not Found", VLOOKUP(A23,'Master List'!A:C,2,FALSE))) -> Robert Allen | D23: =IF(ISBLANK(A23), "Email",IF(ISNA(VLOOKUP(A23,'Master List'!A:C,3,FALSE)), "Not Found", VLOOKUP(A23,'Master List'!A:C,3,FALSE))) -> roballen@sfsu.edu | E23: HDMI > MDP Adapter | F23: =IF(OR(A23="",E23="","",A23="?",E23="?"),"duplicate?",IF(COUNTIFS($A:A,A23,E:E,E23)>1,"yes","no")) -> no | G23: NA | H23: 45282 | K23: =IF(J23="","Date",IF(J23<>"",IF(K23="Date",NOW(),K23),"")) -> Date
A24: 918848234 | B24: 44810 | C24: =IF(ISBLANK(A24),"Name",IF(ISNA(VLOOKUP(A24,'Master List'!A:C,2,FALSE)), "Not Found", VLOOKUP(A24,'Master List'!A:C,2,FALSE))) -> Sanchita Ghose | D24: =IF(ISBLANK(A24), "Email",IF(ISNA(VLOOKUP(A24,'Master List'!A:C,3,FALSE)), "Not Found", VLOOKUP(A24,'Master List'!A:C,3,FALSE))) -> sanchitaghose@sfsu.edu | E24: Keyboard+USB-C > USB-C Cable | F24: =IF(OR(A24="",E24="","",A24="?",E24="?"),"duplicate?",IF(COUNTIFS($A:A,A24,E:E,E24)>1,"yes","no")) -> no | G24: NA | H24: 45282 | K24: =IF(J24="","Date",IF(J24<>"",IF(K24="Date",NOW(),K24),"")) -> Date
A25: 915848432 | B25: 44810 | C25: =IF(ISBLANK(A25),"Name",IF(ISNA(VLOOKUP(A25,'Master List'!A:C,2,FALSE)), "Not Found", VLOOKUP(A25,'Master List'!A:C,2,FALSE))) -> Valerie Fernandez | D25: =IF(ISBLANK(A25), "Email",IF(ISNA(VLOOKUP(A25,'Master List'!A:C,3,FALSE)), "Not Found", VLOOKUP(A25,'Master List'!A:C,3,FALSE))) -> vfernandez3@sfsu.edu | E25: HDMI > USB-C Adapter | F25: =IF(OR(A25="",E25="","",A25="?",E25="?"),"duplicate?",IF(COUNTIFS($A:A,A25,E:E,E25)>1,"yes","no")) -> no | G25: NA | H25: 45282 | K25: =IF(J25="","Date",IF(J25<>"",IF(K25="Date",NOW(),K25),"")) -> Date
A26: 922404701 | B26: 44811 | C26: =IF(ISBLANK(A26),"Name",IF(ISNA(VLOOKUP(A26,'Master List'!A:C,2,FALSE)), "Not Found", VLOOKUP(A26,'Master List'!A:C,2,FALSE))) -> Anudeep Katukojwala | D26: =IF(ISBLANK(A26), "Email",IF(ISNA(VLOOKUP(A26,'Master List'!A:C,3,FALSE)), "Not Found", VLOOKUP(A26,'Master List'!A:C,3,FALSE))) -> akatukojwala@sfsu.edu | E26: Pen Tablet (Wacom Intuos) | F26: =IF(OR(A26="",E26="","",A26="?",E26="?"),"duplicate?",IF(COUNTIFS($A:A,A26,E:E,E26)>1,"yes","no")) -> no | H26: 45282 | K26: =IF(J26="","Date",IF(J26<>"",IF(K26="Date",NOW(),K26),"")) -> Date
A27: 922404701 | B27: 44811 | C27: =IF(ISBLANK(A27),"Name",IF(ISNA(VLOOKUP(A27,'Master List'!A:C,2,FALSE)), "Not Found", VLOOKUP(A27,'Master List'!A:C,2,FALSE))) -> Anudeep Katukojwala | D27: =IF(ISBLANK(A27), "Email",IF(ISNA(VLOOKUP(A27,'Master List'!A:C,3,FALSE)), "Not Found", VLOOKUP(A27,'Master List'!A:C,3,FALSE))) -> akatukojwala@sfsu.edu | E27: HDMI > USB-C Adapter | F27: =IF(OR(A27="",E27="","",A27="?",E27="?"),"duplicate?",IF(COUNTIFS($A:A,A27,E:E,E27)>1,"yes","no")) -> no | G27: NA | H27: 45282 | K27: =IF(J27="","Date",IF(J27<>"",IF(K27="Date",NOW(),K27),"")) -> Date
A28: 900204037 | B28: 44812 | C28: =IF(ISBLANK(A28),"Name",IF(ISNA(VLOOKUP(A28,'Master List'!A:C,2,FALSE)), "Not Found", VLOOKUP(A28,'Master List'!A:C,2,FALSE))) -> Carolyn Gencarella | D28: =IF(ISBLANK(A28), "Email",IF(ISNA(VLOOKUP(A28,'Master List'!A:C,3,FALSE)), "Not Found", VLOOKUP(A28,'Master List'!A:C,3,FALSE))) -> gencarellac@sfsu.edu | E28: VGA > USB-C Adapter Adapter | F28: =IF(OR(A28="",E28="","",A28="?",E28="?"),"duplicate?",IF(COUNTIFS($A:A,A28,E:E,E28)>1,"yes","no")) -> no | G28: NA | H28: 45282 | K28: =IF(J28="","Date",IF(J28<>"",IF(K28="Date",NOW(),K28),"")) -> Date
A29: 909819539 | B29: 44816 | C29: =IF(ISBLANK(A29),"Name",IF(ISNA(VLOOKUP(A29,'Master List'!A:C,2,FALSE)), "Not Found", VLOOKUP(A29,'Master List'!A:C,2,FALSE))) -> Nicholas Torres | D29: =IF(ISBLANK(A29), "Email",IF(ISNA(VLOOKUP(A29,'Master List'!A:C,3,FALSE)), "Not Found", VLOOKUP(A29,'Master List'!A:C,3,FALSE))) -> ntorres3@mail.sfsu.edu | E29: VGA > HDMI Adapter Adapter | F29: =IF(OR(A29="",E29="","",A29="?",E29="?"),"duplicate?",IF(COUNTIFS($A:A,A29,E:E,E29)>1,"yes","no")) -> no | G29: NA | H29: 45282 | K29: =IF(J29="","Date",IF(J29<>"",IF(K29="Date",NOW(),K29),"")) -> Date
A30: 907603858 | B30: 44817 | C30: =IF(ISBLANK(A30),"Name",IF(ISNA(VLOOKUP(A30,'Master List'!A:C,2,FALSE)), "Not Found", VLOOKUP(A30,'Master List'!A:C,2,FALSE))) -> Jason Harris-Boundy | D30: =IF(ISBLANK(A30), "Email",IF(ISNA(VLOOKUP(A30,'Master List'!A:C,3,FALSE)), "Not Found", VLOOKUP(A30,'Master List'!A:C,3,FALSE))) -> jchb@sfsu.edu | E30: HDMI > USB-C Adapter | F30: =IF(OR(A30="",E30="","",A30="?",E30="?"),"duplicate?",IF(COUNTIFS($A:A,A30,E:E,E30)>1,"yes","no")) -> no | G30: NA | H30: 45282 | K30: =IF(J30="","Date",IF(J30<>"",IF(K30="Date",NOW(),K30),"")) -> Date
A31: 909861620 | B31: 44817 | C31: =IF(ISBLANK(A31),"Name",IF(ISNA(VLOOKUP(A31,'Master List'!A:C,2,FALSE)), "Not Found", VLOOKUP(A31,'Master List'!A:C,2,FALSE))) -> Kwong-Liem Kwan | D31: =IF(ISBLANK(A31), "Email",IF(ISNA(VLOOKUP(A31,'Master List'!A:C,3,FALSE)), "Not Found", VLOOKUP(A31,'Master List'!A:C,3,FALSE))) -> kwan@sfsu.edu | E31: HDMI > USB-C Adapter | F31: =IF(OR(A31="",E31="","",A31="?",E31="?"),"duplicate?",IF(COUNTIFS($A:A,A31,E:E,E31)>1,"yes","no")) -> yes | H31: 45282 | K31: =IF(J31="","Date",IF(J31<>"",IF(K31="Date",NOW(),K31),"")) -> Date
A32: 918836274 | B32: 44818 | C32: =IF(ISBLANK(A32),"Name",IF(ISNA(VLOOKUP(A32,'Master List'!A:C,2,FALSE)), "Not Found", VLOOKUP(A32,'Master List'!A:C,2,FALSE))) -> Caroline Casper | D32: =IF(ISBLANK(A32), "Email",IF(ISNA(VLOOKUP(A32,'Master List'!A:C,3,FALSE)), "Not Found", VLOOKUP(A32,'Master List'!A:C,3,FALSE))) -> ccasper@sfsu.edu | E32: HDMI > USB-C Adapter | F32: =IF(OR(A32="",E32="","",A32="?",E32="?"),"duplicate?",IF(COUNTIFS($A:A,A32,E:E,E32)>1,"yes","no")) -> yes | G32: NA | H32: 45282 | K32: =IF(J32="","Date",IF(J32<>"",IF(K32="Date",NOW(),K32),"")) -> Date
A33: 911369841 | B33: 44818 | C33: =IF(ISBLANK(A33),"Name",IF(ISNA(VLOOKUP(A33,'Master List'!A:C,2,FALSE)), "Not Found", VLOOKUP(A33,'Master List'!A:C,2,FALSE))) -> Aiko Yoshino | D33: =IF(ISBLANK(A33), "Email",IF(ISNA(VLOOKUP(A33,'Master List'!A:C,3,FALSE)), "Not Found", VLOOKUP(A33,'Master List'!A:C,3,FALSE))) -> ayoshino@sfsu.edu | E33: HDMI > USB-C Adapter | F33: =IF(OR(A33="",E33="","",A33="?",E33="?"),"duplicate?",IF(COUNTIFS($A:A,A33,E:E,E33)>1,"yes","no")) -> yes | G33: NA | H33: 45282 | K33: =IF(J33="","Date",IF(J33<>"",IF(K33="Date",NOW(),K33),"")) -> Date
A34: 918834168 | B34: 44818 | C34: =IF(ISBLANK(A34),"Name",IF(ISNA(VLOOKUP(A34,'Master List'!A:C,2,FALSE)), "Not Found", VLOOKUP(A34,'Master List'!A:C,2,FALSE))) -> Jingyi Wang | D34: =IF(ISBLANK(A34), "Email",IF(ISNA(VLOOKUP(A34,'Master List'!A:C,3,FALSE)), "Not Found", VLOOKUP(A34,'Master List'!A:C,3,FALSE))) -> jingyiwang@sfsu.edu | E34: HDMI > USB-C Adapter | F34: =IF(OR(A34="",E34="","",A34="?",E34="?"),"duplicate?",IF(COUNTIFS($A:A,A34,E:E,E34)>1,"yes","no")) -> no | G34: NA | H34: 45282 | K34: =IF(J34="","Date",IF(J34<>"",IF(K34="Date",NOW(),K34),"")) -> Date
A35: 900029187 | B35: 44818 | C35: =IF(ISBLANK(A35),"Name",IF(ISNA(VLOOKUP(A35,'Master List'!A:C,2,FALSE)), "Not Found", VLOOKUP(A35,'Master List'!A:C,2,FALSE))) -> Karen Johnson-Brennan | D35: =IF(ISBLANK(A35), "Email",IF(ISNA(VLOOKUP(A35,'Master List'!A:C,3,FALSE)), "Not Found", VLOOKUP(A35,'Master List'!A:C,3,FALSE))) -> kcjb@sfsu.edu | E35: PA - Small | F35: =IF(OR(A35="",E35="","",A35="?",E35="?"),"duplicate?",IF(COUNTIFS($A:A,A35,E:E,E35)>1,"yes","no")) -> no | G35: NA | H35: 45282 | K35: =IF(J35="","Date",IF(J35<>"",IF(K35="Date",NOW(),K35),"")) -> Date
A36: 900025404 | B36: 44819 | C36: =IF(ISBLANK(A36),"Name",IF(ISNA(VLOOKUP(A36,'Master List'!A:C,2,FALSE)), "Not Found", VLOOKUP(A36,'Master List'!A:C,2,FALSE))) -> Bruce Heiman | D36: =IF(ISBLANK(A36), "Email",IF(ISNA(VLOOKUP(A36,'Master List'!A:C,3,FALSE)), "Not Found", VLOOKUP(A36,'Master List'!A:C,3,FALSE))) -> bheiman@sfsu.edu | E36: Multiport adapter (USB-C hub) (USB-C hub) | F36: =IF(OR(A36="",E36="","",A36="?",E36="?"),"duplicate?",IF(COUNTIFS($A:A,A36,E:E,E36)>1,"yes","no")) -> no | G36: N/A | H36: 45282 | K36: =IF(J36="","Date",IF(J36<>"",IF(K36="Date",NOW(),K36),"")) -> Date
A37: 906207684 | B37: 44819 | C37: =IF(ISBLANK(A37),"Name",IF(ISNA(VLOOKUP(A37,'Master List'!A:C,2,FALSE)), "Not Found", VLOOKUP(A37,'Master List'!A:C,2,FALSE))) -> Mark Shrayber | D37: =IF(ISBLANK(A37), "Email",IF(ISNA(VLOOKUP(A37,'Master List'!A:C,3,FALSE)), "Not Found", VLOOKUP(A37,'Master List'!A:C,3,FALSE))) -> mshraybe@sfsu.edu | E37: HDMI > USB-C Adapter | F37: =IF(OR(A37="",E37="","",A37="?",E37="?"),"duplicate?",IF(COUNTIFS($A:A,A37,E:E,E37)>1,"yes","no")) -> no | G37: NA | H37: 45282 | K37: =IF(J37="","Date",IF(J37<>"",IF(K37="Date",NOW(),K37),"")) -> Date
A38: 922404701 | B38: 44823 | C38: =IF(ISBLANK(A38),"Name",IF(ISNA(VLOOKUP(A38,'Master List'!A:C,2,FALSE)), "Not Found", VLOOKUP(A38,'Master List'!A:C,2,FALSE))) -> Anudeep Katukojwala | D38: =IF(ISBLANK(A38), "Email",IF(ISNA(VLOOKUP(A38,'Master List'!A:C,3,FALSE)), "Not Found", VLOOKUP(A38,'Master List'!A:C,3,FALSE))) -> akatukojwala@sfsu.edu | E38: USB-A > USB-C Adapter Adapter | F38: =IF(OR(A38="",E38="","",A38="?",E38="?"),"duplicate?",IF(COUNTIFS($A:A,A38,E:E,E38)>1,"yes","no")) -> no | G38: NA | H38: 45282 | K38: =IF(J38="","Date",IF(J38<>"",IF(K38="Date",NOW(),K38),"")) -> Date
A39: 900018007 | B39: 44823 | C39: =IF(ISBLANK(A39),"Name",IF(ISNA(VLOOKUP(A39,'Master List'!A:C,2,FALSE)), "Not Found", VLOOKUP(A39,'Master List'!A:C,2,FALSE))) -> Deborah Miller | D39: =IF(ISBLANK(A39), "Email",IF(ISNA(VLOOKUP(A39,'Master List'!A:C,3,FALSE)), "Not Found", VLOOKUP(A39,'Master List'!A:C,3,FALSE))) -> debbiem@sfsu.edu | E39: HDMI > MDP Adapter | F39: =IF(OR(A39="",E39="","",A39="?",E39="?"),"duplicate?",IF(COUNTIFS($A:A,A39,E:E,E39)>1,"yes","no")) -> no | G39: N/A | H39: 45282 | K39: =IF(J39="","Date",IF(J39<>"",IF(K39="Date",NOW(),K39),"")) -> Date
A40: 917242331 | B40: 44823 | C40: =IF(ISBLANK(A40),"Name",IF(ISNA(VLOOKUP(A40,'Master List'!A:C,2,FALSE)), "Not Found", VLOOKUP(A40,'Master List'!A:C,2,FALSE))) -> Ilana Crispi | D40: =IF(ISBLANK(A40), "Email",IF(ISNA(VLOOKUP(A40,'Master List'!A:C,3,FALSE)), "Not Found", VLOOKUP(A40,'Master List'!A:C,3,FALSE))) -> icrispi@sfsu.edu | E40: Headset (Logi H390) | F40: =IF(OR(A40="",E40="","",A40="?",E40="?"),"duplicate?",IF(COUNTIFS($A:A,A40,E:E,E40)>1,"yes","no")) -> no | G40: N/A | H40: 45282 | K40: =IF(J40="","Date",IF(J40<>"",IF(K40="Date",NOW(),K40),"")) -> Date
A41: 917242331 | B41: 44823 | C41: =IF(ISBLANK(A41),"Name",IF(ISNA(VLOOKUP(A41,'Master List'!A:C,2,FALSE)), "Not Found", VLOOKUP(A41,'Master List'!A:C,2,FALSE))) -> Ilana Crispi | D41: =IF(ISBLANK(A41), "Email",IF(ISNA(VLOOKUP(A41,'Master List'!A:C,3,FALSE)), "Not Found", VLOOKUP(A41,'Master List'!A:C,3,FALSE))) -> icrispi@sfsu.edu | E41: Ethernet > USB-C Adapter | F41: =IF(OR(A41="",E41="","",A41="?",E41="?"),"duplicate?",IF(COUNTIFS($A:A,A41,E:E,E41)>1,"yes","no")) -> no | G41: N/A | H41: 45282 | K41: =IF(J41="","Date",IF(J41<>"",IF(K41="Date",NOW(),K41),"")) -> Date
A42: 900003304 | B42: 44823 | C42: =IF(ISBLANK(A42),"Name",IF(ISNA(VLOOKUP(A42,'Master List'!A:C,2,FALSE)), "Not Found", VLOOKUP(A42,'Master List'!A:C,2,FALSE))) -> Raquel Rivera Pinderhughes | D42: =IF(ISBLANK(A42), "Email",IF(ISNA(VLOOKUP(A42,'Master List'!A:C,3,FALSE)), "Not Found", VLOOKUP(A42,'Master List'!A:C,3,FALSE))) -> raquelrp@sfsu.edu | E42: HDMI > USB-C Adapter | F42: =IF(OR(A42="",E42="","",A42="?",E42="?"),"duplicate?",IF(COUNTIFS($A:A,A42,E:E,E42)>1,"yes","no")) -> no | G42: NA | H42: 45282 | K42: =IF(J42="","Date",IF(J42<>"",IF(K42="Date",NOW(),K42),"")) -> Date
A43: 900011962 | B43: 44824 | C43: =IF(ISBLANK(A43),"Name",IF(ISNA(VLOOKUP(A43,'Master List'!A:C,2,FALSE)), "Not Found", VLOOKUP(A43,'Master List'!A:C,2,FALSE))) -> Alexander Schuster | D43: =IF(ISBLANK(A43), "Email",IF(ISNA(VLOOKUP(A43,'Master List'!A:C,3,FALSE)), "Not Found", VLOOKUP(A43,'Master List'!A:C,3,FALSE))) -> schuster@sfsu.edu | E43: HDMI > USB-C Adapter | F43: =IF(OR(A43="",E43="","",A43="?",E43="?"),"duplicate?",IF(COUNTIFS($A:A,A43,E:E,E43)>1,"yes","no")) -> no | G43: NA | H43: 45282 | K43: =IF(J43="","Date",IF(J43<>"",IF(K43="Date",NOW(),K43),"")) -> Date
A44: 917242435 | B44: 44824 | C44: =IF(ISBLANK(A44),"Name",IF(ISNA(VLOOKUP(A44,'Master List'!A:C,2,FALSE)), "Not Found", VLOOKUP(A44,'Master List'!A:C,2,FALSE))) -> Susanna Jones | D44: =IF(ISBLANK(A44), "Email",IF(ISNA(VLOOKUP(A44,'Master List'!A:C,3,FALSE)), "Not Found", VLOOKUP(A44,'Master List'!A:C,3,FALSE))) -> susjones@sfsu.edu | E44: HDMI > USB-C Adapter | F44: =IF(OR(A44="",E44="","",A44="?",E44="?"),"duplicate?",IF(COUNTIFS($A:A,A44,E:E,E44)>1,"yes","no")) -> no | G44: NA | H44: 45282 | K44: =IF(J44="","Date",IF(J44<>"",IF(K44="Date",NOW(),K44),"")) -> Date
A45: 904343380 | B45: 44825 | C45: =IF(ISBLANK(A45),"Name",IF(ISNA(VLOOKUP(A45,'Master List'!A:C,2,FALSE)), "Not Found", VLOOKUP(A45,'Master List'!A:C,2,FALSE))) -> Cynthia Martinez | D45: =IF(ISBLANK(A45), "Email",IF(ISNA(VLOOKUP(A45,'Master List'!A:C,3,FALSE)), "Not Found", VLOOKUP(A45,'Master List'!A:C,3,FALSE))) -> cmartinez42@sfsu.edu | E45: HDMI > USB-C Adapter | F45: =IF(OR(A45="",E45="","",A45="?",E45="?"),"duplicate?",IF(COUNTIFS($A:A,A45,E:E,E45)>1,"yes","no")) -> yes | H45: 45282 | K45: =IF(J45="","Date",IF(J45<>"",IF(K45="Date",NOW(),K45),"")) -> Date
A46: 910600371 | B46: 44830 | C46: =IF(ISBLANK(A46),"Name",IF(ISNA(VLOOKUP(A46,'Master List'!A:C,2,FALSE)), "Not Found", VLOOKUP(A46,'Master List'!A:C,2,FALSE))) -> Charles Postel | D46: =IF(ISBLANK(A46), "Email",IF(ISNA(VLOOKUP(A46,'Master List'!A:C,3,FALSE)), "Not Found", VLOOKUP(A46,'Master List'!A:C,3,FALSE))) -> postel@sfsu.edu | E46: Mac Power Adapter (MagSafe 3) | F46: =IF(OR(A46="",E46="","",A46="?",E46="?"),"duplicate?",IF(COUNTIFS($A:A,A46,E:E,E46)>1,"yes","no")) -> no | H46: 45282 | K46: =IF(J46="","Date",IF(J46<>"",IF(K46="Date",NOW(),K46),"")) -> Date
A47: 910660652 | B47: 44830 | C47: =IF(ISBLANK(A47),"Name",IF(ISNA(VLOOKUP(A47,'Master List'!A:C,2,FALSE)), "Not Found", VLOOKUP(A47,'Master List'!A:C,2,FALSE))) -> Chelsea Mcnutt | D47: =IF(ISBLANK(A47), "Email",IF(ISNA(VLOOKUP(A47,'Master List'!A:C,3,FALSE)), "Not Found", VLOOKUP(A47,'Master List'!A:C,3,FALSE))) -> cmcnutt@sfsu.edu | E47: Headset (Logi H390) | F47: =IF(OR(A47="",E47="","",A47="?",E47="?"),"duplicate?",IF(COUNTIFS($A:A,A47,E:E,E47)>1,"yes","no")) -> no | H47: 45195 | K47: =IF(J47="","Date",IF(J47<>"",IF(K47="Date",NOW(),K47),"")) -> Date
A48: 913032515 | B48: 44830 | C48: =IF(ISBLANK(A48),"Name",IF(ISNA(VLOOKUP(A48,'Master List'!A:C,2,FALSE)), "Not Found", VLOOKUP(A48,'Master List'!A:C,2,FALSE))) -> Marisa Gymson | D48: =IF(ISBLANK(A48), "Email",IF(ISNA(VLOOKUP(A48,'Master List'!A:C,3,FALSE)), "Not Found", VLOOKUP(A48,'Master List'!A:C,3,FALSE))) -> mjimison@sfsu.edu | E48: HDMI > USB-C Adapter | F48: =IF(OR(A48="",E48="","",A48="?",E48="?"),"duplicate?",IF(COUNTIFS($A:A,A48,E:E,E48)>1,"yes","no")) -> no | H48: 45282 | K48: =IF(J48="","Date",IF(J48<>"",IF(K48="Date",NOW(),K48),"")) -> Date
A49: 903505439 | B49: 44830 | C49: =IF(ISBLANK(A49),"Name",IF(ISNA(VLOOKUP(A49,'Master List'!A:C,2,FALSE)), "Not Found", VLOOKUP(A49,'Master List'!A:C,2,FALSE))) -> Omar Kudsi | D49: =IF(ISBLANK(A49), "Email",IF(ISNA(VLOOKUP(A49,'Master List'!A:C,3,FALSE)), "Not Found", VLOOKUP(A49,'Master List'!A:C,3,FALSE))) -> kudsi@sfsu.edu | E49: HDMI Cable | F49: =IF(OR(A49="",E49="","",A49="?",E49="?"),"duplicate?",IF(COUNTIFS($A:A,A49,E:E,E49)>1,"yes","no")) -> no | G49: Hum 279 | H49: 45282 | K49: =IF(J49="","Date",IF(J49<>"",IF(K49="Date",NOW(),K49),"")) -> Date
A50: 904849457 | B50: 44831 | C50: =IF(ISBLANK(A50),"Name",IF(ISNA(VLOOKUP(A50,'Master List'!A:C,2,FALSE)), "Not Found", VLOOKUP(A50,'Master List'!A:C,2,FALSE))) -> aa valdivia | D50: =IF(ISBLANK(A50), "Email",IF(ISNA(VLOOKUP(A50,'Master List'!A:C,3,FALSE)), "Not Found", VLOOKUP(A50,'Master List'!A:C,3,FALSE))) -> aavaldivia@sfsu.edu | E50: HDMI > USB-C Adapter | F50: =IF(OR(A50="",E50="","",A50="?",E50="?"),"duplicate?",IF(COUNTIFS($A:A,A50,E:E,E50)>1,"yes","no")) -> no | H50: 45282 | K50: =IF(J50="","Date",IF(J50<>"",IF(K50="Date",NOW(),K50),"")) -> Date
A51: 918119389 | B51: 44831 | C51: =IF(ISBLANK(A51),"Name",IF(ISNA(VLOOKUP(A51,'Master List'!A:C,2,FALSE)), "Not Found", VLOOKUP(A51,'Master List'!A:C,2,FALSE))) -> Katharine Mahalic | D51: =IF(ISBLANK(A51), "Email",IF(ISNA(VLOOKUP(A51,'Master List'!A:C,3,FALSE)), "Not Found", VLOOKUP(A51,'Master List'!A:C,3,FALSE))) -> kmahalic@sfsu.edu | E51: HDMI > USB-C Adapter | F51: =IF(OR(A51="",E51="","",A51="?",E51="?"),"duplicate?",IF(COUNTIFS($A:A,A51,E:E,E51)>1,"yes","no")) -> yes | H51: 45282 | K51: =IF(J51="","Date",IF(J51<>"",IF(K51="Date",NOW(),K51),"")) -> Date
A52: 908778356 | B52: 44833 | C52: =IF(ISBLANK(A52),"Name",IF(ISNA(VLOOKUP(A52,'Master List'!A:C,2,FALSE)), "Not Found", VLOOKUP(A52,'Master List'!A:C,2,FALSE))) -> Allen Conkle | D52: =IF(ISBLANK(A52), "Email",IF(ISNA(VLOOKUP(A52,'Master List'!A:C,3,FALSE)), "Not Found", VLOOKUP(A52,'Master List'!A:C,3,FALSE))) -> aconkle@sfsu.edu | E52: ? | F52: =IF(OR(A52="",E52="","",A52="?",E52="?"),"duplicate?",IF(COUNTIFS($A:A,A52,E:E,E52)>1,"yes","no")) -> duplicate? | H52: 45282 | K52: =IF(J52="","Date",IF(J52<>"",IF(K52="Date",NOW(),K52),"")) -> Date
A53: 916405287 | B53: 44833 | C53: =IF(ISBLANK(A53),"Name",IF(ISNA(VLOOKUP(A53,'Master List'!A:C,2,FALSE)), "Not Found", VLOOKUP(A53,'Master List'!A:C,2,FALSE))) -> Christopher Wessels | D53: =IF(ISBLANK(A53), "Email",IF(ISNA(VLOOKUP(A53,'Master List'!A:C,3,FALSE)), "Not Found", VLOOKUP(A53,'Master List'!A:C,3,FALSE))) -> cwessels@sfsu.edu | E53: HDMI > USB-C Adapter | F53: =IF(OR(A53="",E53="","",A53="?",E53="?"),"duplicate?",IF(COUNTIFS($A:A,A53,E:E,E53)>1,"yes","no")) -> no | H53: 45282 | K53: =IF(J53="","Date",IF(J53<>"",IF(K53="Date",NOW(),K53),"")) -> Date
A54: 917924870 | B54: 44833 | C54: =IF(ISBLANK(A54),"Name",IF(ISNA(VLOOKUP(A54,'Master List'!A:C,2,FALSE)), "Not Found", VLOOKUP(A54,'Master List'!A:C,2,FALSE))) -> Teresa Pratt | D54: =IF(ISBLANK(A54), "Email",IF(ISNA(VLOOKUP(A54,'Master List'!A:C,3,FALSE)), "Not Found", VLOOKUP(A54,'Master List'!A:C,3,FALSE))) -> tpratt@sfsu.edu | E54: HDMI > USB-C Adapter | F54: =IF(OR(A54="",E54="","",A54="?",E54="?"),"duplicate?",IF(COUNTIFS($A:A,A54,E:E,E54)>1,"yes","no")) -> yes | H54: 45282 | K54: =IF(J54="","Date",IF(J54<>"",IF(K54="Date",NOW(),K54),"")) -> Date
A55: 909169370 | B55: 44833 | C55: =IF(ISBLANK(A55),"Name",IF(ISNA(VLOOKUP(A55,'Master List'!A:C,2,FALSE)), "Not Found", VLOOKUP(A55,'Master List'!A:C,2,FALSE))) -> Veronika Papyrina | D55: =IF(ISBLANK(A55), "Email",IF(ISNA(VLOOKUP(A55,'Master List'!A:C,3,FALSE)), "Not Found", VLOOKUP(A55,'Master List'!A:C,3,FALSE))) -> papyrina@sfsu.edu | E55: Blu-ray/DVD Player | F55: =IF(OR(A55="",E55="","",A55="?",E55="?"),"duplicate?",IF(COUNTIFS($A:A,A55,E:E,E55)>1,"yes","no")) -> no | H55: 44838 | K55: =IF(J55="","Date",IF(J55<>"",IF(K55="Date",NOW(),K55),"")) -> Date
A56: 900049597 | B56: 44837 | C56: =IF(ISBLANK(A56),"Name",IF(ISNA(VLOOKUP(A56,'Master List'!A:C,2,FALSE)), "Not Found", VLOOKUP(A56,'Master List'!A:C,2,FALSE))) -> Burcu Ellis | D56: =IF(ISBLANK(A56), "Email",IF(ISNA(VLOOKUP(A56,'Master List'!A:C,3,FALSE)), "Not Found", VLOOKUP(A56,'Master List'!A:C,3,FALSE))) -> bellis@sfsu.edu | E56: Webcam (Logi C920s) | F56: =IF(OR(A56="",E56="","",A56="?",E56="?"),"duplicate?",IF(COUNTIFS($A:A,A56,E:E,E56)>1,"yes","no")) -> no | H56: 45282 | K56: =IF(J56="","Date",IF(J56<>"",IF(K56="Date",NOW(),K56),"")) -> Date
A57: 911215765 | B57: 44837 | C57: =IF(ISBLANK(A57),"Name",IF(ISNA(VLOOKUP(A57,'Master List'!A:C,2,FALSE)), "Not Found", VLOOKUP(A57,'Master List'!A:C,2,FALSE))) -> Mays Danfoura | D57: =IF(ISBLANK(A57), "Email",IF(ISNA(VLOOKUP(A57,'Master List'!A:C,3,FALSE)), "Not Found", VLOOKUP(A57,'Master List'!A:C,3,FALSE))) -> mdanfura@sfsu.edu | E57: HDMI > USB-C Adapter | F57: =IF(OR(A57="",E57="","",A57="?",E57="?"),"duplicate?",IF(COUNTIFS($A:A,A57,E:E,E57)>1,"yes","no")) -> no | H57: 45282 | K57: =IF(J57="","Date",IF(J57<>"",IF(K57="Date",NOW(),K57),"")) -> Date
A58: 918831256 | B58: 44837 | C58: =IF(ISBLANK(A58),"Name",IF(ISNA(VLOOKUP(A58,'Master List'!A:C,2,FALSE)), "Not Found", VLOOKUP(A58,'Master List'!A:C,2,FALSE))) -> Michelle Toney | D58: =IF(ISBLANK(A58), "Email",IF(ISNA(VLOOKUP(A58,'Master List'!A:C,3,FALSE)), "Not Found", VLOOKUP(A58,'Master List'!A:C,3,FALSE))) -> mstoney@sfsu.edu | E58: Mac Power Adapter (USB-C) | F58: =IF(OR(A58="",E58="","",A58="?",E58="?"),"duplicate?",IF(COUNTIFS($A:A,A58,E:E,E58)>1,"yes","no")) -> no | H58: 45282 | K58: =IF(J58="","Date",IF(J58<>"",IF(K58="Date",NOW(),K58),"")) -> Date
A59: 903505439 | B59: 44837 | C59: =IF(ISBLANK(A59),"Name",IF(ISNA(VLOOKUP(A59,'Master List'!A:C,2,FALSE)), "Not Found", VLOOKUP(A59,'Master List'!A:C,2,FALSE))) -> Omar Kudsi | D59: =IF(ISBLANK(A59), "Email",IF(ISNA(VLOOKUP(A59,'Master List'!A:C,3,FALSE)), "Not Found", VLOOKUP(A59,'Master List'!A:C,3,FALSE))) -> kudsi@sfsu.edu | E59: HDMI > USB-C Adapter | F59: =IF(OR(A59="",E59="","",A59="?",E59="?"),"duplicate?",IF(COUNTIFS($A:A,A59,E:E,E59)>1,"yes","no")) -> no | H59: 45282 | K59: =IF(J59="","Date",IF(J59<>"",IF(K59="Date",NOW(),K59),"")) -> Date
A60: 918825406 | B60: 44838 | C60: =IF(ISBLANK(A60),"Name",IF(ISNA(VLOOKUP(A60,'Master List'!A:C,2,FALSE)), "Not Found", VLOOKUP(A60,'Master List'!A:C,2,FALSE))) -> Chenghao Hu | D60: =IF(ISBLANK(A60), "Email",IF(ISNA(VLOOKUP(A60,'Master List'!A:C,3,FALSE)), "Not Found", VLOOKUP(A60,'Master List'!A:C,3,FALSE))) -> chhu@sfsu.edu | E60: Mac Power Adapter (USB-C) | F60: =IF(OR(A60="",E60="","",A60="?",E60="?"),"duplicate?",IF(COUNTIFS($A:A,A60,E:E,E60)>1,"yes","no")) -> no | H60: 45282 | K60: =IF(J60="","Date",IF(J60<>"",IF(K60="Date",NOW(),K60),"")) -> Date
A61: 900021790 | B61: 44844 | C61: =IF(ISBLANK(A61),"Name",IF(ISNA(VLOOKUP(A61,'Master List'!A:C,2,FALSE)), "Not Found", VLOOKUP(A61,'Master List'!A:C,2,FALSE))) -> Christine Manuguid | D61: =IF(ISBLANK(A61), "Email",IF(ISNA(VLOOKUP(A61,'Master List'!A:C,3,FALSE)), "Not Found", VLOOKUP(A61,'Master List'!A:C,3,FALSE))) -> cmanu@sfsu.edu | E61: Webcam (Logi C920s) | F61: =IF(OR(A61="",E61="","",A61="?",E61="?"),"duplicate?",IF(COUNTIFS($A:A,A61,E:E,E61)>1,"yes","no")) -> no | H61: 45282 | K61: =IF(J61="","Date",IF(J61<>"",IF(K61="Date",NOW(),K61),"")) -> Date
... A73: 908492096 | B73: 44852 | C73: =IF(ISBLANK(A73),"Name",IF(ISNA(VLOOKUP(A73,'Master List'!A:C,2,FALSE)), "Not Found", VLOOKUP(A73,'Master List'!A:C,2,FALSE))) -> Alexandra Piryatinska | D73: =IF(ISBLANK(A73), "Email",IF(ISNA(VLOOKUP(A73,'Master List'!A:C,3,FALSE)), "Not Found", VLOOKUP(A73,'Master List'!A:C,3,FALSE))) -> alpiryat@sfsu.edu | E73: Mac Power Adapter (USB-C) | F73: =IF(OR(A73="",E73="","",A73="?",E73="?"),"duplicate?",IF(COUNTIFS($A:A,A73,E:E,E73)>1,"yes","no")) -> no | H73: 44854 | K73: =IF(J73="","Date",IF(J73<>"",IF(K73="Date",NOW(),K73),"")) -> Date
A74: 900987456 | B74: 44852 | C74: =IF(ISBLANK(A74),"Name",IF(ISNA(VLOOKUP(A74,'Master List'!A:C,2,FALSE)), "Not Found", VLOOKUP(A74,'Master List'!A:C,2,FALSE))) -> Christopher Chekuri | D74: =IF(ISBLANK(A74), "Email",IF(ISNA(VLOOKUP(A74,'Master List'!A:C,3,FALSE)), "Not Found", VLOOKUP(A74,'Master List'!A:C,3,FALSE))) -> cchekuri@sfsu.edu | E74: Mac Power Adapter (USB-C) | F74: =IF(OR(A74="",E74="","",A74="?",E74="?"),"duplicate?",IF(COUNTIFS($A:A,A74,E:E,E74)>1,"yes","no")) -> no | H74: 12/22/23? | K74: =IF(J74="","Date",IF(J74<>"",IF(K74="Date",NOW(),K74),"")) -> Date
A75: 913444134 | B75: 44852 | C75: =IF(ISBLANK(A75),"Name",IF(ISNA(VLOOKUP(A75,'Master List'!A:C,2,FALSE)), "Not Found", VLOOKUP(A75,'Master List'!A:C,2,FALSE))) -> Gary Straub | D75: =IF(ISBLANK(A75), "Email",IF(ISNA(VLOOKUP(A75,'Master List'!A:C,3,FALSE)), "Not Found", VLOOKUP(A75,'Master List'!A:C,3,FALSE))) -> gstraub@sfsu.edu | E75: Camcorder (DJI Pocket 2) | F75: =IF(OR(A75="",E75="","",A75="?",E75="?"),"duplicate?",IF(COUNTIFS($A:A,A75,E:E,E75)>1,"yes","no")) -> no | H75: 45282 | I75: Cristian | K75: =IF(J75="","Date",IF(J75<>"",IF(K75="Date",NOW(),K75),"")) -> Date | L75: email sent 1/20/23; 12/20/23;
A76: 917243813 | B76: 44852 | C76: =IF(ISBLANK(A76),"Name",IF(ISNA(VLOOKUP(A76,'Master List'!A:C,2,FALSE)), "Not Found", VLOOKUP(A76,'Master List'!A:C,2,FALSE))) -> Kimbrough Moore | D76: =IF(ISBLANK(A76), "Email",IF(ISNA(VLOOKUP(A76,'Master List'!A:C,3,FALSE)), "Not Found", VLOOKUP(A76,'Master List'!A:C,3,FALSE))) -> amoore8@sfsu.edu | E76: HDMI > USB-C Adapter | F76: =IF(OR(A76="",E76="","",A76="?",E76="?"),"duplicate?",IF(COUNTIFS($A:A,A76,E:E,E76)>1,"yes","no")) -> yes | H76: 45282 | K76: =IF(J76="","Date",IF(J76<>"",IF(K76="Date",NOW(),K76),"")) -> Date
A77: 921873560 | B77: 44852 | C77: =IF(ISBLANK(A77),"Name",IF(ISNA(VLOOKUP(A77,'Master List'!A:C,2,FALSE)), "Not Found", VLOOKUP(A77,'Master List'!A:C,2,FALSE))) -> Luis Ybarra | D77: =IF(ISBLANK(A77), "Email",IF(ISNA(VLOOKUP(A77,'Master List'!A:C,3,FALSE)), "Not Found", VLOOKUP(A77,'Master List'!A:C,3,FALSE))) -> lybarra@mail.sfsu.edu | E77: HDMI > USB-C Adapter | F77: =IF(OR(A77="",E77="","",A77="?",E77="?"),"duplicate?",IF(COUNTIFS($A:A,A77,E:E,E77)>1,"yes","no")) -> yes | H77: 45282 | K77: =IF(J77="","Date",IF(J77<>"",IF(K77="Date",NOW(),K77),"")) -> Date
A78: 901528763 | B78: 44852 | C78: =IF(ISBLANK(A78),"Name",IF(ISNA(VLOOKUP(A78,'Master List'!A:C,2,FALSE)), "Not Found", VLOOKUP(A78,'Master List'!A:C,2,FALSE))) -> Nico Peck | D78: =IF(ISBLANK(A78), "Email",IF(ISNA(VLOOKUP(A78,'Master List'!A:C,3,FALSE)), "Not Found", VLOOKUP(A78,'Master List'!A:C,3,FALSE))) -> nicopeck@sfsu.edu | E78: HDMI > USB-C Adapter | F78: =IF(OR(A78="",E78="","",A78="?",E78="?"),"duplicate?",IF(COUNTIFS($A:A,A78,E:E,E78)>1,"yes","no")) -> no | H78: 45282 | K78: =IF(J78="","Date",IF(J78<>"",IF(K78="Date",NOW(),K78),"")) -> Date
A79: 909169188 | B79: 44852 | C79: =IF(ISBLANK(A79),"Name",IF(ISNA(VLOOKUP(A79,'Master List'!A:C,2,FALSE)), "Not Found", VLOOKUP(A79,'Master List'!A:C,2,FALSE))) -> Ryan Howell | D79: =IF(ISBLANK(A79), "Email",IF(ISNA(VLOOKUP(A79,'Master List'!A:C,3,FALSE)), "Not Found", VLOOKUP(A79,'Master List'!A:C,3,FALSE))) -> rhowell@sfsu.edu | E79: HDMI > USB-C Adapter | F79: =IF(OR(A79="",E79="","",A79="?",E79="?"),"duplicate?",IF(COUNTIFS($A:A,A79,E:E,E79)>1,"yes","no")) -> no | H79: 45282 | K79: =IF(J79="","Date",IF(J79<>"",IF(K79="Date",NOW(),K79),"")) -> Date
A80: 911369841 | B80: 44853 | C80: =IF(ISBLANK(A80),"Name",IF(ISNA(VLOOKUP(A80,'Master List'!A:C,2,FALSE)), "Not Found", VLOOKUP(A80,'Master List'!A:C,2,FALSE))) -> Aiko Yoshino | D80: =IF(ISBLANK(A80), "Email",IF(ISNA(VLOOKUP(A80,'Master List'!A:C,3,FALSE)), "Not Found", VLOOKUP(A80,'Master List'!A:C,3,FALSE))) -> ayoshino@sfsu.edu | E80: HDMI > USB-C Adapter | F80: =IF(OR(A80="",E80="","",A80="?",E80="?"),"duplicate?",IF(COUNTIFS($A:A,A80,E:E,E80)>1,"yes","no")) -> yes | H80: 45282 | K80: =IF(J80="","Date",IF(J80<>"",IF(K80="Date",NOW(),K80),"")) -> Date
A81: 906495374 | B81: 44859 | C81: =IF(ISBLANK(A81),"Name",IF(ISNA(VLOOKUP(A81,'Master List'!A:C,2,FALSE)), "Not Found", VLOOKUP(A81,'Master List'!A:C,2,FALSE))) -> Felicia Viator | D81: =IF(ISBLANK(A81), "Email",IF(ISNA(VLOOKUP(A81,'Master List'!A:C,3,FALSE)), "Not Found", VLOOKUP(A81,'Master List'!A:C,3,FALSE))) -> fviator@sfsu.edu | E81: VGA > HDMI Adapter Adapter | F81: =IF(OR(A81="",E81="","",A81="?",E81="?"),"duplicate?",IF(COUNTIFS($A:A,A81,E:E,E81)>1,"yes","no")) -> no | H81: 44859 | K81: =IF(J81="","Date",IF(J81<>"",IF(K81="Date",NOW(),K81),"")) -> Date
A82: 912361195 | B82: 44859 | C82: =IF(ISBLANK(A82),"Name",IF(ISNA(VLOOKUP(A82,'Master List'!A:C,2,FALSE)), "Not Found", VLOOKUP(A82,'Master List'!A:C,2,FALSE))) -> Joanna Englehardt | D82: =IF(ISBLANK(A82), "Email",IF(ISNA(VLOOKUP(A82,'Master List'!A:C,3,FALSE)), "Not Found", VLOOKUP(A82,'Master List'!A:C,3,FALSE))) -> joannae@sfsu.edu | E82: HDMI > USB-C Adapter | F82: =IF(OR(A82="",E82="","",A82="?",E82="?"),"duplicate?",IF(COUNTIFS($A:A,A82,E:E,E82)>1,"yes","no")) -> no | H82: 45282 | K82: =IF(J82="","Date",IF(J82<>"",IF(K82="Date",NOW(),K82),"")) -> Date
A83: 912361195 | B83: 44859 | C83: =IF(ISBLANK(A83),"Name",IF(ISNA(VLOOKUP(A83,'Master List'!A:C,2,FALSE)), "Not Found", VLOOKUP(A83,'Master List'!A:C,2,FALSE))) -> Joanna Englehardt | D83: =IF(ISBLANK(A83), "Email",IF(ISNA(VLOOKUP(A83,'Master List'!A:C,3,FALSE)), "Not Found", VLOOKUP(A83,'Master List'!A:C,3,FALSE))) -> joannae@sfsu.edu | E83: VGA > USB-C Adapter Adapter | F83: =IF(OR(A83="",E83="","",A83="?",E83="?"),"duplicate?",IF(COUNTIFS($A:A,A83,E:E,E83)>1,"yes","no")) -> no | H83: 45282 | K83: =IF(J83="","Date",IF(J83<>"",IF(K83="Date",NOW(),K83),"")) -> Date
A84: 900058281 | B84: 44860 | C84: =IF(ISBLANK(A84),"Name",IF(ISNA(VLOOKUP(A84,'Master List'!A:C,2,FALSE)), "Not Found", VLOOKUP(A84,'Master List'!A:C,2,FALSE))) -> Kevin Conner | D84: =IF(ISBLANK(A84), "Email",IF(ISNA(VLOOKUP(A84,'Master List'!A:C,3,FALSE)), "Not Found", VLOOKUP(A84,'Master List'!A:C,3,FALSE))) -> kevin@sfsu.edu | E84: Ring Light - Small | F84: =IF(OR(A84="",E84="","",A84="?",E84="?"),"duplicate?",IF(COUNTIFS($A:A,A84,E:E,E84)>1,"yes","no")) -> no | H84: 45282 | K84: =IF(J84="","Date",IF(J84<>"",IF(K84="Date",NOW(),K84),"")) -> Date
A85: 908379035 | B85: 44860 | C85: =IF(ISBLANK(A85),"Name",IF(ISNA(VLOOKUP(A85,'Master List'!A:C,2,FALSE)), "Not Found", VLOOKUP(A85,'Master List'!A:C,2,FALSE))) -> Soumyaa Behrens | D85: =IF(ISBLANK(A85), "Email",IF(ISNA(VLOOKUP(A85,'Master List'!A:C,3,FALSE)), "Not Found", VLOOKUP(A85,'Master List'!A:C,3,FALSE))) -> soumyaa@sfsu.edu | E85: Extension Cord Power Outlet | F85: =IF(OR(A85="",E85="","",A85="?",E85="?"),"duplicate?",IF(COUNTIFS($A:A,A85,E:E,E85)>1,"yes","no")) -> no | H85: 44860 | K85: =IF(J85="","Date",IF(J85<>"",IF(K85="Date",NOW(),K85),"")) -> Date
A86: 913477401 | B86: 44861 | C86: =IF(ISBLANK(A86),"Name",IF(ISNA(VLOOKUP(A86,'Master List'!A:C,2,FALSE)), "Not Found", VLOOKUP(A86,'Master List'!A:C,2,FALSE))) -> Manav Thapar | D86: =IF(ISBLANK(A86), "Email",IF(ISNA(VLOOKUP(A86,'Master List'!A:C,3,FALSE)), "Not Found", VLOOKUP(A86,'Master List'!A:C,3,FALSE))) -> mthapar@sfsu.edu | E86: HDMI > USB-C Adapter | F86: =IF(OR(A86="",E86="","",A86="?",E86="?"),"duplicate?",IF(COUNTIFS($A:A,A86,E:E,E86)>1,"yes","no")) -> no | H86: 45282 | K86: =IF(J86="","Date",IF(J86<>"",IF(K86="Date",NOW(),K86),"")) -> Date
A87: 909004140 | B87: 44861 | C87: =IF(ISBLANK(A87),"Name",IF(ISNA(VLOOKUP(A87,'Master List'!A:C,2,FALSE)), "Not Found", VLOOKUP(A87,'Master List'!A:C,2,FALSE))) -> Ryan Gurney | D87: =IF(ISBLANK(A87), "Email",IF(ISNA(VLOOKUP(A87,'Master List'!A:C,3,FALSE)), "Not Found", VLOOKUP(A87,'Master List'!A:C,3,FALSE))) -> rgurney@sfsu.edu | E87: PA - Small | F87: =IF(OR(A87="",E87="","",A87="?",E87="?"),"duplicate?",IF(COUNTIFS($A:A,A87,E:E,E87)>1,"yes","no")) -> no | H87: 44861 | K87: =IF(J87="","Date",IF(J87<>"",IF(K87="Date",NOW(),K87),"")) -> Date
... A104: 911407775 | B104: 44872 | C104: =IF(ISBLANK(A104),"Name",IF(ISNA(VLOOKUP(A104,'Master List'!A:C,2,FALSE)), "Not Found", VLOOKUP(A104,'Master List'!A:C,2,FALSE))) -> Deborah Farris | D104: =IF(ISBLANK(A104), "Email",IF(ISNA(VLOOKUP(A104,'Master List'!A:C,3,FALSE)), "Not Found", VLOOKUP(A104,'Master List'!A:C,3,FALSE))) -> dfarris@mail.sfsu.edu | E104: HDMI > USB-C Adapter | F104: =IF(OR(A104="",E104="","",A104="?",E104="?"),"duplicate?",IF(COUNTIFS($A:A,A104,E:E,E104)>1,"yes","no")) -> no | H104: 45282 | K104: =IF(J104="","Date",IF(J104<>"",IF(K104="Date",NOW(),K104),"")) -> Date
A105: 918845608 | B105: 44874 | C105: =IF(ISBLANK(A105),"Name",IF(ISNA(VLOOKUP(A105,'Master List'!A:C,2,FALSE)), "Not Found", VLOOKUP(A105,'Master List'!A:C,2,FALSE))) -> Angela Fillingim | D105: =IF(ISBLANK(A105), "Email",IF(ISNA(VLOOKUP(A105,'Master List'!A:C,3,FALSE)), "Not Found", VLOOKUP(A105,'Master List'!A:C,3,FALSE))) -> afillingim@sfsu.edu | E105: Mouse (PC) | F105: =IF(OR(A105="",E105="","",A105="?",E105="?"),"duplicate?",IF(COUNTIFS($A:A,A105,E:E,E105)>1,"yes","no")) -> no | H105: 45282 | I105: Desktop | K105: =IF(J105="","Date",IF(J105<>"",IF(K105="Date",NOW(),K105),"")) -> Date
A106: 913683958 | B106: 44874 | C106: =IF(ISBLANK(A106),"Name",IF(ISNA(VLOOKUP(A106,'Master List'!A:C,2,FALSE)), "Not Found", VLOOKUP(A106,'Master List'!A:C,2,FALSE))) -> Andrea Crapanzano | D106: =IF(ISBLANK(A106), "Email",IF(ISNA(VLOOKUP(A106,'Master List'!A:C,3,FALSE)), "Not Found", VLOOKUP(A106,'Master List'!A:C,3,FALSE))) -> acrapanzano@sfsu.edu | E106: VGA > USB-C Adapter Adapter | F106: =IF(OR(A106="",E106="","",A106="?",E106="?"),"duplicate?",IF(COUNTIFS($A:A,A106,E:E,E106)>1,"yes","no")) -> no | H106: 45282 | I106: Desktop | K106: =IF(J106="","Date",IF(J106<>"",IF(K106="Date",NOW(),K106),"")) -> Date
A107: 918845608 | B107: 44874 | C107: =IF(ISBLANK(A107),"Name",IF(ISNA(VLOOKUP(A107,'Master List'!A:C,2,FALSE)), "Not Found", VLOOKUP(A107,'Master List'!A:C,2,FALSE))) -> Angela Fillingim | D107: =IF(ISBLANK(A107), "Email",IF(ISNA(VLOOKUP(A107,'Master List'!A:C,3,FALSE)), "Not Found", VLOOKUP(A107,'Master List'!A:C,3,FALSE))) -> afillingim@sfsu.edu | E107: VGA > USB-C Adapter Adapter | F107: =IF(OR(A107="",E107="","",A107="?",E107="?"),"duplicate?",IF(COUNTIFS($A:A,A107,E:E,E107)>1,"yes","no")) -> no | H107: 45282 | I107: Desktop | K107: =IF(J107="","Date",IF(J107<>"",IF(K107="Date",NOW(),K107),"")) -> Date
A108: 912991357 | B108: 44874 | C108: =IF(ISBLANK(A108),"Name",IF(ISNA(VLOOKUP(A108,'Master List'!A:C,2,FALSE)), "Not Found", VLOOKUP(A108,'Master List'!A:C,2,FALSE))) -> Anne Linton | D108: =IF(ISBLANK(A108), "Email",IF(ISNA(VLOOKUP(A108,'Master List'!A:C,3,FALSE)), "Not Found", VLOOKUP(A108,'Master List'!A:C,3,FALSE))) -> aelinton@sfsu.edu | E108: Multiport adapter (USB-C hub) (USB-C hub) | F108: =IF(OR(A108="",E108="","",A108="?",E108="?"),"duplicate?",IF(COUNTIFS($A:A,A108,E:E,E108)>1,"yes","no")) -> no | H108: 45282 | I108: Desktop | K108: =IF(J108="","Date",IF(J108<>"",IF(K108="Date",NOW(),K108),"")) -> Date
A109: 909024589 | B109: 44874 | C109: =IF(ISBLANK(A109),"Name",IF(ISNA(VLOOKUP(A109,'Master List'!A:C,2,FALSE)), "Not Found", VLOOKUP(A109,'Master List'!A:C,2,FALSE))) -> B ferns | D109: =IF(ISBLANK(A109), "Email",IF(ISNA(VLOOKUP(A109,'Master List'!A:C,3,FALSE)), "Not Found", VLOOKUP(A109,'Master List'!A:C,3,FALSE))) -> fern.bryan@gmail.com | E109: HDMI > USB-C Adapter | F109: =IF(OR(A109="",E109="","",A109="?",E109="?"),"duplicate?",IF(COUNTIFS($A:A,A109,E:E,E109)>1,"yes","no")) -> yes | H109: 45282 | I109: Desktop | K109: =IF(J109="","Date",IF(J109<>"",IF(K109="Date",NOW(),K109),"")) -> Date
A110: 909024589 | B110: 44874 | C110: =IF(ISBLANK(A110),"Name",IF(ISNA(VLOOKUP(A110,'Master List'!A:C,2,FALSE)), "Not Found", VLOOKUP(A110,'Master List'!A:C,2,FALSE))) -> B ferns | D110: =IF(ISBLANK(A110), "Email",IF(ISNA(VLOOKUP(A110,'Master List'!A:C,3,FALSE)), "Not Found", VLOOKUP(A110,'Master List'!A:C,3,FALSE))) -> fern.bryan@gmail.com | E110: HDMI > USB-C Adapter | F110: =IF(OR(A110="",E110="","",A110="?",E110="?"),"duplicate?",IF(COUNTIFS($A:A,A110,E:E,E110)>1,"yes","no")) -> yes | H110: 45282 | K110: =IF(J110="","Date",IF(J110<>"",IF(K110="Date",NOW(),K110),"")) -> Date
A111: 917316938 | B111: 44874 | C111: =IF(ISBLANK(A111),"Name",IF(ISNA(VLOOKUP(A111,'Master List'!A:C,2,FALSE)), "Not Found", VLOOKUP(A111,'Master List'!A:C,2,FALSE))) -> Brian Vu | D111: =IF(ISBLANK(A111), "Email",IF(ISNA(VLOOKUP(A111,'Master List'!A:C,3,FALSE)), "Not Found", VLOOKUP(A111,'Master List'!A:C,3,FALSE))) -> brianvu@sfsu.edu | E111: Webcam (Logi C920s) | F111: =IF(OR(A111="",E111="","",A111="?",E111="?"),"duplicate?",IF(COUNTIFS($A:A,A111,E:E,E111)>1,"yes","no")) -> no | H111: 45282 | I111: Desktop | K111: =IF(J111="","Date",IF(J111<>"",IF(K111="Date",NOW(),K111),"")) -> Date
A112: 918836274 | B112: 44874 | C112: =IF(ISBLANK(A112),"Name",IF(ISNA(VLOOKUP(A112,'Master List'!A:C,2,FALSE)), "Not Found", VLOOKUP(A112,'Master List'!A:C,2,FALSE))) -> Caroline Casper | D112: =IF(ISBLANK(A112), "Email",IF(ISNA(VLOOKUP(A112,'Master List'!A:C,3,FALSE)), "Not Found", VLOOKUP(A112,'Master List'!A:C,3,FALSE))) -> ccasper@sfsu.edu | E112: HDMI > USB-C Adapter | F112: =IF(OR(A112="",E112="","",A112="?",E112="?"),"duplicate?",IF(COUNTIFS($A:A,A112,E:E,E112)>1,"yes","no")) -> yes | H112: 45282 | I112: Desktop | K112: =IF(J112="","Date",IF(J112<>"",IF(K112="Date",NOW(),K112),"")) -> Date
A113: 921389102 | B113: 44874 | C113: =IF(ISBLANK(A113),"Name",IF(ISNA(VLOOKUP(A113,'Master List'!A:C,2,FALSE)), "Not Found", VLOOKUP(A113,'Master List'!A:C,2,FALSE))) -> Christine Vargas | D113: =IF(ISBLANK(A113), "Email",IF(ISNA(VLOOKUP(A113,'Master List'!A:C,3,FALSE)), "Not Found", VLOOKUP(A113,'Master List'!A:C,3,FALSE))) -> christinemariev98@gmail.com | E113: Webcam (Logi C920s) | F113: =IF(OR(A113="",E113="","",A113="?",E113="?"),"duplicate?",IF(COUNTIFS($A:A,A113,E:E,E113)>1,"yes","no")) -> no | H113: 45282 | I113: Desktop | K113: =IF(J113="","Date",IF(J113<>"",IF(K113="Date",NOW(),K113),"")) -> Date
A114: 900029746 | B114: 44874 | C114: =IF(ISBLANK(A114),"Name",IF(ISNA(VLOOKUP(A114,'Master List'!A:C,2,FALSE)), "Not Found", VLOOKUP(A114,'Master List'!A:C,2,FALSE))) -> Diana Rumjahn | D114: =IF(ISBLANK(A114), "Email",IF(ISNA(VLOOKUP(A114,'Master List'!A:C,3,FALSE)), "Not Found", VLOOKUP(A114,'Master List'!A:C,3,FALSE))) -> drumjahn@sfsu.edu | E114: HDMI > USB-C Adapter | F114: =IF(OR(A114="",E114="","",A114="?",E114="?"),"duplicate?",IF(COUNTIFS($A:A,A114,E:E,E114)>1,"yes","no")) -> yes | H114: 45282 | K114: =IF(J114="","Date",IF(J114<>"",IF(K114="Date",NOW(),K114),"")) -> Date
A115: 900029746 | B115: 44874 | C115: =IF(ISBLANK(A115),"Name",IF(ISNA(VLOOKUP(A115,'Master List'!A:C,2,FALSE)), "Not Found", VLOOKUP(A115,'Master List'!A:C,2,FALSE))) -> Diana Rumjahn | D115: =IF(ISBLANK(A115), "Email",IF(ISNA(VLOOKUP(A115,'Master List'!A:C,3,FALSE)), "Not Found", VLOOKUP(A115,'Master List'!A:C,3,FALSE))) -> drumjahn@sfsu.edu | E115: VGA > HDMI Adapter Adapter | F115: =IF(OR(A115="",E115="","",A115="?",E115="?"),"duplicate?",IF(COUNTIFS($A:A,A115,E:E,E115)>1,"yes","no")) -> yes | H115: 45282 | K115: =IF(J115="","Date",IF(J115<>"",IF(K115="Date",NOW(),K115),"")) -> Date
A116: 900029746 | B116: 44874 | C116: =IF(ISBLANK(A116),"Name",IF(ISNA(VLOOKUP(A116,'Master List'!A:C,2,FALSE)), "Not Found", VLOOKUP(A116,'Master List'!A:C,2,FALSE))) -> Diana Rumjahn | D116: =IF(ISBLANK(A116), "Email",IF(ISNA(VLOOKUP(A116,'Master List'!A:C,3,FALSE)), "Not Found", VLOOKUP(A116,'Master List'!A:C,3,FALSE))) -> drumjahn@sfsu.edu | E116: VGA > HDMI Adapter Adapter | F116: =IF(OR(A116="",E116="","",A116="?",E116="?"),"duplicate?",IF(COUNTIFS($A:A,A116,E:E,E116)>1,"yes","no")) -> yes | H116: 45282 | K116: =IF(J116="","Date",IF(J116<>"",IF(K116="Date",NOW(),K116),"")) -> Date
A117: 900029746 | B117: 44874 | C117: =IF(ISBLANK(A117),"Name",IF(ISNA(VLOOKUP(A117,'Master List'!A:C,2,FALSE)), "Not Found", VLOOKUP(A117,'Master List'!A:C,2,FALSE))) -> Diana Rumjahn | D117: =IF(ISBLANK(A117), "Email",IF(ISNA(VLOOKUP(A117,'Master List'!A:C,3,FALSE)), "Not Found", VLOOKUP(A117,'Master List'!A:C,3,FALSE))) -> drumjahn@sfsu.edu | E117: HDMI > USB-C Adapter | F117: =IF(OR(A117="",E117="","",A117="?",E117="?"),"duplicate?",IF(COUNTIFS($A:A,A117,E:E,E117)>1,"yes","no")) -> yes | H117: 45282 | K117: =IF(J117="","Date",IF(J117<>"",IF(K117="Date",NOW(),K117),"")) -> Date
A118: 900029746 | B118: 44874 | C118: =IF(ISBLANK(A118),"Name",IF(ISNA(VLOOKUP(A118,'Master List'!A:C,2,FALSE)), "Not Found", VLOOKUP(A118,'Master List'!A:C,2,FALSE))) -> Diana Rumjahn | D118: =IF(ISBLANK(A118), "Email",IF(ISNA(VLOOKUP(A118,'Master List'!A:C,3,FALSE)), "Not Found", VLOOKUP(A118,'Master List'!A:C,3,FALSE))) -> drumjahn@sfsu.edu | E118: HDMI > USB-C Adapter | F118: =IF(OR(A118="",E118="","",A118="?",E118="?"),"duplicate?",IF(COUNTIFS($A:A,A118,E:E,E118)>1,"yes","no")) -> yes | H118: 45282 | K118: =IF(J118="","Date",IF(J118<>"",IF(K118="Date",NOW(),K118),"")) -> Date
A119: 900029746 | B119: 44874 | C119: =IF(ISBLANK(A119),"Name",IF(ISNA(VLOOKUP(A119,'Master List'!A:C,2,FALSE)), "Not Found", VLOOKUP(A119,'Master List'!A:C,2,FALSE))) -> Diana Rumjahn | D119: =IF(ISBLANK(A119), "Email",IF(ISNA(VLOOKUP(A119,'Master List'!A:C,3,FALSE)), "Not Found", VLOOKUP(A119,'Master List'!A:C,3,FALSE))) -> drumjahn@sfsu.edu | E119: HDMI > USB-C Adapter | F119: =IF(OR(A119="",E119="","",A119="?",E119="?"),"duplicate?",IF(COUNTIFS($A:A,A119,E:E,E119)>1,"yes","no")) -> yes | H119: 45282 | K119: =IF(J119="","Date",IF(J119<>"",IF(K119="Date",NOW(),K119),"")) -> Date
A120: 900029746 | B120: 44874 | C120: =IF(ISBLANK(A120),"Name",IF(ISNA(VLOOKUP(A120,'Master List'!A:C,2,FALSE)), "Not Found", VLOOKUP(A120,'Master List'!A:C,2,FALSE))) -> Diana Rumjahn | D120: =IF(ISBLANK(A120), "Email",IF(ISNA(VLOOKUP(A120,'Master List'!A:C,3,FALSE)), "Not Found", VLOOKUP(A120,'Master List'!A:C,3,FALSE))) -> drumjahn@sfsu.edu | E120: HDMI > USB-C Adapter | F120: =IF(OR(A120="",E120="","",A120="?",E120="?"),"duplicate?",IF(COUNTIFS($A:A,A120,E:E,E120)>1,"yes","no")) -> yes | H120: 45282 | K120: =IF(J120="","Date",IF(J120<>"",IF(K120="Date",NOW(),K120),"")) -> Date
A121: 900029746 | B121: 44874 | C121: =IF(ISBLANK(A121),"Name",IF(ISNA(VLOOKUP(A121,'Master List'!A:C,2,FALSE)), "Not Found", VLOOKUP(A121,'Master List'!A:C,2,FALSE))) -> Diana Rumjahn | D121: =IF(ISBLANK(A121), "Email",IF(ISNA(VLOOKUP(A121,'Master List'!A:C,3,FALSE)), "Not Found", VLOOKUP(A121,'Master List'!A:C,3,FALSE))) -> drumjahn@sfsu.edu | E121: VGA > USB-C Adapter Adapter | F121: =IF(OR(A121="",E121="","",A121="?",E121="?"),"duplicate?",IF(COUNTIFS($A:A,A121,E:E,E121)>1,"yes","no")) -> yes | H121: 45282 | K121: =IF(J121="","Date",IF(J121<>"",IF(K121="Date",NOW(),K121),"")) -> Date
A122: 900029746 | B122: 44874 | C122: =IF(ISBLANK(A122),"Name",IF(ISNA(VLOOKUP(A122,'Master List'!A:C,2,FALSE)), "Not Found", VLOOKUP(A122,'Master List'!A:C,2,FALSE))) -> Diana Rumjahn | D122: =IF(ISBLANK(A122), "Email",IF(ISNA(VLOOKUP(A122,'Master List'!A:C,3,FALSE)), "Not Found", VLOOKUP(A122,'Master List'!A:C,3,FALSE))) -> drumjahn@sfsu.edu | E122: VGA > USB-C Adapter Adapter | F122: =IF(OR(A122="",E122="","",A122="?",E122="?"),"duplicate?",IF(COUNTIFS($A:A,A122,E:E,E122)>1,"yes","no")) -> yes | H122: 45282 | I122: Desktop | K122: =IF(J122="","Date",IF(J122<>"",IF(K122="Date",NOW(),K122),"")) -> Date
A123: 909749144 | B123: 44874 | C123: =IF(ISBLANK(A123),"Name",IF(ISNA(VLOOKUP(A123,'Master List'!A:C,2,FALSE)), "Not Found", VLOOKUP(A123,'Master List'!A:C,2,FALSE))) -> Erica Maciel | D123: =IF(ISBLANK(A123), "Email",IF(ISNA(VLOOKUP(A123,'Master List'!A:C,3,FALSE)), "Not Found", VLOOKUP(A123,'Master List'!A:C,3,FALSE))) -> emaciel@sfsu.edu | E123: Laser Clicker | F123: =IF(OR(A123="",E123="","",A123="?",E123="?"),"duplicate?",IF(COUNTIFS($A:A,A123,E:E,E123)>1,"yes","no")) -> no | H123: 45282 | K123: =IF(J123="","Date",IF(J123<>"",IF(K123="Date",NOW(),K123),"")) -> Date
A124: 909749144 | B124: 44874 | C124: =IF(ISBLANK(A124),"Name",IF(ISNA(VLOOKUP(A124,'Master List'!A:C,2,FALSE)), "Not Found", VLOOKUP(A124,'Master List'!A:C,2,FALSE))) -> Erica Maciel | D124: =IF(ISBLANK(A124), "Email",IF(ISNA(VLOOKUP(A124,'Master List'!A:C,3,FALSE)), "Not Found", VLOOKUP(A124,'Master List'!A:C,3,FALSE))) -> emaciel@sfsu.edu | E124: PA - Small | F124: =IF(OR(A124="",E124="","",A124="?",E124="?"),"duplicate?",IF(COUNTIFS($A:A,A124,E:E,E124)>1,"yes","no")) -> no | H124: 45282 | I124: Desktop | K124: =IF(J124="","Date",IF(J124<>"",IF(K124="Date",NOW(),K124),"")) -> Date
A125: 902976066 | B125: 44874 | C125: =IF(ISBLANK(A125),"Name",IF(ISNA(VLOOKUP(A125,'Master List'!A:C,2,FALSE)), "Not Found", VLOOKUP(A125,'Master List'!A:C,2,FALSE))) -> Fenicia Jacks, ASW, PPSC | D125: =IF(ISBLANK(A125), "Email",IF(ISNA(VLOOKUP(A125,'Master List'!A:C,3,FALSE)), "Not Found", VLOOKUP(A125,'Master List'!A:C,3,FALSE))) -> jacksf@sfsu.edu | E125: HDMI > MDP Adapter | F125: =IF(OR(A125="",E125="","",A125="?",E125="?"),"duplicate?",IF(COUNTIFS($A:A,A125,E:E,E125)>1,"yes","no")) -> no | H125: 45282 | I125: Desktop | K125: =IF(J125="","Date",IF(J125<>"",IF(K125="Date",NOW(),K125),"")) -> Date
A126: 905387982 | B126: 44874 | C126: =IF(ISBLANK(A126),"Name",IF(ISNA(VLOOKUP(A126,'Master List'!A:C,2,FALSE)), "Not Found", VLOOKUP(A126,'Master List'!A:C,2,FALSE))) -> Glenda Ortez-Galan | D126: =IF(ISBLANK(A126), "Email",IF(ISNA(VLOOKUP(A126,'Master List'!A:C,3,FALSE)), "Not Found", VLOOKUP(A126,'Master List'!A:C,3,FALSE))) -> gortezgalan@sfsu.edu | E126: HDMI > USB-C Adapter | F126: =IF(OR(A126="",E126="","",A126="?",E126="?"),"duplicate?",IF(COUNTIFS($A:A,A126,E:E,E126)>1,"yes","no")) -> no | H126: 45282 | I126: Chris | K126: =IF(J126="","Date",IF(J126<>"",IF(K126="Date",NOW(),K126),"")) -> Date
A127: 905387982 | B127: 44874 | C127: =IF(ISBLANK(A127),"Name",IF(ISNA(VLOOKUP(A127,'Master List'!A:C,2,FALSE)), "Not Found", VLOOKUP(A127,'Master List'!A:C,2,FALSE))) -> Glenda Ortez-Galan | D127: =IF(ISBLANK(A127), "Email",IF(ISNA(VLOOKUP(A127,'Master List'!A:C,3,FALSE)), "Not Found", VLOOKUP(A127,'Master List'!A:C,3,FALSE))) -> gortezgalan@sfsu.edu | E127: VGA > USB-C Adapter Adapter | F127: =IF(OR(A127="",E127="","",A127="?",E127="?"),"duplicate?",IF(COUNTIFS($A:A,A127,E:E,E127)>1,"yes","no")) -> no | H127: 45282 | I127: Desktop | K127: =IF(J127="","Date",IF(J127<>"",IF(K127="Date",NOW(),K127),"")) -> Date
...

Sheet Student GoPros
A1: ID | B1: Date | C1: Name | D1: Email | E1: Equipment Description | F1: Duplicate | G1: GoPro # | H1: Expected Return Date | I1: Checked out by | J1: Checked in by | K1: Returned Date | L1: Notes
A2: 916490346 | B2: =IF(A2="","Date",IF(A2<>"",IF(B2="Date",NOW(),B2),"")) -> 45329.683 | C2: Vessela Anguelova | D2: vanguelova@sfsu.edu | E2: GoPro 4 w/ tripod | F2: =IF(OR(A2="",E2="","",A2="?",E2="?"),"duplicate?",IF(COUNTIFS($A:A,A2,E:E,E2)>1,"yes","no")) -> no | G2: GP74 | H2: 45384 | I2: Kevin | J2: Mari | K2: =IF(J2="","Date",IF(J2<>"",IF(K2="Date",NOW(),K2),"")) -> 45372.657
A3: 923240510 | B3: =IF(A3="","Date",IF(A3<>"",IF(B3="Date",NOW(),B3),"")) -> 45336.637 | C3: =IF(ISBLANK(A3),"Name",IF(ISNA(VLOOKUP(A3,'Master List'!A:C,2,FALSE)), "Not Found", VLOOKUP(A3,'Master List'!A:C,2,FALSE))) -> Kunie Kikunaga | D3: =IF(ISBLANK(A3), "Email",IF(ISNA(VLOOKUP(A3,'Master List'!A:C,3,FALSE)), "Not Found", VLOOKUP(A3,'Master List'!A:C,3,FALSE))) -> kkikunaga@sfsu.edu | E3: GoPro 11 w/ tripod | F3: =IF(OR(A3="",E3="","",A3="?",E3="?"),"duplicate?",IF(COUNTIFS($A:A,A3,E:E,E3)>1,"yes","no")) -> yes | G3: GP 77 | H3: 45356 | I3: Sam | J3: Jeremy | K3: =IF(J3="","Date",IF(J3<>"",IF(K3="Date",NOW(),K3),"")) -> 45363.774 | L3: GoPro 11
A4: 920938353 | B4: =IF(A4="","Date",IF(A4<>"",IF(B4="Date",NOW(),B4),"")) -> 45337.56 | C4: =IF(ISBLANK(A4),"Name",IF(ISNA(VLOOKUP(A4,'Master List'!A:C,2,FALSE)), "Not Found", VLOOKUP(A4,'Master List'!A:C,2,FALSE))) -> Maelynn Le | D4: =IF(ISBLANK(A4), "Email",IF(ISNA(VLOOKUP(A4,'Master List'!A:C,3,FALSE)), "Not Found", VLOOKUP(A4,'Master List'!A:C,3,FALSE))) -> mle12@mail.sfsu.edu | E4: GoPro 11 w/ tripod | F4: =IF(OR(A4="",E4="","",A4="?",E4="?"),"duplicate?",IF(COUNTIFS($A:A,A4,E:E,E4)>1,"yes","no")) -> no | G4: GP120 | H4: 45379 | I4: Sam | J4: Sam | K4: =IF(J4="","Date",IF(J4<>"",IF(K4="Date",NOW(),K4),"")) -> 45378.688 | L4: Already returned the clear water cases (not sure why) -Kevin
A5: 923240510 | B5: =IF(A5="","Date",IF(A5<>"",IF(B5="Date",NOW(),B5),"")) -> 45341.501 | C5: =IF(ISBLANK(A5),"Name",IF(ISNA(VLOOKUP(A5,'Master List'!A:C,2,FALSE)), "Not Found", VLOOKUP(A5,'Master List'!A:C,2,FALSE))) -> Kunie Kikunaga | D5: =IF(ISBLANK(A5), "Email",IF(ISNA(VLOOKUP(A5,'Master List'!A:C,3,FALSE)), "Not Found", VLOOKUP(A5,'Master List'!A:C,3,FALSE))) -> kkikunaga@sfsu.edu | E5: GoPro Wireless Mic | F5: =IF(OR(A5="",E5="","",A5="?",E5="?"),"duplicate?",IF(COUNTIFS($A:A,A5,E:E,E5)>1,"yes","no")) -> yes | G5: ? | H5: 45356 | I5: Ariana | J5: Jeremy | K5: =IF(J5="","Date",IF(J5<>"",IF(K5="Date",NOW(),K5),"")) -> 45363.774
A6: 911104394 | B6: =IF(A6="","Date",IF(A6<>"",IF(B6="Date",NOW(),B6),"")) -> 45343.672 | C6: =IF(ISBLANK(A6),"Name",IF(ISNA(VLOOKUP(A6,'Master List'!A:C,2,FALSE)), "Not Found", VLOOKUP(A6,'Master List'!A:C,2,FALSE))) -> Natalie Ayala | D6: =IF(ISBLANK(A6), "Email",IF(ISNA(VLOOKUP(A6,'Master List'!A:C,3,FALSE)), "Not Found", VLOOKUP(A6,'Master List'!A:C,3,FALSE))) -> nayala@sfsu.edu | E6: GoPro 11 w/ tripod | F6: =IF(OR(A6="",E6="","",A6="?",E6="?"),"duplicate?",IF(COUNTIFS($A:A,A6,E:E,E6)>1,"yes","no")) -> no | G6: GP111 | H6: 46818 | I6: Kevin | J6: Sam | K6: =IF(J6="","Date",IF(J6<>"",IF(K6="Date",NOW(),K6),"")) -> 45357.607 | L6: USB C-C cable was not included, apprently was not included when loaned out.
A7: 923660943 | B7: =IF(A7="","Date",IF(A7<>"",IF(B7="Date",NOW(),B7),"")) -> 45350.367 | C7: =IF(ISBLANK(A7),"Name",IF(ISNA(VLOOKUP(A7,'Master List'!A:C,2,FALSE)), "Not Found", VLOOKUP(A7,'Master List'!A:C,2,FALSE))) -> Shufen Ma | D7: =IF(ISBLANK(A7), "Email",IF(ISNA(VLOOKUP(A7,'Master List'!A:C,3,FALSE)), "Not Found", VLOOKUP(A7,'Master List'!A:C,3,FALSE))) -> sma@sfsu.edu | E7: GoPro 11 w/ tripod | F7: =IF(OR(A7="",E7="","",A7="?",E7="?"),"duplicate?",IF(COUNTIFS($A:A,A7,E:E,E7)>1,"yes","no")) -> no | G7: GP118 | H7: 45357 | I7: Josh | J7: Kevin | K7: =IF(J7="","Date",IF(J7<>"",IF(K7="Date",NOW(),K7),"")) -> 45422.653
A8: 923660943 | B8: =IF(A8="","Date",IF(A8<>"",IF(B8="Date",NOW(),B8),"")) -> 45350.367 | C8: =IF(ISBLANK(A8),"Name",IF(ISNA(VLOOKUP(A8,'Master List'!A:C,2,FALSE)), "Not Found", VLOOKUP(A8,'Master List'!A:C,2,FALSE))) -> Shufen Ma | D8: =IF(ISBLANK(A8), "Email",IF(ISNA(VLOOKUP(A8,'Master List'!A:C,3,FALSE)), "Not Found", VLOOKUP(A8,'Master List'!A:C,3,FALSE))) -> sma@sfsu.edu | E8: GoPro Wireless Mic | F8: =IF(OR(A8="",E8="","",A8="?",E8="?"),"duplicate?",IF(COUNTIFS($A:A,A8,E:E,E8)>1,"yes","no")) -> no | H8: 45357 | I8: Josh | J8: Kevin | K8: =IF(J8="","Date",IF(J8<>"",IF(K8="Date",NOW(),K8),"")) -> 45422.653
A9: 920743353 | B9: =IF(A9="","Date",IF(A9<>"",IF(B9="Date",NOW(),B9),"")) -> 45350.368 | C9: =IF(ISBLANK(A9),"Name",IF(ISNA(VLOOKUP(A9,'Master List'!A:C,2,FALSE)), "Not Found", VLOOKUP(A9,'Master List'!A:C,2,FALSE))) -> Eli Dinkelspiel | D9: =IF(ISBLANK(A9), "Email",IF(ISNA(VLOOKUP(A9,'Master List'!A:C,3,FALSE)), "Not Found", VLOOKUP(A9,'Master List'!A:C,3,FALSE))) -> edinkelspiel@sfsu.edu | E9: GoPro (Hero 8) | F9: =IF(OR(A9="",E9="","",A9="?",E9="?"),"duplicate?",IF(COUNTIFS($A:A,A9,E:E,E9)>1,"yes","no")) -> no | G9: GP82 / GP14? | H9: 45357 | I9: Josh | J9: Cloud | K9: =IF(#REF!="","Date",IF(#REF!<>"",IF(K9="Date",NOW(),K9),"")) -> #REF!
A10: 920743353 | B10: =IF(A10="","Date",IF(A10<>"",IF(B10="Date",NOW(),B10),"")) -> 45350.369 | C10: =IF(ISBLANK(A10),"Name",IF(ISNA(VLOOKUP(A10,'Master List'!A:C,2,FALSE)), "Not Found", VLOOKUP(A10,'Master List'!A:C,2,FALSE))) -> Eli Dinkelspiel | D10: =IF(ISBLANK(A10), "Email",IF(ISNA(VLOOKUP(A10,'Master List'!A:C,3,FALSE)), "Not Found", VLOOKUP(A10,'Master List'!A:C,3,FALSE))) -> edinkelspiel@sfsu.edu | E10: GoPro Wireless Mic | F10: =IF(OR(A10="",E10="","",A10="?",E10="?"),"duplicate?",IF(COUNTIFS($A:A,A10,E:E,E10)>1,"yes","no")) -> no | G10: WM3 | H10: 45357 | I10: Josh | J10: Cloud | K10: =IF(J9="","Date",IF(J9<>"",IF(K10="Date",NOW(),K10),"")) -> 45429.67
A11: 913060374 | B11: =IF(A11="","Date",IF(A11<>"",IF(B11="Date",NOW(),B11),"")) -> 45350.37 | C11: =IF(ISBLANK(A11),"Name",IF(ISNA(VLOOKUP(A11,'Master List'!A:C,2,FALSE)), "Not Found", VLOOKUP(A11,'Master List'!A:C,2,FALSE))) -> Paul Medeiros | D11: =IF(ISBLANK(A11), "Email",IF(ISNA(VLOOKUP(A11,'Master List'!A:C,3,FALSE)), "Not Found", VLOOKUP(A11,'Master List'!A:C,3,FALSE))) -> pauljmed@mail.sfsu.edu | E11: GoPro (Hero 8) | F11: =IF(OR(A11="",E11="","",A11="?",E11="?"),"duplicate?",IF(COUNTIFS($A:A,A11,E:E,E11)>1,"yes","no")) -> no | G11: GP85 and Tripod | H11: 45357 | I11: Mari | J11: Mari | K11: =IF(J11="","Date",IF(J11<>"",IF(K11="Date",NOW(),K11),"")) -> 45358.696 | L11: Cristian snapped off the small flap
A12: 913060374 | B12: =IF(A12="","Date",IF(A12<>"",IF(B12="Date",NOW(),B12),"")) -> 45350.371 | C12: =IF(ISBLANK(A12),"Name",IF(ISNA(VLOOKUP(A12,'Master List'!A:C,2,FALSE)), "Not Found", VLOOKUP(A12,'Master List'!A:C,2,FALSE))) -> Paul Medeiros | D12: =IF(ISBLANK(A12), "Email",IF(ISNA(VLOOKUP(A12,'Master List'!A:C,3,FALSE)), "Not Found", VLOOKUP(A12,'Master List'!A:C,3,FALSE))) -> pauljmed@mail.sfsu.edu | E12: GoPro Wireless Mic | F12: =IF(OR(A12="",E12="","",A12="?",E12="?"),"duplicate?",IF(COUNTIFS($A:A,A12,E:E,E12)>1,"yes","no")) -> no | H12: 45357 | I12: Mari | J12: Mari | K12: =IF(J12="","Date",IF(J12<>"",IF(K12="Date",NOW(),K12),"")) -> 45358.696
A13: 900016746 | B13: =IF(A13="","Date",IF(A13<>"",IF(B13="Date",NOW(),B13),"")) -> 45350.704 | C13: =IF(ISBLANK(A13),"Name",IF(ISNA(VLOOKUP(A13,'Master List'!A:C,2,FALSE)), "Not Found", VLOOKUP(A13,'Master List'!A:C,2,FALSE))) -> Kurt Nutting | D13: =IF(ISBLANK(A13), "Email",IF(ISNA(VLOOKUP(A13,'Master List'!A:C,3,FALSE)), "Not Found", VLOOKUP(A13,'Master List'!A:C,3,FALSE))) -> knutting@sfsu.edu | E13: External DVD Drive | F13: =IF(OR(A13="",E13="","",A13="?",E13="?"),"duplicate?",IF(COUNTIFS($A:A,A13,E:E,E13)>1,"yes","no")) -> no | H13: In two weeks | I13: Mari | K13: =IF(J13="","Date",IF(J13<>"",IF(K13="Date",NOW(),K13),"")) -> Date
A14: 923658993 | B14: =IF(A14="","Date",IF(A14<>"",IF(B14="Date",NOW(),B14),"")) -> 45351.798 | C14: =IF(ISBLANK(A14),"Name",IF(ISNA(VLOOKUP(A14,'Master List'!A:C,2,FALSE)), "Not Found", VLOOKUP(A14,'Master List'!A:C,2,FALSE))) -> Colin Schildhauer | D14: =IF(ISBLANK(A14), "Email",IF(ISNA(VLOOKUP(A14,'Master List'!A:C,3,FALSE)), "Not Found", VLOOKUP(A14,'Master List'!A:C,3,FALSE))) -> SchildhauerC@sfsu.edu | E14: GoPro 11 w/ tripod | F14: =IF(OR(A14="",E14="","",A14="?",E14="?"),"duplicate?",IF(COUNTIFS($A:A,A14,E:E,E14)>1,"yes","no")) -> no | G14: GP-90 and Tripod GP-100 | H14: 45365 | I14: Adisat | J14: Cloud | K14: =IF(J14="","Date",IF(J14<>"",IF(K14="Date",NOW(),K14),"")) -> 45421.686
A15: 911104394 | B15: =IF(A15="","Date",IF(A15<>"",IF(B15="Date",NOW(),B15),"")) -> 45357.602 | C15: =IF(ISBLANK(A15),"Name",IF(ISNA(VLOOKUP(A15,'Master List'!A:C,2,FALSE)), "Not Found", VLOOKUP(A15,'Master List'!A:C,2,FALSE))) -> Natalie Ayala | D15: =IF(ISBLANK(A15), "Email",IF(ISNA(VLOOKUP(A15,'Master List'!A:C,3,FALSE)), "Not Found", VLOOKUP(A15,'Master List'!A:C,3,FALSE))) -> nayala@sfsu.edu | E15: GoPro 4 w/ tripod | F15: =IF(OR(A15="",E15="","",A15="?",E15="?"),"duplicate?",IF(COUNTIFS($A:A,A15,E:E,E15)>1,"yes","no")) -> yes | G15: GP 53 | H15: 45371 | I15: Sam | J15: Mari | K15: =IF(J15="","Date",IF(J15<>"",IF(K15="Date",NOW(),K15),"")) -> 45371.666 | L15: Tripod from previous rental (same student)
A16: 923661671 | B16: =IF(A16="","Date",IF(A16<>"",IF(B16="Date",NOW(),B16),"")) -> 45362.616 | C16: Zachary Crowley | D16: zcrowley@sfsu.edu | E16: GoPro 11 w/ tripod | F16: =IF(OR(A16="",E16="","",A16="?",E16="?"),"duplicate?",IF(COUNTIFS($A:A,A16,E:E,E16)>1,"yes","no")) -> no | G16: GP-83 | H16: 45377 | I16: ARIANA | J16: Sam | K16: =IF(J16="","Date",IF(J16<>"",IF(K16="Date",NOW(),K16),"")) -> 45379.643
A17: 923240510 | B17: =IF(A17="","Date",IF(A17<>"",IF(B17="Date",NOW(),B17),"")) -> 45363.774 | C17: =IF(ISBLANK(A17),"Name",IF(ISNA(VLOOKUP(A17,'Master List'!A:C,2,FALSE)), "Not Found", VLOOKUP(A17,'Master List'!A:C,2,FALSE))) -> Kunie Kikunaga | D17: =IF(ISBLANK(A17), "Email",IF(ISNA(VLOOKUP(A17,'Master List'!A:C,3,FALSE)), "Not Found", VLOOKUP(A17,'Master List'!A:C,3,FALSE))) -> kkikunaga@sfsu.edu | E17: GoPro 11 w/ tripod | F17: =IF(OR(A17="",E17="","",A17="?",E17="?"),"duplicate?",IF(COUNTIFS($A:A,A17,E:E,E17)>1,"yes","no")) -> yes | G17: GP 77 | H17: 45377 | I17: Jeremy | J17: Mari | K17: =IF(J17="","Date",IF(J17<>"",IF(K17="Date",NOW(),K17),"")) -> 45378.531
A18: 923240510 | B18: =IF(A18="","Date",IF(A18<>"",IF(B18="Date",NOW(),B18),"")) -> 45363.774 | C18: =IF(ISBLANK(A18),"Name",IF(ISNA(VLOOKUP(A18,'Master List'!A:C,2,FALSE)), "Not Found", VLOOKUP(A18,'Master List'!A:C,2,FALSE))) -> Kunie Kikunaga | D18: =IF(ISBLANK(A18), "Email",IF(ISNA(VLOOKUP(A18,'Master List'!A:C,3,FALSE)), "Not Found", VLOOKUP(A18,'Master List'!A:C,3,FALSE))) -> kkikunaga@sfsu.edu | E18: GoPro Wireless Mic | F18: =IF(OR(A18="",E18="","",A18="?",E18="?"),"duplicate?",IF(COUNTIFS($A:A,A18,E:E,E18)>1,"yes","no")) -> yes | H18: 45377 | I18: Jeremy | J18: Mari | K18: =IF(J18="","Date",IF(J18<>"",IF(K18="Date",NOW(),K18),"")) -> 45378.531
A19: 911104394 | B19: =IF(A19="","Date",IF(A19<>"",IF(B19="Date",NOW(),B19),"")) -> 45371.666 | C19: =IF(ISBLANK(A19),"Name",IF(ISNA(VLOOKUP(A19,'Master List'!A:C,2,FALSE)), "Not Found", VLOOKUP(A19,'Master List'!A:C,2,FALSE))) -> Natalie Ayala | D19: =IF(ISBLANK(A19), "Email",IF(ISNA(VLOOKUP(A19,'Master List'!A:C,3,FALSE)), "Not Found", VLOOKUP(A19,'Master List'!A:C,3,FALSE))) -> nayala@sfsu.edu | E19: GoPro 4 w/ tripod | F19: =IF(OR(A19="",E19="","",A19="?",E19="?"),"duplicate?",IF(COUNTIFS($A:A,A19,E:E,E19)>1,"yes","no")) -> yes | G19: GP 53 | H19: 45385 | I19: Mari | J19: Cloud | K19: =IF(J19="","Date",IF(J19<>"",IF(K19="Date",NOW(),K19),"")) -> 45406.684
A20: 923864653 | B20: =IF(A20="","Date",IF(A20<>"",IF(B20="Date",NOW(),B20),"")) -> 45385.639 | C20: =IF(ISBLANK(A20),"Name",IF(ISNA(VLOOKUP(A20,'Master List'!A:C,2,FALSE)), "Not Found", VLOOKUP(A20,'Master List'!A:C,2,FALSE))) -> Nesma Elhizzawi | D20: =IF(ISBLANK(A20), "Email",IF(ISNA(VLOOKUP(A20,'Master List'!A:C,3,FALSE)), "Not Found", VLOOKUP(A20,'Master List'!A:C,3,FALSE))) -> nelhizzawi@sfsu.edu | E20: GoPro 11 w/ tripod | F20: =IF(OR(A20="",E20="","",A20="?",E20="?"),"duplicate?",IF(COUNTIFS($A:A,A20,E:E,E20)>1,"yes","no")) -> yes | G20: GP 115 | H20: 45399 | I20: Sam | J20: Cloud | K20: =IF(J20="","Date",IF(J20<>"",IF(K20="Date",NOW(),K20),"")) -> 45397.932
A21: 923864653 | B21: =IF(A21="","Date",IF(A21<>"",IF(B21="Date",NOW(),B21),"")) -> 45397.952 | C21: =IF(ISBLANK(A21),"Name",IF(ISNA(VLOOKUP(A21,'Master List'!A:C,2,FALSE)), "Not Found", VLOOKUP(A21,'Master List'!A:C,2,FALSE))) -> Nesma Elhizzawi | D21: =IF(ISBLANK(A21), "Email",IF(ISNA(VLOOKUP(A21,'Master List'!A:C,3,FALSE)), "Not Found", VLOOKUP(A21,'Master List'!A:C,3,FALSE))) -> nelhizzawi@sfsu.edu | E21: GoPro 11 w/ tripod | F21: =IF(OR(A21="",E21="","",A21="?",E21="?"),"duplicate?",IF(COUNTIFS($A:A,A21,E:E,E21)>1,"yes","no")) -> yes | G21: GP 115 | H21: 45411 | I21: Cloud | J21: Cloud | K21: =IF(J21="","Date",IF(J21<>"",IF(K21="Date",NOW(),K21),"")) -> 45411.636
A22: 911104394 | B22: =IF(A22="","Date",IF(A22<>"",IF(B22="Date",NOW(),B22),"")) -> 45406.684 | C22: =IF(ISBLANK(A22),"Name",IF(ISNA(VLOOKUP(A22,'Master List'!A:C,2,FALSE)), "Not Found", VLOOKUP(A22,'Master List'!A:C,2,FALSE))) -> Natalie Ayala | D22: =IF(ISBLANK(A22), "Email",IF(ISNA(VLOOKUP(A22,'Master List'!A:C,3,FALSE)), "Not Found", VLOOKUP(A22,'Master List'!A:C,3,FALSE))) -> nayala@sfsu.edu | E22: GoPro 4 w/ tripod | F22: =IF(OR(A22="",E22="","",A22="?",E22="?"),"duplicate?",IF(COUNTIFS($A:A,A22,E:E,E22)>1,"yes","no")) -> yes | G22: GP 53 | H22: 45427 | I22: Cloud | J22: Josh | K22: =IF(J22="","Date",IF(J22<>"",IF(K22="Date",NOW(),K22),"")) -> 45426.703
A23: 918785600 | B23: =IF(A23="","Date",IF(A23<>"",IF(B23="Date",NOW(),B23),"")) -> 45560.526 | C23: Keren Nichole Zendejas | D23: kzendejas@sfsu.edu | E23: GoPro 11 w/ tripod | F23: =IF(OR(A23="",E23="","",A23="?",E23="?"),"duplicate?",IF(COUNTIFS($A:A,A23,E:E,E23)>1,"yes","no")) -> yes | G23: GP 82 | H23: 45567 | I23: Kanisha | J23: Cloud | K23: =IF(J23="","Date",IF(J23<>"",IF(K23="Date",NOW(),K23),"")) -> 45567.527
A24: 923901885 | B24: =IF(A24="","Date",IF(A24<>"",IF(B24="Date",NOW(),B24),"")) -> 45567.676 | C24: =IF(ISBLANK(A24),"Name",IF(ISNA(VLOOKUP(A24,'Master List'!A:C,2,FALSE)), "Not Found", VLOOKUP(A24,'Master List'!A:C,2,FALSE))) -> Yasi Martin-Partovi | D24: =IF(ISBLANK(A24), "Email",IF(ISNA(VLOOKUP(A24,'Master List'!A:C,3,FALSE)), "Not Found", VLOOKUP(A24,'Master List'!A:C,3,FALSE))) -> jmartinpartovi@sfsu.edu | E24: GoPro 11 w/ tripod | F24: =IF(OR(A24="",E24="","",A24="?",E24="?"),"duplicate?",IF(COUNTIFS($A:A,A24,E:E,E24)>1,"yes","no")) -> yes | G24: GP 90 | H24: 45574 | I24: Cloud | J24: Sam | K24: =IF(J24="","Date",IF(J24<>"",IF(K24="Date",NOW(),K24),"")) -> 45568.674
A25: 921051297 | B25: =IF(A25="","Date",IF(A25<>"",IF(B25="Date",NOW(),B25),"")) -> 45575.599 | C25: =IF(ISBLANK(A25),"Name",IF(ISNA(VLOOKUP(A25,'Master List'!A:C,2,FALSE)), "Not Found", VLOOKUP(A25,'Master List'!A:C,2,FALSE))) -> Samuel Reid | D25: =IF(ISBLANK(A25), "Email",IF(ISNA(VLOOKUP(A25,'Master List'!A:C,3,FALSE)), "Not Found", VLOOKUP(A25,'Master List'!A:C,3,FALSE))) -> sreid1@mail.sfsu.edu | E25: GoPro 11 w/ tripod | F25: =IF(OR(A25="",E25="","",A25="?",E25="?"),"duplicate?",IF(COUNTIFS($A:A,A25,E:E,E25)>1,"yes","no")) -> yes | G25: He also check out a microphone | H25: 45589 | I25: Ariana | J25: Sam | K25: =IF(J25="","Date",IF(J25<>"",IF(K25="Date",NOW(),K25),"")) -> 45579.53
A26: 920457548 | B26: =IF(A26="","Date",IF(A26<>"",IF(B26="Date",NOW(),B26),"")) -> 45576.411 | C26: Maria Del Castillo Schmidhiber | D26: mdelcastilloschmidhiber@mail.sfsu.edu | E26: GoPro 11 w/ tripod | F26: =IF(OR(A26="",E26="","",A26="?",E26="?"),"duplicate?",IF(COUNTIFS($A:A,A26,E:E,E26)>1,"yes","no")) -> no | G26: GP 118 | H26: 45583 | I26: Adisat | J26: Cloud | K26: =IF(J26="","Date",IF(J26<>"",IF(K26="Date",NOW(),K26),"")) -> 45581.656
A27: 921051297 | B27: =IF(A27="","Date",IF(A27<>"",IF(B27="Date",NOW(),B27),"")) -> 45588.596 | C27: =IF(ISBLANK(A27),"Name",IF(ISNA(VLOOKUP(A27,'Master List'!A:C,2,FALSE)), "Not Found", VLOOKUP(A27,'Master List'!A:C,2,FALSE))) -> Samuel Reid | D27: =IF(ISBLANK(A27), "Email",IF(ISNA(VLOOKUP(A27,'Master List'!A:C,3,FALSE)), "Not Found", VLOOKUP(A27,'Master List'!A:C,3,FALSE))) -> sreid1@mail.sfsu.edu | E27: GoPro 11 w/ tripod | F27: =IF(OR(A27="",E27="","",A27="?",E27="?"),"duplicate?",IF(COUNTIFS($A:A,A27,E:E,E27)>1,"yes","no")) -> yes | G27: GP 88 | H27: 45610 | I27: Kanisha | J27: Mari | K27: =IF(J27="","Date",IF(J27<>"",IF(K27="Date",NOW(),K27),"")) -> 45614.634 | L27: He checked out a microphone too and Tripod 14
A28: 917694887 | B28: =IF(A28="","Date",IF(A28<>"",IF(B28="Date",NOW(),B28),"")) -> 45590.626 | C28: =IF(ISBLANK(A28),"Name",IF(ISNA(VLOOKUP(A28,'Master List'!A:C,2,FALSE)), "Not Found", VLOOKUP(A28,'Master List'!A:C,2,FALSE))) -> Joey Samuel Ng | D28: jng9@sfsu.edu | E28: GoPro 11 w/ tripod | F28: =IF(OR(A28="",E28="","",A28="?",E28="?"),"duplicate?",IF(COUNTIFS($A:A,A28,E:E,E28)>1,"yes","no")) -> no | H28: End of Semester | I28: Athan | J28: Ethan | K28: =IF(J28="","Date",IF(J28<>"",IF(K28="Date",NOW(),K28),"")) -> 45595.668
A29: 923901846 | B29: =IF(A29="","Date",IF(A29<>"",IF(B29="Date",NOW(),B29),"")) -> 45596.688 | C29: =IF(ISBLANK(A29),"Name",IF(ISNA(VLOOKUP(A29,'Master List'!A:C,2,FALSE)), "Not Found", VLOOKUP(A29,'Master List'!A:C,2,FALSE))) -> Sofia Fulgoni | D29: =IF(ISBLANK(A29), "Email",IF(ISNA(VLOOKUP(A29,'Master List'!A:C,3,FALSE)), "Not Found", VLOOKUP(A29,'Master List'!A:C,3,FALSE))) -> sfulgoni@sfsu.edu | E29: GoPro 11 w/ tripod | F29: =IF(OR(A29="",E29="","",A29="?",E29="?"),"duplicate?",IF(COUNTIFS($A:A,A29,E:E,E29)>1,"yes","no")) -> yes | G29: GP 95 | H29: 45610 | I29: Sam | J29: Mari | K29: =IF(J29="","Date",IF(J29<>"",IF(K29="Date",NOW(),K29),"")) -> 45602.698
A30: 922788305 | B30: =IF(A30="","Date",IF(A30<>"",IF(B30="Date",NOW(),B30),"")) -> 45601.678 | C30: =IF(ISBLANK(A30),"Name",IF(ISNA(VLOOKUP(A30,'Master List'!A:C,2,FALSE)), "Not Found", VLOOKUP(A30,'Master List'!A:C,2,FALSE))) -> Anesu Mupombwa | D30: =IF(ISBLANK(A30), "Email",IF(ISNA(VLOOKUP(A30,'Master List'!A:C,3,FALSE)), "Not Found", VLOOKUP(A30,'Master List'!A:C,3,FALSE))) -> amupombwa@sfsu.edu | E30: GoPro 11 w/ tripod | F30: =IF(OR(A30="",E30="","",A30="?",E30="?"),"duplicate?",IF(COUNTIFS($A:A,A30,E:E,E30)>1,"yes","no")) -> no | H30: End of Semester | I30: Athan | K30: =IF(J30="","Date",IF(J30<>"",IF(K30="Date",NOW(),K30),"")) -> Date
A31: 918785600 | B31: =IF(A31="","Date",IF(A31<>"",IF(B31="Date",NOW(),B31),"")) -> 45604.351 | C31: Keren Nichole Zendejas | D31: kzendejas@sfsu.edu | E31: GoPro 11 w/ tripod | F31: =IF(OR(A31="",E31="","",A31="?",E31="?"),"duplicate?",IF(COUNTIFS($A:A,A31,E:E,E31)>1,"yes","no")) -> yes | G31: GP 118 | H31: 45615 | J31: Cloud | K31: =IF(J31="","Date",IF(J31<>"",IF(K31="Date",NOW(),K31),"")) -> 45616.535
A32: 924309136 | B32: =IF(A32="","Date",IF(A32<>"",IF(B32="Date",NOW(),B32),"")) -> 45615.693 | C32: =IF(ISBLANK(A32),"Name",IF(ISNA(VLOOKUP(A32,'Master List'!A:C,2,FALSE)), "Not Found", VLOOKUP(A32,'Master List'!A:C,2,FALSE))) -> Lewis Haidt | D32: =IF(ISBLANK(A32), "Email",IF(ISNA(VLOOKUP(A32,'Master List'!A:C,3,FALSE)), "Not Found", VLOOKUP(A32,'Master List'!A:C,3,FALSE))) -> lhaidt@sfsu.edu | E32: GoPro 11 w/ tripod | F32: =IF(OR(A32="",E32="","",A32="?",E32="?"),"duplicate?",IF(COUNTIFS($A:A,A32,E:E,E32)>1,"yes","no")) -> yes | G32: GP 88 | H32: 45629 | I32: Athan | J32: Sam | K32: =IF(J32="","Date",IF(J32<>"",IF(K32="Date",NOW(),K32),"")) -> 45638.67
A33: 921782430 | B33: =IF(A33="","Date",IF(A33<>"",IF(B33="Date",NOW(),B33),"")) -> 45631.521 | C33: =IF(ISBLANK(A33),"Name",IF(ISNA(VLOOKUP(A33,'Master List'!A:C,2,FALSE)), "Not Found", VLOOKUP(A33,'Master List'!A:C,2,FALSE))) -> Raymond Hernandez | D33: =IF(ISBLANK(A33), "Email",IF(ISNA(VLOOKUP(A33,'Master List'!A:C,3,FALSE)), "Not Found", VLOOKUP(A33,'Master List'!A:C,3,FALSE))) -> rhernandez15@sfsu.edu | E33: GoPro 11 w/ tripod | F33: =IF(OR(A33="",E33="","",A33="?",E33="?"),"duplicate?",IF(COUNTIFS($A:A,A33,E:E,E33)>1,"yes","no")) -> no | G33: GP 114 | H33: Early Jan | I33: Sam | J33: Athan | K33: =IF(J33="","Date",IF(J33<>"",IF(K33="Date",NOW(),K33),"")) -> 45772.372
A34: 924307290 | B34: =IF(A34="","Date",IF(A34<>"",IF(B34="Date",NOW(),B34),"")) -> 45692.758 | C34: =IF(ISBLANK(A34),"Name",IF(ISNA(VLOOKUP(A34,'Master List'!A:C,2,FALSE)), "Not Found", VLOOKUP(A34,'Master List'!A:C,2,FALSE))) -> Tyler Berkson | D34: =IF(ISBLANK(A34), "Email",IF(ISNA(VLOOKUP(A34,'Master List'!A:C,3,FALSE)), "Not Found", VLOOKUP(A34,'Master List'!A:C,3,FALSE))) -> tberkson@sfsu.edu | E34: GoPro 11 w/ tripod | F34: =IF(OR(A34="",E34="","",A34="?",E34="?"),"duplicate?",IF(COUNTIFS($A:A,A34,E:E,E34)>1,"yes","no")) -> no | G34: GP88 | H34: 45706 | I34: Mari | J34: Yukti | K34: =IF(J34="","Date",IF(J34<>"",IF(K34="Date",NOW(),K34),"")) -> 45727.79 | L34: Turning it in a week later
A35: 923901885 | B35: =IF(A35="","Date",IF(A35<>"",IF(B35="Date",NOW(),B35),"")) -> 45699.798 | C35: =IF(ISBLANK(A35),"Name",IF(ISNA(VLOOKUP(A35,'Master List'!A:C,2,FALSE)), "Not Found", VLOOKUP(A35,'Master List'!A:C,2,FALSE))) -> Yasi Martin-Partovi | D35: =IF(ISBLANK(A35), "Email",IF(ISNA(VLOOKUP(A35,'Master List'!A:C,3,FALSE)), "Not Found", VLOOKUP(A35,'Master List'!A:C,3,FALSE))) -> jmartinpartovi@sfsu.edu | E35: GoPro 11 w/ tripod | F35: =IF(OR(A35="",E35="","",A35="?",E35="?"),"duplicate?",IF(COUNTIFS($A:A,A35,E:E,E35)>1,"yes","no")) -> yes | G35: GP98 | H35: 45712 | I35: Yukti | J35: Mari | K35: =IF(J35="","Date",IF(J35<>"",IF(K35="Date",NOW(),K35),"")) -> 45783.697
A36: 921051297 | B36: =IF(A36="","Date",IF(A36<>"",IF(B36="Date",NOW(),B36),"")) -> 45701.64 | C36: =IF(ISBLANK(A36),"Name",IF(ISNA(VLOOKUP(A36,'Master List'!A:C,2,FALSE)), "Not Found", VLOOKUP(A36,'Master List'!A:C,2,FALSE))) -> Samuel Reid | D36: =IF(ISBLANK(A36), "Email",IF(ISNA(VLOOKUP(A36,'Master List'!A:C,3,FALSE)), "Not Found", VLOOKUP(A36,'Master List'!A:C,3,FALSE))) -> sreid1@mail.sfsu.edu | E36: GoPro 11 w/ tripod | F36: =IF(OR(A36="",E36="","",A36="?",E36="?"),"duplicate?",IF(COUNTIFS($A:A,A36,E:E,E36)>1,"yes","no")) -> yes | G36: GP84 | H36: 45722 | I36: Yukti | J36: Athan | K36: =IF(J36="","Date",IF(J36<>"",IF(K36="Date",NOW(),K36),"")) -> 45765.042 | L36: Returned + mic, tripod April 18 - returned tripod
A37: 916125371 | B37: =IF(A37="","Date",IF(A37<>"",IF(B37="Date",NOW(),B37),"")) -> 45705.641 | C37: =IF(ISBLANK(A37),"Name",IF(ISNA(VLOOKUP(A37,'Master List'!A:C,2,FALSE)), "Not Found", VLOOKUP(A37,'Master List'!A:C,2,FALSE))) -> Mayra Torres | D37: =IF(ISBLANK(A37), "Email",IF(ISNA(VLOOKUP(A37,'Master List'!A:C,3,FALSE)), "Not Found", VLOOKUP(A37,'Master List'!A:C,3,FALSE))) -> mtorres5@sfsu.edu | E37: GoPro 11 w/ tripod | F37: =IF(OR(A37="",E37="","",A37="?",E37="?"),"duplicate?",IF(COUNTIFS($A:A,A37,E:E,E37)>1,"yes","no")) -> yes | G37: GP118 | H37: 45713 | I37: Cloud | J37: Cloud | K37: =IF(J37="","Date",IF(J37<>"",IF(K37="Date",NOW(),K37),"")) -> 45723.69 | L37: Tripod GP-14
A38: 922838524 | B38: =IF(A38="","Date",IF(A38<>"",IF(B38="Date",NOW(),B38),"")) -> 45706.686 | C38: =IF(ISBLANK(A38),"Name",IF(ISNA(VLOOKUP(A38,'Master List'!A:C,2,FALSE)), "Not Found", VLOOKUP(A38,'Master List'!A:C,2,FALSE))) -> Nicholas Knight | D38: =IF(ISBLANK(A38), "Email",IF(ISNA(VLOOKUP(A38,'Master List'!A:C,3,FALSE)), "Not Found", VLOOKUP(A38,'Master List'!A:C,3,FALSE))) -> nknight2@sfsu.edu | E38: GoPro 11 w/ tripod | F38: =IF(OR(A38="",E38="","",A38="?",E38="?"),"duplicate?",IF(COUNTIFS($A:A,A38,E:E,E38)>1,"yes","no")) -> no | G38: GP117 | H38: March 4th | I38: Mari | J38: Mari | K38: =IF(J38="","Date",IF(J38<>"",IF(K38="Date",NOW(),K38),"")) -> 45748.682 | L38: Didnt borrow Tripod
A39: 921219673 | B39: =IF(A39="","Date",IF(A39<>"",IF(B39="Date",NOW(),B39),"")) -> 45708.789 | C39: =IF(ISBLANK(A39),"Name",IF(ISNA(VLOOKUP(A39,'Master List'!A:C,2,FALSE)), "Not Found", VLOOKUP(A39,'Master List'!A:C,2,FALSE))) -> Erik Malagon-Leon | D39: =IF(ISBLANK(A39), "Email",IF(ISNA(VLOOKUP(A39,'Master List'!A:C,3,FALSE)), "Not Found", VLOOKUP(A39,'Master List'!A:C,3,FALSE))) -> emalagonleon@sfsu.edu | E39: GoPro 11 w/ tripod | F39: =IF(OR(A39="",E39="","",A39="?",E39="?"),"duplicate?",IF(COUNTIFS($A:A,A39,E:E,E39)>1,"yes","no")) -> no | G39: GP89 | H39: March 6th | I39: Yukti | J39: Yukti | K39: =IF(J39="","Date",IF(J39<>"",IF(K39="Date",NOW(),K39),"")) -> 45722.628 | L39: TRIPOD- GP-100
A40: 921345149 | B40: =IF(A40="","Date",IF(A40<>"",IF(B40="Date",NOW(),B40),"")) -> 45709.392 | C40: =IF(ISBLANK(A40),"Name",IF(ISNA(VLOOKUP(A40,'Master List'!A:C,2,FALSE)), "Not Found", VLOOKUP(A40,'Master List'!A:C,2,FALSE))) -> Ryan Pearce | D40: rpearce@sfsu.edu | E40: GoPro 11 w/ tripod | F40: =IF(OR(A40="",E40="","",A40="?",E40="?"),"duplicate?",IF(COUNTIFS($A:A,A40,E:E,E40)>1,"yes","no")) -> no | G40: GP93 | H40: 45716 | I40: Jason | K40: =IF(J40="","Date",IF(J40<>"",IF(K40="Date",NOW(),K40),"")) -> Date
A41: 918785600 | B41: =IF(A41="","Date",IF(A41<>"",IF(B41="Date",NOW(),B41),"")) -> 45712.658 | C41: =IF(ISBLANK(A41),"Name",IF(ISNA(VLOOKUP(A41,'Master List'!A:C,2,FALSE)), "Not Found", VLOOKUP(A41,'Master List'!A:C,2,FALSE))) -> Keren Nichole Zendejas | D41: =IF(ISBLANK(A41), "Email",IF(ISNA(VLOOKUP(A41,'Master List'!A:C,3,FALSE)), "Not Found", VLOOKUP(A41,'Master List'!A:C,3,FALSE))) -> kzendejas@sfsu.edu | E41: GoPro 11 w/ tripod | F41: =IF(OR(A41="",E41="","",A41="?",E41="?"),"duplicate?",IF(COUNTIFS($A:A,A41,E:E,E41)>1,"yes","no")) -> yes | G41: GP94 | H41: 45726 | I41: Mari | J41: Cloud | K41: =IF(J41="","Date",IF(J41<>"",IF(K41="Date",NOW(),K41),"")) -> 45726.624 | L41: Tripod- GP95
A42: 921219673 | B42: =IF(A42="","Date",IF(A42<>"",IF(B42="Date",NOW(),B42),"")) -> 45712.684 | C42: =IF(ISBLANK(A42),"Name",IF(ISNA(VLOOKUP(A42,'Master List'!A:C,2,FALSE)), "Not Found", VLOOKUP(A42,'Master List'!A:C,2,FALSE))) -> Erik Malagon-Leon | D42: =IF(ISBLANK(A42), "Email",IF(ISNA(VLOOKUP(A42,'Master List'!A:C,3,FALSE)), "Not Found", VLOOKUP(A42,'Master List'!A:C,3,FALSE))) -> emalagonleon@sfsu.edu | E42: GoPro Wireless Mic | F42: =IF(OR(A42="",E42="","",A42="?",E42="?"),"duplicate?",IF(COUNTIFS($A:A,A42,E:E,E42)>1,"yes","no")) -> no | G42: #12 | H42: March 6th | I42: Cloud | J42: Yukti | K42: =IF(J42="","Date",IF(J42<>"",IF(K42="Date",NOW(),K42),"")) -> 45722.628
A43: 924309136 | B43: =IF(A43="","Date",IF(A43<>"",IF(B43="Date",NOW(),B43),"")) -> 45714.67 | C43: =IF(ISBLANK(A43),"Name",IF(ISNA(VLOOKUP(A43,'Master List'!A:C,2,FALSE)), "Not Found", VLOOKUP(A43,'Master List'!A:C,2,FALSE))) -> Lewis Haidt | D43: =IF(ISBLANK(A43), "Email",IF(ISNA(VLOOKUP(A43,'Master List'!A:C,3,FALSE)), "Not Found", VLOOKUP(A43,'Master List'!A:C,3,FALSE))) -> lhaidt@sfsu.edu | E43: GoPro 11 w/ tripod | F43: =IF(OR(A43="",E43="","",A43="?",E43="?"),"duplicate?",IF(COUNTIFS($A:A,A43,E:E,E43)>1,"yes","no")) -> yes | G43: GP118 | H43: March 12th | I43: Mari | J43: Cloud | K43: =IF(J43="","Date",IF(J43<>"",IF(K43="Date",NOW(),K43),"")) -> 45742.704 | L43: Tripod- GP14
A44: 924326062 | B44: =IF(A44="","Date",IF(A44<>"",IF(B44="Date",NOW(),B44),"")) -> 45720.679 | C44: =IF(ISBLANK(A44),"Name",IF(ISNA(VLOOKUP(A44,'Master List'!A:C,2,FALSE)), "Not Found", VLOOKUP(A44,'Master List'!A:C,2,FALSE))) -> Celia Xinyu Wei | D44: =IF(ISBLANK(A44), "Email",IF(ISNA(VLOOKUP(A44,'Master List'!A:C,3,FALSE)), "Not Found", VLOOKUP(A44,'Master List'!A:C,3,FALSE))) -> xwei@sfsu.edu | E44: GoPro 4 w/ tripod | F44: =IF(OR(A44="",E44="","",A44="?",E44="?"),"duplicate?",IF(COUNTIFS($A:A,A44,E:E,E44)>1,"yes","no")) -> no | G44: GP-93 | H44: 45734 | I44: Yukti | J44: Yukti | K44: =IF(J44="","Date",IF(J44<>"",IF(K44="Date",NOW(),K44),"")) -> 45734.692 | L44: Tripod- GP108
A45: 924326062 | B45: =IF(A45="","Date",IF(A45<>"",IF(B45="Date",NOW(),B45),"")) -> 45720.681 | C45: =IF(ISBLANK(A45),"Name",IF(ISNA(VLOOKUP(A45,'Master List'!A:C,2,FALSE)), "Not Found", VLOOKUP(A45,'Master List'!A:C,2,FALSE))) -> Celia Xinyu Wei | D45: =IF(ISBLANK(A45), "Email",IF(ISNA(VLOOKUP(A45,'Master List'!A:C,3,FALSE)), "Not Found", VLOOKUP(A45,'Master List'!A:C,3,FALSE))) -> xwei@sfsu.edu | E45: GoPro Wireless Mic | F45: =IF(OR(A45="",E45="","",A45="?",E45="?"),"duplicate?",IF(COUNTIFS($A:A,A45,E:E,E45)>1,"yes","no")) -> no | G45: #8 | H45: 45734 | I45: Yukti | J45: Yukti | K45: =IF(J45="","Date",IF(J45<>"",IF(K45="Date",NOW(),K45),"")) -> 45734.692
A46: 912474867 | B46: =IF(A46="","Date",IF(A46<>"",IF(B46="Date",NOW(),B46),"")) -> 45720.793 | C46: =IF(ISBLANK(A46),"Name",IF(ISNA(VLOOKUP(A46,'Master List'!A:C,2,FALSE)), "Not Found", VLOOKUP(A46,'Master List'!A:C,2,FALSE))) -> Kyle Liu | D46: =IF(ISBLANK(A46), "Email",IF(ISNA(VLOOKUP(A46,'Master List'!A:C,3,FALSE)), "Not Found", VLOOKUP(A46,'Master List'!A:C,3,FALSE))) -> kliu17@sfsu.edu | E46: GoPro 4 w/ tripod | F46: =IF(OR(A46="",E46="","",A46="?",E46="?"),"duplicate?",IF(COUNTIFS($A:A,A46,E:E,E46)>1,"yes","no")) -> no | G46: GP-95 | H46: May 1st | I46: Mari | J46: Athan | K46: =IF(J46="","Date",IF(J46<>"",IF(K46="Date",NOW(),K46),"")) -> 45785.693 | L46: Tripod GP- 105 Extension- 3rd April
A47: 917572414 | B47: =IF(A47="","Date",IF(A47<>"",IF(B47="Date",NOW(),B47),"")) -> 45723.594 | C47: =IF(ISBLANK(A47),"Name",IF(ISNA(VLOOKUP(A47,'Master List'!A:C,2,FALSE)), "Not Found", VLOOKUP(A47,'Master List'!A:C,2,FALSE))) -> Angelica Joy Alberti | D47: aalberti@mail.sfsu.edu | E47: GoPro 11 w/ tripod | F47: =IF(OR(A47="",E47="","",A47="?",E47="?"),"duplicate?",IF(COUNTIFS($A:A,A47,E:E,E47)>1,"yes","no")) -> no | G47: GP-82 | H47: Thursday | I47: Athan | K47: =IF(J47="","Date",IF(J47<>"",IF(K47="Date",NOW(),K47),"")) -> Date
A48: 916125371 | B48: =IF(A48="","Date",IF(A48<>"",IF(B48="Date",NOW(),B48),"")) -> 45723.688 | C48: =IF(ISBLANK(A48),"Name",IF(ISNA(VLOOKUP(A48,'Master List'!A:C,2,FALSE)), "Not Found", VLOOKUP(A48,'Master List'!A:C,2,FALSE))) -> Mayra Torres | D48: =IF(ISBLANK(A48), "Email",IF(ISNA(VLOOKUP(A48,'Master List'!A:C,3,FALSE)), "Not Found", VLOOKUP(A48,'Master List'!A:C,3,FALSE))) -> mtorres5@sfsu.edu | E48: GoPro 11 w/ tripod | F48: =IF(OR(A48="",E48="","",A48="?",E48="?"),"duplicate?",IF(COUNTIFS($A:A,A48,E:E,E48)>1,"yes","no")) -> yes | G48: GP-89 | H48: 45737 | I48: Cloud | J48: Kevin | K48: =IF(J48="","Date",IF(J48<>"",IF(K48="Date",NOW(),K48),"")) -> 45748.546
A49: 916125371 | B49: =IF(A49="","Date",IF(A49<>"",IF(B49="Date",NOW(),B49),"")) -> 45723.688 | C49: =IF(ISBLANK(A49),"Name",IF(ISNA(VLOOKUP(A49,'Master List'!A:C,2,FALSE)), "Not Found", VLOOKUP(A49,'Master List'!A:C,2,FALSE))) -> Mayra Torres | D49: =IF(ISBLANK(A49), "Email",IF(ISNA(VLOOKUP(A49,'Master List'!A:C,3,FALSE)), "Not Found", VLOOKUP(A49,'Master List'!A:C,3,FALSE))) -> mtorres5@sfsu.edu | E49: GoPro Wireless Mic | F49: =IF(OR(A49="",E49="","",A49="?",E49="?"),"duplicate?",IF(COUNTIFS($A:A,A49,E:E,E49)>1,"yes","no")) -> no | G49: #12 | H49: 45737 | I49: Cloud | J49: Kevin | K49: =IF(J49="","Date",IF(J49<>"",IF(K49="Date",NOW(),K49),"")) -> 45748.546
A50: 921103479 | B50: =IF(A50="","Date",IF(A50<>"",IF(B50="Date",NOW(),B50),"")) -> 45726.705 | C50: =IF(ISBLANK(A50),"Name",IF(ISNA(VLOOKUP(A50,'Master List'!A:C,2,FALSE)), "Not Found", VLOOKUP(A50,'Master List'!A:C,2,FALSE))) -> Patrick JieJun Xiong | D50: =IF(ISBLANK(A50), "Email",IF(ISNA(VLOOKUP(A50,'Master List'!A:C,3,FALSE)), "Not Found", VLOOKUP(A50,'Master List'!A:C,3,FALSE))) -> jxiong4@mail.sfsu.edu | E50: GoPro 11 w/ tripod | F50: =IF(OR(A50="",E50="","",A50="?",E50="?"),"duplicate?",IF(COUNTIFS($A:A,A50,E:E,E50)>1,"yes","no")) -> no | G50: GP#100 | H50: 45740 | I50: Cloud | J50: Adisat | K50: =IF(J50="","Date",IF(J50<>"",IF(K50="Date",NOW(),K50),"")) -> 45740.401
A51: 920434915 | B51: =IF(A51="","Date",IF(A51<>"",IF(B51="Date",NOW(),B51),"")) -> 45726.706 | C51: =IF(ISBLANK(A51),"Name",IF(ISNA(VLOOKUP(A51,'Master List'!A:C,2,FALSE)), "Not Found", VLOOKUP(A51,'Master List'!A:C,2,FALSE))) -> Yuneng Tan | D51: =IF(ISBLANK(A51), "Email",IF(ISNA(VLOOKUP(A51,'Master List'!A:C,3,FALSE)), "Not Found", VLOOKUP(A51,'Master List'!A:C,3,FALSE))) -> ytan12@mail.sfsu.edu | E51: GoPro 11 w/ tripod | F51: =IF(OR(A51="",E51="","",A51="?",E51="?"),"duplicate?",IF(COUNTIFS($A:A,A51,E:E,E51)>1,"yes","no")) -> no | G51: GP81 | H51: 45740 | I51: Mari | J51: Adisat | K51: =IF(J51="","Date",IF(J51<>"",IF(K51="Date",NOW(),K51),"")) -> 45740.401 | L51: Tripod: GP95
A52: 917308228 | B52: =IF(A52="","Date",IF(A52<>"",IF(B52="Date",NOW(),B52),"")) -> 45733.4 | C52: =IF(ISBLANK(A52),"Name",IF(ISNA(VLOOKUP(A52,'Master List'!A:C,2,FALSE)), "Not Found", VLOOKUP(A52,'Master List'!A:C,2,FALSE))) -> Paige Reilly | D52: =IF(ISBLANK(A52), "Email",IF(ISNA(VLOOKUP(A52,'Master List'!A:C,3,FALSE)), "Not Found", VLOOKUP(A52,'Master List'!A:C,3,FALSE))) -> preilly@sfsu.edu | E52: GoPro 11 w/ tripod | F52: =IF(OR(A52="",E52="","",A52="?",E52="?"),"duplicate?",IF(COUNTIFS($A:A,A52,E:E,E52)>1,"yes","no")) -> no | H52: 45748 | I52: Ariana | J52: Athan | K52: =IF(J52="","Date",IF(J52<>"",IF(K52="Date",NOW(),K52),"")) -> 45798.442
A53: 917308228 | B53: =IF(A53="","Date",IF(A53<>"",IF(B53="Date",NOW(),B53),"")) -> 45733.407 | C53: =IF(ISBLANK(A53),"Name",IF(ISNA(VLOOKUP(A53,'Master List'!A:C,2,FALSE)), "Not Found", VLOOKUP(A53,'Master List'!A:C,2,FALSE))) -> Paige Reilly | D53: =IF(ISBLANK(A53), "Email",IF(ISNA(VLOOKUP(A53,'Master List'!A:C,3,FALSE)), "Not Found", VLOOKUP(A53,'Master List'!A:C,3,FALSE))) -> preilly@sfsu.edu | E53: GoPro Wireless Mic | F53: =IF(OR(A53="",E53="","",A53="?",E53="?"),"duplicate?",IF(COUNTIFS($A:A,A53,E:E,E53)>1,"yes","no")) -> no | H53: 45748 | I53: Ariana | J53: Athan | K53: =IF(J53="","Date",IF(J53<>"",IF(K53="Date",NOW(),K53),"")) -> 45798.443
A54: 923901846 | B54: =IF(A54="","Date",IF(A54<>"",IF(B54="Date",NOW(),B54),"")) -> 45733.687 | C54: =IF(ISBLANK(A54),"Name",IF(ISNA(VLOOKUP(A54,'Master List'!A:C,2,FALSE)), "Not Found", VLOOKUP(A54,'Master List'!A:C,2,FALSE))) -> Sofia Fulgoni | D54: =IF(ISBLANK(A54), "Email",IF(ISNA(VLOOKUP(A54,'Master List'!A:C,3,FALSE)), "Not Found", VLOOKUP(A54,'Master List'!A:C,3,FALSE))) -> sfulgoni@sfsu.edu | E54: GoPro 11 w/ tripod | F54: =IF(OR(A54="",E54="","",A54="?",E54="?"),"duplicate?",IF(COUNTIFS($A:A,A54,E:E,E54)>1,"yes","no")) -> yes | G54: GP83 | H54: 45754 | I54: Mari | J54: Mari | K54: =IF(J54="","Date",IF(J54<>"",IF(K54="Date",NOW(),K54),"")) -> 45754.679 | L54: Tripod STP-300; extended by Kevin
A55: 924309136 | B55: =IF(A55="","Date",IF(A55<>"",IF(B55="Date",NOW(),B55),"")) -> 45733.708 | C55: =IF(ISBLANK(A55),"Name",IF(ISNA(VLOOKUP(A55,'Master List'!A:C,2,FALSE)), "Not Found", VLOOKUP(A55,'Master List'!A:C,2,FALSE))) -> Lewis Haidt | D55: =IF(ISBLANK(A55), "Email",IF(ISNA(VLOOKUP(A55,'Master List'!A:C,3,FALSE)), "Not Found", VLOOKUP(A55,'Master List'!A:C,3,FALSE))) -> lhaidt@sfsu.edu | E55: GoPro Wireless Mic | F55: =IF(OR(A55="",E55="","",A55="?",E55="?"),"duplicate?",IF(COUNTIFS($A:A,A55,E:E,E55)>1,"yes","no")) -> no | G55: #8 | H55: March 31 2025 | I55: Mari | J55: Kevin | K55: =IF(J55="","Date",IF(J55<>"",IF(K55="Date",NOW(),K55),"")) -> 45740.71
A56: 912474867 | B56: =IF(A56="","Date",IF(A56<>"",IF(B56="Date",NOW(),B56),"")) -> 45736.679 | C56: =IF(ISBLANK(A56),"Name",IF(ISNA(VLOOKUP(A56,'Master List'!A:C,2,FALSE)), "Not Found", VLOOKUP(A56,'Master List'!A:C,2,FALSE))) -> Kyle Liu | D56: =IF(ISBLANK(A56), "Email",IF(ISNA(VLOOKUP(A56,'Master List'!A:C,3,FALSE)), "Not Found", VLOOKUP(A56,'Master List'!A:C,3,FALSE))) -> kliu17@sfsu.edu | E56: GoPro Wireless Mic | F56: =IF(OR(A56="",E56="","",A56="?",E56="?"),"duplicate?",IF(COUNTIFS($A:A,A56,E:E,E56)>1,"yes","no")) -> no | G56: #11 | H56: May 1st | I56: Mari | J56: Athan | K56: =IF(J56="","Date",IF(J56<>"",IF(K56="Date",NOW(),K56),"")) -> 45785.693
A57: 924309136 | B57: =IF(A57="","Date",IF(A57<>"",IF(B57="Date",NOW(),B57),"")) -> 45740.71 | C57: =IF(ISBLANK(A57),"Name",IF(ISNA(VLOOKUP(A57,'Master List'!A:C,2,FALSE)), "Not Found", VLOOKUP(A57,'Master List'!A:C,2,FALSE))) -> Lewis Haidt | D57: =IF(ISBLANK(A57), "Email",IF(ISNA(VLOOKUP(A57,'Master List'!A:C,3,FALSE)), "Not Found", VLOOKUP(A57,'Master List'!A:C,3,FALSE))) -> lhaidt@sfsu.edu | E57: Multiport adapter (USB-C hub) | F57: =IF(OR(A57="",E57="","",A57="?",E57="?"),"duplicate?",IF(COUNTIFS($A:A,A57,E:E,E57)>1,"yes","no")) -> no | H57: 45728 | I57: Kevin | J57: Cloud | K57: =IF(J57="","Date",IF(J57<>"",IF(K57="Date",NOW(),K57),"")) -> 45742.704 | L57: Approved by Kevin so he didn't have to go back to Oakland. He'll return it with camera
A58: 920557531 | B58: =IF(A58="","Date",IF(A58<>"",IF(B58="Date",NOW(),B58),"")) -> 45770.338 | C58: Jose Hernandez | D58: =IF(ISBLANK(A58), "Email",IF(ISNA(VLOOKUP(A58,'Master List'!A:C,3,FALSE)), "Not Found", VLOOKUP(A58,'Master List'!A:C,3,FALSE))) -> jhernandez70@mail.sfsu.edu | E58: GoPro Wireless Mic | F58: =IF(OR(A58="",E58="","",A58="?",E58="?"),"duplicate?",IF(COUNTIFS($A:A,A58,E:E,E58)>1,"yes","no")) -> no | G58: 12 | H58: 45777 | I58: Ariana | J58: Cloud | K58: =IF(J58="","Date",IF(J58<>"",IF(K58="Date",NOW(),K58),"")) -> 45772.99
A59: 920557531 | B59: =IF(A59="","Date",IF(A59<>"",IF(B59="Date",NOW(),B59),"")) -> 45770.344 | C59: =IF(ISBLANK(A59),"Name",IF(ISNA(VLOOKUP(A59,'Master List'!A:C,2,FALSE)), "Not Found", VLOOKUP(A59,'Master List'!A:C,2,FALSE))) -> Jose Hernandez | D59: =IF(ISBLANK(A59), "Email",IF(ISNA(VLOOKUP(A59,'Master List'!A:C,3,FALSE)), "Not Found", VLOOKUP(A59,'Master List'!A:C,3,FALSE))) -> jhernandez70@mail.sfsu.edu | E59: GoPro 11 w/ tripod | F59: =IF(OR(A59="",E59="","",A59="?",E59="?"),"duplicate?",IF(COUNTIFS($A:A,A59,E:E,E59)>1,"yes","no")) -> no | G59: gp#84 | H59: 45777 | I59: Ariana | J59: Cloud | K59: =IF(J59="","Date",IF(J59<>"",IF(K59="Date",NOW(),K59),"")) -> 45772.992
B60: =IF(A60="","Date",IF(A60<>"",IF(B60="Date",NOW(),B60),"")) -> Date | C60: =IF(ISBLANK(A60),"Name",IF(ISNA(VLOOKUP(A60,'Master List'!A:C,2,FALSE)), "Not Found", VLOOKUP(A60,'Master List'!A:C,2,FALSE))) -> Name | D60: =IF(ISBLANK(A60), "Email",IF(ISNA(VLOOKUP(A60,'Master List'!A:C,3,FALSE)), "Not Found", VLOOKUP(A60,'Master List'!A:C,3,FALSE))) -> Email | F60: =IF(OR(A60="",E60="","",A60="?",E60="?"),"duplicate?",IF(COUNTIFS($A:A,A60,E:E,E60)>1,"yes","no")) -> duplicate? | K60: =IF(J60="","Date",IF(J60<>"",IF(K60="Date",NOW(),K60),"")) -> Date
B61: =IF(A61="","Date",IF(A61<>"",IF(B61="Date",NOW(),B61),"")) -> Date | C61: =IF(ISBLANK(A61),"Name",IF(ISNA(VLOOKUP(A61,'Master List'!A:C,2,FALSE)), "Not Found", VLOOKUP(A61,'Master List'!A:C,2,FALSE))) -> Name | D61: =IF(ISBLANK(A61), "Email",IF(ISNA(VLOOKUP(A61,'Master List'!A:C,3,FALSE)), "Not Found", VLOOKUP(A61,'Master List'!A:C,3,FALSE))) -> Email | F61: =IF(OR(A61="",E61="","",A61="?",E61="?"),"duplicate?",IF(COUNTIFS($A:A,A61,E:E,E61)>1,"yes","no")) -> duplicate? | K61: =IF(J61="","Date",IF(J61<>"",IF(K61="Date",NOW(),K61),"")) -> Date
B62: =IF(A62="","Date",IF(A62<>"",IF(B62="Date",NOW(),B62),"")) -> Date | C62: =IF(ISBLANK(A62),"Name",IF(ISNA(VLOOKUP(A62,'Master List'!A:C,2,FALSE)), "Not Found", VLOOKUP(A62,'Master List'!A:C,2,FALSE))) -> Name | D62: =IF(ISBLANK(A62), "Email",IF(ISNA(VLOOKUP(A62,'Master List'!A:C,3,FALSE)), "Not Found", VLOOKUP(A62,'Master List'!A:C,3,FALSE))) -> Email | F62: =IF(OR(A62="",E62="","",A62="?",E62="?"),"duplicate?",IF(COUNTIFS($A:A,A62,E:E,E62)>1,"yes","no")) -> duplicate? | K62: =IF(J62="","Date",IF(J62<>"",IF(K62="Date",NOW(),K62),"")) -> Date
B63: =IF(A63="","Date",IF(A63<>"",IF(B63="Date",NOW(),B63),"")) -> Date | C63: =IF(ISBLANK(A63),"Name",IF(ISNA(VLOOKUP(A63,'Master List'!A:C,2,FALSE)), "Not Found", VLOOKUP(A63,'Master List'!A:C,2,FALSE))) -> Name | D63: =IF(ISBLANK(A63), "Email",IF(ISNA(VLOOKUP(A63,'Master List'!A:C,3,FALSE)), "Not Found", VLOOKUP(A63,'Master List'!A:C,3,FALSE))) -> Email | F63: =IF(OR(A63="",E63="","",A63="?",E63="?"),"duplicate?",IF(COUNTIFS($A:A,A63,E:E,E63)>1,"yes","no")) -> duplicate? | K63: =IF(J63="","Date",IF(J63<>"",IF(K63="Date",NOW(),K63),"")) -> Date
B64: =IF(A64="","Date",IF(A64<>"",IF(B64="Date",NOW(),B64),"")) -> Date | C64: =IF(ISBLANK(A64),"Name",IF(ISNA(VLOOKUP(A64,'Master List'!A:C,2,FALSE)), "Not Found", VLOOKUP(A64,'Master List'!A:C,2,FALSE))) -> Name | D64: =IF(ISBLANK(A64), "Email",IF(ISNA(VLOOKUP(A64,'Master List'!A:C,3,FALSE)), "Not Found", VLOOKUP(A64,'Master List'!A:C,3,FALSE))) -> Email | F64: =IF(OR(A64="",E64="","",A64="?",E64="?"),"duplicate?",IF(COUNTIFS($A:A,A64,E:E,E64)>1,"yes","no")) -> duplicate? | K64: =IF(J64="","Date",IF(J64<>"",IF(K64="Date",NOW(),K64),"")) -> Date
B65: =IF(A65="","Date",IF(A65<>"",IF(B65="Date",NOW(),B65),"")) -> Date | C65: =IF(ISBLANK(A65),"Name",IF(ISNA(VLOOKUP(A65,'Master List'!A:C,2,FALSE)), "Not Found", VLOOKUP(A65,'Master List'!A:C,2,FALSE))) -> Name | D65: =IF(ISBLANK(A65), "Email",IF(ISNA(VLOOKUP(A65,'Master List'!A:C,3,FALSE)), "Not Found", VLOOKUP(A65,'Master List'!A:C,3,FALSE))) -> Email | F65: =IF(OR(A65="",E65="","",A65="?",E65="?"),"duplicate?",IF(COUNTIFS($A:A,A65,E:E,E65)>1,"yes","no")) -> duplicate? | K65: =IF(J65="","Date",IF(J65<>"",IF(K65="Date",NOW(),K65),"")) -> Date
B66: =IF(A66="","Date",IF(A66<>"",IF(B66="Date",NOW(),B66),"")) -> Date | C66: =IF(ISBLANK(A66),"Name",IF(ISNA(VLOOKUP(A66,'Master List'!A:C,2,FALSE)), "Not Found", VLOOKUP(A66,'Master List'!A:C,2,FALSE))) -> Name | D66: =IF(ISBLANK(A66), "Email",IF(ISNA(VLOOKUP(A66,'Master List'!A:C,3,FALSE)), "Not Found", VLOOKUP(A66,'Master List'!A:C,3,FALSE))) -> Email | F66: =IF(OR(A66="",E66="","",A66="?",E66="?"),"duplicate?",IF(COUNTIFS($A:A,A66,E:E,E66)>1,"yes","no")) -> duplicate? | K66: =IF(J66="","Date",IF(J66<>"",IF(K66="Date",NOW(),K66),"")) -> Date
B67: =IF(A67="","Date",IF(A67<>"",IF(B67="Date",NOW(),B67),"")) -> Date | C67: =IF(ISBLANK(A67),"Name",IF(ISNA(VLOOKUP(A67,'Master List'!A:C,2,FALSE)), "Not Found", VLOOKUP(A67,'Master List'!A:C,2,FALSE))) -> Name | D67: =IF(ISBLANK(A67), "Email",IF(ISNA(VLOOKUP(A67,'Master List'!A:C,3,FALSE)), "Not Found", VLOOKUP(A67,'Master List'!A:C,3,FALSE))) -> Email | F67: =IF(OR(A67="",E67="","",A67="?",E67="?"),"duplicate?",IF(COUNTIFS($A:A,A67,E:E,E67)>1,"yes","no")) -> duplicate? | K67: =IF(J67="","Date",IF(J67<>"",IF(K67="Date",NOW(),K67),"")) -> Date
B68: =IF(A68="","Date",IF(A68<>"",IF(B68="Date",NOW(),B68),"")) -> Date | C68: =IF(ISBLANK(A68),"Name",IF(ISNA(VLOOKUP(A68,'Master List'!A:C,2,FALSE)), "Not Found", VLOOKUP(A68,'Master List'!A:C,2,FALSE))) -> Name | D68: =IF(ISBLANK(A68), "Email",IF(ISNA(VLOOKUP(A68,'Master List'!A:C,3,FALSE)), "Not Found", VLOOKUP(A68,'Master List'!A:C,3,FALSE))) -> Email | F68: =IF(OR(A68="",E68="","",A68="?",E68="?"),"duplicate?",IF(COUNTIFS($A:A,A68,E:E,E68)>1,"yes","no")) -> duplicate? | K68: =IF(J68="","Date",IF(J68<>"",IF(K68="Date",NOW(),K68),"")) -> Date
B69: =IF(A69="","Date",IF(A69<>"",IF(B69="Date",NOW(),B69),"")) -> Date | C69: =IF(ISBLANK(A69),"Name",IF(ISNA(VLOOKUP(A69,'Master List'!A:C,2,FALSE)), "Not Found", VLOOKUP(A69,'Master List'!A:C,2,FALSE))) -> Name | D69: =IF(ISBLANK(A69), "Email",IF(ISNA(VLOOKUP(A69,'Master List'!A:C,3,FALSE)), "Not Found", VLOOKUP(A69,'Master List'!A:C,3,FALSE))) -> Email | F69: =IF(OR(A69="",E69="","",A69="?",E69="?"),"duplicate?",IF(COUNTIFS($A:A,A69,E:E,E69)>1,"yes","no")) -> duplicate? | K69: =IF(J69="","Date",IF(J69<>"",IF(K69="Date",NOW(),K69),"")) -> Date
B70: =IF(A70="","Date",IF(A70<>"",IF(B70="Date",NOW(),B70),"")) -> Date | C70: =IF(ISBLANK(A70),"Name",IF(ISNA(VLOOKUP(A70,'Master List'!A:C,2,FALSE)), "Not Found", VLOOKUP(A70,'Master List'!A:C,2,FALSE))) -> Name | D70: =IF(ISBLANK(A70), "Email",IF(ISNA(VLOOKUP(A70,'Master List'!A:C,3,FALSE)), "Not Found", VLOOKUP(A70,'Master List'!A:C,3,FALSE))) -> Email | F70: =IF(OR(A70="",E70="","",A70="?",E70="?"),"duplicate?",IF(COUNTIFS($A:A,A70,E:E,E70)>1,"yes","no")) -> duplicate? | K70: =IF(J70="","Date",IF(J70<>"",IF(K70="Date",NOW(),K70),"")) -> Date
B71: =IF(A71="","Date",IF(A71<>"",IF(B71="Date",NOW(),B71),"")) -> Date | C71: =IF(ISBLANK(A71),"Name",IF(ISNA(VLOOKUP(A71,'Master List'!A:C,2,FALSE)), "Not Found", VLOOKUP(A71,'Master List'!A:C,2,FALSE))) -> Name | D71: =IF(ISBLANK(A71), "Email",IF(ISNA(VLOOKUP(A71,'Master List'!A:C,3,FALSE)), "Not Found", VLOOKUP(A71,'Master List'!A:C,3,FALSE))) -> Email | F71: =IF(OR(A71="",E71="","",A71="?",E71="?"),"duplicate?",IF(COUNTIFS($A:A,A71,E:E,E71)>1,"yes","no")) -> duplicate? | K71: =IF(J71="","Date",IF(J71<>"",IF(K71="Date",NOW(),K71),"")) -> Date
... B97: =IF(A97="","Date",IF(A97<>"",IF(B97="Date",NOW(),B97),"")) -> Date | C97: =IF(ISBLANK(A97),"Name",IF(ISNA(VLOOKUP(A97,'Master List'!A:C,2,FALSE)), "Not Found", VLOOKUP(A97,'Master List'!A:C,2,FALSE))) -> Name | D97: =IF(ISBLANK(A97), "Email",IF(ISNA(VLOOKUP(A97,'Master List'!A:C,3,FALSE)), "Not Found", VLOOKUP(A97,'Master List'!A:C,3,FALSE))) -> Email | F97: =IF(OR(A97="",E97="","",A97="?",E97="?"),"duplicate?",IF(COUNTIFS($A:A,A97,E:E,E97)>1,"yes","no")) -> duplicate? | K97: =IF(J97="","Date",IF(J97<>"",IF(K97="Date",NOW(),K97),"")) -> Date

Sheet Master List
A1: 922374775 | B1: Joey Cuomo | C1: jcuomoscanzi@sfsu.edu
A2: 900000197 | B2: Mark Roberge | C2: roberge@sfsu.edu
A3: 900000249 | B3: Tom Holton | C3: tholton@sfsu.edu
A4: 900000340 | B4: Erik Peper | C4: epeper@sfsu.edu
A5: 900000431 | B5: Bruce Manning | C5: bmanning@sfsu.edu
A6: 900000483 | B6: Susan Zieff | C6: susangz@sfsu.edu
A7: 900000574 | B7: Jono Kornfeld | C7: jonok@sfsu.edu
A8: 900000808 | B8: Kenneth Monteiro | C8: monteiro@sfsu.edu
A9: 900000821 | B9: Masahiko Minami | C9: mminami@sfsu.edu
A10: 900000951 | B10: Ricardo Gomes | C10: ricgomes@sfsu.edu
A11: 900001003 | B11: Michael Goldman | C11: goldman@sfsu.edu
A12: 900001042 | B12: Jamie Eng | C12: jeng@sfsu.edu
... A2737: 923022942 | B2737: Alexis Hooper | C2737: ahooper2@sfsu.edu
A2738: 908492005 | B2738: Kazunori Okada | C2738: kazokada@sfsu.edu
A2739: 918850808 | B2739: Ried Wagner | C2739: riedwagner@sfsu.edu
A2740: 909072104 | B2740: Noah Price | C2740: nprice@sfsu.edu
A2741: 917158819 | B2741: Carolina De Robertis | C2741: caro@sfsu.edu
A2742: 922215018 | B2742: Lan De Vera | C2742: ldevera@sfsu.edu
A2743: 922386176 | B2743: Stanislav Shaposhnikov | C2743: sshaposhnikov@sfsu.edu
A2744: 918837691 | B2744: Michelle Montoya | C2744: mmontoy@sfsu.edu
A2745: 916804478 | B2745: Victor Aguilar | C2745: vaguila4@sfsu.edu
A2746: 916181362 | B2746: Ty Maniulit | C2746: tymaniulit@sfsu.edu
A2747: 900030006 | B2747: Christopher Clark | C2747: cclark@sfsu.edu
A2748: 918850145 | B2748: Zia Davidian | C2748: zdavidian@sfsu.edu
A2749: 900028329 | B2749: Sheldon Gen | C2749: sgen@sfsu.edu
A2750: 917461355 | B2750: Alcides Fuentes | C2750: alcidesfuentes@sfsu.edu
... A2754: 904421185 | B2754: John Ryan | C2754: jbr@sfsu.edu
A2755: Jason Bell | B2755: Jason Bell | C2755: jbell@asi.sfsu.edu
A2756: 921790152 | B2756: Julio Torress | C2756: jtorres30@sfsu.edu
A2757: Elizabeth Hallford | B2757: Elizabeth Hallford | C2757: betsey8050@me.com
A2758: 918851679 | B2758: Rebecca Cheng | C2758: rebeccacheng@sfsu.edu
A2759: 900020828 | B2759: Amy Sueyoshi | C2759: sueyoshi@sfsu.edu
A2760: 918844633 | B2760: Evan Jaynes | C2760: jaynes@sfsu.edu
A2761: 921279525 | B2761: Luis Poncio | C2761: lponcio@mail.sfsu.edu
A2762: 918838822 | B2762: Matthew Menor | C2762: menor@sfsu.edu
A2763: 918099577 | B2763: Time Ubungen | C2763: time@sfsu.edu
A2764: 920197873 | B2764: J.C. Gonzales | C2764: jj.gonzales@me.com
A2765: 904975115 | B2765: Elizabeth Hallford | C2765: betsey8050@mac.com
A2766: 900040562 | B2766: Sally G Pasion | C2766: pasion@sfsu.edu
A2767: 915553046 | B2767: Alexandra Theodotou | C2767: atheodotou@sfsu.edu
A2768: 911079720 | B2768: Joshua Baltodano | C2768: jbltodano@sfsu.edu
A2769: 909198113 | B2769: Dawn-Elissa Fischer | C2769: def@sfsu.edu
... A2845: 911104394 | B2845: Natalie Ayala | C2845: nayala@sfsu.edu
A2846: 905374475 | B2846: Katsafumi Araki
A2847: 913824020 | B2847: Sarah Bakker | C2847: sbakker@sfsu.edu
A2848: 920743353 | B2848: Eli Dinkelspiel | C2848: edinkelspiel@sfsu.edu
A2849: 913060374 | B2849: Paul Medeiros | C2849: pauljmed@mail.sfsu.edu
A2850: 923660943 | B2850: Shufen Ma | C2850: sma@sfsu.edu
A2851: 920056134 | B2851: Nicole Gluckstern | C2851: ngluckstern@mail.sfsu.edu
A2852: 923658993 | B2852: Colin Schildhauer | C2852: SchildhauerC@sfsu.edu
A2853: 900931179 | B2853: Jack Darrow | C2853: jkdarrow@mail.sfsu.edu
A2854: 917316327 | B2854: Cynthia Chu | C2854: cchu4@sfsu.edu
A2855: 909162155 | B2855: Minu Kumar | C2855: mkumar@sfsu.edu
A2856: 910108438 | B2856: Yuki Huynh | C2856: yukihuynh@sfsu.edu
A2857: 923864653 | B2857: Nesma Elhizzawi | C2857: nelhizzawi@sfsu.edu
A2858: 910342828 | B2858: Justin Wong | C2858: justinw707@sfsu.edu
... A2938: 900005683 | B2938: Caitlin Ryan | C2938: caitlin@sfsu.edu
A2939: 917572414 | B2939: Angelica Joy Alberti
A2940: 920434915 | B2940: Yuneng Tan | C2940: ytan12@mail.sfsu.edu
A2941: 921103479 | B2941: Patrick JieJun Xiong | C2941: jxiong4@mail.sfsu.edu
A2942: 917308228 | B2942: Paige Reilly | C2942: preilly@sfsu.edu
A2943: 922921217 | B2943: Evie Hidysmith | C2943: jhidysmith@sfsu.edu
A2944: 900013899 | B2944: Victoria Narkewicz | C2944: toria@sfsu.edu
A2945: 918859804 | B2945: Kate White | C2945: katewhite@sfsu.edu
A2946: 903567202 | B2946: Sugeetha Pathmanabhan | C2946: sugeetha@sfsu.edu
A2947: 907519657 | B2947: Eusebio Lozano | C2947: eusebiolozano@sfsu.edu
A2948: 918846726 | B2948: Sandra Williams | C2948: sswilliams@sfsu.edu
A2949: 918857737 | B2949: Bianca Licata | C2949: blicata@sfsu.edu
A2950: 913814257 | B2950: Ally Nguyen | C2950: an@sfsu.edu
A2951: 920557531 | B2951: Jose Hernandez | C2951: jhernandez70@mail.sfsu.edu
... A2958: 918851458 | B2958: Corrine Cheung | C2958: corrinec@sfsu.edu

Sheet Returned_checkout
A1: SFSU ID number | B1: Date | C1: Name | D1: Email | E1: Equipment Description | G1: Equipment ID (if applicable) | H1: Expected Return Date | I1: Checked out by | J1: Checked in by | K1: Returned Date | L1: Notes | M1: DEBT COLLECTOR
A2: 909168824 | B2: 44854 | C2: Ian Sinapuelas | D2: =IF(ISBLANK(B2), "Email",IF(ISNA(VLOOKUP(A2,'Master List'!A:C,3,FALSE)), "Not Found", VLOOKUP(A2,'Master List'!A:C,3,FALSE))) -> sinapuel@sfsu.edu | E2: Ethernet > USB-C Adapter | H2: 3 Weeks | K2: 37563 | M2: =IF(AND(COUNTIF(#REF!, Returned_checkout!A53)=0, ISBLANK(K2)),"Yes", "No") -> #REF!
A3: 920775489 | B3: 44895 | C3: Katelyn Endow | D3: =IF(ISBLANK(B3), "Email",IF(ISNA(VLOOKUP(A3,'Master List'!A:C,3,FALSE)), "Not Found", VLOOKUP(A3,'Master List'!A:C,3,FALSE))) -> kendow@sfsu.edu | E3: Camcorder (Sony 4K) | H3: end of semester | I3: Ritu | J3: Kevin | K3: 44578 | M3: =IF(AND(COUNTIF(#REF!, Returned_checkout!A68)=0, ISBLANK(K3)),"Yes", "No") -> #REF!
A4: 913869494 | B4: 44902 | C4: Nikolas Nackley | D4: =IF(ISBLANK(B4), "Email",IF(ISNA(VLOOKUP(A4,'Master List'!A:C,3,FALSE)), "Not Found", VLOOKUP(A4,'Master List'!A:C,3,FALSE))) -> nnackley@sfsu.edu | E4: Camcorder (Sony 4K) | H4: 44907 | I4: Larissa | J4: Kevin | K4: 44578 | M4: =IF(AND(COUNTIF(#REF!, Returned_checkout!A102)=0, ISBLANK(K4)),"Yes", "No") -> #REF!
A5: 901610000 | B5: 44834 | C5: Benjamin Sabey | D5: =IF(ISBLANK(B5), "Email",IF(ISNA(VLOOKUP(A5,'Master List'!A:C,3,FALSE)), "Not Found", VLOOKUP(A5,'Master List'!A:C,3,FALSE))) -> sabey@sfsu.edu | E5: Projector - Loose (CP-EX250N) | G5: LCD450 | H5: a week | J5: Rithik | K5: 44593 | L5: email sent 1/20/23 | M5: =IF(AND(COUNTIF(#REF!, Returned_checkout!A17)=0, ISBLANK(K5)),"Yes", "No") -> #REF!
A6: 918839459 | B6: 44823 | C6: Alexandra Hinck | D6: =IF(ISBLANK(B6), "Email",IF(ISNA(VLOOKUP(A6,'Master List'!A:C,3,FALSE)), "Not Found", VLOOKUP(A6,'Master List'!A:C,3,FALSE))) -> ahinck@sfsu.edu | E6: HDMI > USB-C Adapter | G6: N/A | H6: one day | K6: 44823 | M6: =IF(AND(COUNTIF(#REF!, Returned_checkout!A3)=0, ISBLANK(K6)),"Yes", "No") -> #REF!
A7: 900005774 | B7: 44823 | C7: M Schoerke | D7: =IF(ISBLANK(B7), "Email",IF(ISNA(VLOOKUP(A7,'Master List'!A:C,3,FALSE)), "Not Found", VLOOKUP(A7,'Master List'!A:C,3,FALSE))) -> schoerke@sfsu.edu | E7: HDMI > USB-C Adapter | G7: N/A | H7: one day | K7: 44823 | M7: =IF(AND(COUNTIF(#REF!, Returned_checkout!A89)=0, ISBLANK(K7)),"Yes", "No") -> #REF!
A8: 902221312 | B8: 44823 | C8: Paul Glanting | D8: =IF(ISBLANK(B8), "Email",IF(ISNA(VLOOKUP(A8,'Master List'!A:C,3,FALSE)), "Not Found", VLOOKUP(A8,'Master List'!A:C,3,FALSE))) -> pbg@mail.sfsu.edu | E8: HDMI > USB-C Adapter | G8: N/A | H8: one day | K8: 44823 | M8: =IF(AND(COUNTIF(#REF!, Returned_checkout!A103)=0, ISBLANK(K8)),"Yes", "No") -> #REF!
A9: 908543108 | B9: 44825 | C9: Kevin D Croshal | D9: =IF(ISBLANK(B9), "Email",IF(ISNA(VLOOKUP(A9,'Master List'!A:C,3,FALSE)), "Not Found", VLOOKUP(A9,'Master List'!A:C,3,FALSE))) -> kcroshal@sfsu.edu | E9: Blu-ray/DVD Player | H9: Later tonight | K9: 44825 | M9: =IF(AND(COUNTIF(#REF!, Returned_checkout!A75)=0, ISBLANK(K9)),"Yes", "No") -> #REF!
A10: 907441085 | B10: 44826 | C10: Cathy Rath | D10: =IF(ISBLANK(B10), "Email",IF(ISNA(VLOOKUP(A10,'Master List'!A:C,3,FALSE)), "Not Found", VLOOKUP(A10,'Master List'!A:C,3,FALSE))) -> crath@sfsu.edu | E10: Tripod - Small | G10: Webcam-6 AT Lib 85 | H10: one day | K10: 44826 | M10: =IF(AND(COUNTIF(#REF!, Returned_checkout!A22)=0, ISBLANK(K10)),"Yes", "No") -> #REF!
A11: 907441085 | B11: 44826 | C11: Cathy Rath | D11: =IF(ISBLANK(B11), "Email",IF(ISNA(VLOOKUP(A11,'Master List'!A:C,3,FALSE)), "Not Found", VLOOKUP(A11,'Master List'!A:C,3,FALSE))) -> crath@sfsu.edu | E11: Webcam (Logi C920s) | G11: ES-CTP-001 | H11: one day | K11: 44826 | M11: =IF(AND(COUNTIF(#REF!, Returned_checkout!A23)=0, ISBLANK(K11)),"Yes", "No") -> #REF!
A12: 907441085 | B12: 44826 | C12: Cathy Rath | D12: =IF(ISBLANK(B12), "Email",IF(ISNA(VLOOKUP(A12,'Master List'!A:C,3,FALSE)), "Not Found", VLOOKUP(A12,'Master List'!A:C,3,FALSE))) -> crath@sfsu.edu | E12: HDMI > USB-C Adapter | H12: one day | K12: 44826 | M12: =IF(AND(COUNTIF(#REF!, Returned_checkout!A24)=0, ISBLANK(K12)),"Yes", "No") -> #REF!
A13: 918844984 | B13: 44830 | C13: Meredith Stefran | D13: =IF(ISBLANK(B13), "Email",IF(ISNA(VLOOKUP(A13,'Master List'!A:C,3,FALSE)), "Not Found", VLOOKUP(A13,'Master List'!A:C,3,FALSE))) -> msafran@sfsu.edu | E13: HDMI > MDP Adapter | H13: A Week | K13: 44830 | M13: =IF(AND(COUNTIF(#REF!, Returned_checkout!A96)=0, ISBLANK(K13)),"Yes", "No") -> #REF!
A14: 913032515 | B14: 44830 | C14: Marisa Gymson | D14: =IF(ISBLANK(B14), "Email",IF(ISNA(VLOOKUP(A14,'Master List'!A:C,3,FALSE)), "Not Found", VLOOKUP(A14,'Master List'!A:C,3,FALSE))) -> mjimison@sfsu.edu | E14: HDMI > MDP Adapter | H14: a day | K14: 44831 | M14: =IF(AND(COUNTIF(#REF!, Returned_checkout!A93)=0, ISBLANK(K14)),"Yes", "No") -> #REF!
A15: 912817092 | B15: 44832 | C15: Deepika Ahuja | D15: =IF(ISBLANK(B15), "Email",IF(ISNA(VLOOKUP(A15,'Master List'!A:C,3,FALSE)), "Not Found", VLOOKUP(A15,'Master List'!A:C,3,FALSE))) -> deepikaahuja@sfsu.edu | E15: Headset (Logi H390) | H15: ? | K15: 44832 | M15: =IF(AND(COUNTIF(#REF!, Returned_checkout!A39)=0, ISBLANK(K15)),"Yes", "No") -> #REF!
A16: 904119858 | B16: 44833 | C16: Arturo Arritta | D16: =IF(ISBLANK(B16), "Email",IF(ISNA(VLOOKUP(A16,'Master List'!A:C,3,FALSE)), "Not Found", VLOOKUP(A16,'Master List'!A:C,3,FALSE))) -> aarrieta@sfsu.edu | E16: DVD The War: 1. A Necessarly War | H16: ? | K16: 44833 | M16: =IF(AND(COUNTIF(#REF!, Returned_checkout!A10)=0, ISBLANK(K16)),"Yes", "No") -> #REF!
A17: 904119858 | B17: 44833 | C17: Arturo Arritta | D17: =IF(ISBLANK(B17), "Email",IF(ISNA(VLOOKUP(A17,'Master List'!A:C,3,FALSE)), "Not Found", VLOOKUP(A17,'Master List'!A:C,3,FALSE))) -> aarrieta@sfsu.edu | E17: DVD 500 nations Cauldron of War | G17: 68401 | H17: Picked up last semester | K17: 44833 | M17: =IF(AND(COUNTIF(#REF!, Returned_checkout!A11)=0, ISBLANK(K17)),"Yes", "No") -> #REF!
A18: 904119858 | B18: 44833 | C18: Arturo Arritta | D18: =IF(ISBLANK(B18), "Email",IF(ISNA(VLOOKUP(A18,'Master List'!A:C,3,FALSE)), "Not Found", VLOOKUP(A18,'Master List'!A:C,3,FALSE))) -> aarrieta@sfsu.edu | E18: Blu-ray/DVD Player | G18: 89875 | H18: a week | K18: 44833 | M18: =IF(AND(COUNTIF(#REF!, Returned_checkout!A12)=0, ISBLANK(K18)),"Yes", "No") -> #REF!
A19: 916483521 | B19: 44833 | C19: Tomomi Kinukawa | D19: =IF(ISBLANK(B19), "Email",IF(ISNA(VLOOKUP(A19,'Master List'!A:C,3,FALSE)), "Not Found", VLOOKUP(A19,'Master List'!A:C,3,FALSE))) -> tkinukaw@sfsu.edu | E19: HDMI > MDP Adapter | H19: Returned from last semester | K19: 44833 | M19: =IF(AND(COUNTIF(#REF!, Returned_checkout!A123)=0, ISBLANK(K19)),"Yes", "No") -> #REF!
A20: 900030903 | B20: 44830 | C20: Ping Hsiao | D20: =IF(ISBLANK(B20), "Email",IF(ISNA(VLOOKUP(A20,'Master List'!A:C,3,FALSE)), "Not Found", VLOOKUP(A20,'Master List'!A:C,3,FALSE))) -> phsiao@sfsu.edu | E20: HDMI > USB-C Adapter | H20: 2 Weeks | K20: 44834 | M20: =IF(AND(COUNTIF(#REF!, Returned_checkout!A104)=0, ISBLANK(K20)),"Yes", "No") -> #REF!
A21: 911216610 | B21: 44826 | C21: Kim Nguyen | D21: =IF(ISBLANK(B21), "Email",IF(ISNA(VLOOKUP(A21,'Master List'!A:C,3,FALSE)), "Not Found", VLOOKUP(A21,'Master List'!A:C,3,FALSE))) -> kimn@sfsu.edu | E21: PA - Small | H21: A Week | K21: 44837 | M21: =IF(AND(COUNTIF(#REF!, Returned_checkout!A76)=0, ISBLANK(K21)),"Yes", "No") -> #REF!
A22: 912975029 | B22: 44837 | C22: Andrea Swei | D22: =IF(ISBLANK(B22), "Email",IF(ISNA(VLOOKUP(A22,'Master List'!A:C,3,FALSE)), "Not Found", VLOOKUP(A22,'Master List'!A:C,3,FALSE))) -> aswei@sfsu.edu | E22: VGA > USB-C Adapter Adapter | H22: end of the day | K22: 44837 | M22: =IF(AND(COUNTIF(#REF!, Returned_checkout!A7)=0, ISBLANK(K22)),"Yes", "No") -> #REF!
A23: 912333934 | B23: 44837 | C23: CAROLINA MARTINEZ | D23: =IF(ISBLANK(B23), "Email",IF(ISNA(VLOOKUP(A23,'Master List'!A:C,3,FALSE)), "Not Found", VLOOKUP(A23,'Master List'!A:C,3,FALSE))) -> cmartine@sfsu.edu | E23: HDMI > USB-C Adapter | H23: A DAY | K23: 44837 | M23: =IF(AND(COUNTIF(#REF!, Returned_checkout!A21)=0, ISBLANK(K23)),"Yes", "No") -> #REF!
A24: 902976066 | B24: 44838 | C24: Fenicia Jacks | D24: =IF(ISBLANK(B24), "Email",IF(ISNA(VLOOKUP(A24,'Master List'!A:C,3,FALSE)), "Not Found", VLOOKUP(A24,'Master List'!A:C,3,FALSE))) -> jacksf@sfsu.edu | E24: HDMI > MDP Adapter | J24: Dylan | K24: 44838 | M24: =IF(AND(COUNTIF(#REF!, Returned_checkout!A50)=0, ISBLANK(K24)),"Yes", "No") -> #REF!
A25: 900011585 | B25: 44838 | C25: Venise Wangner | D25: =IF(ISBLANK(B25), "Email",IF(ISNA(VLOOKUP(A25,'Master List'!A:C,3,FALSE)), "Not Found", VLOOKUP(A25,'Master List'!A:C,3,FALSE))) -> vwagner@sfsu.edu | E25: VHS Cart | G25: 81076 @HSS154 | H25: Today | J25: Kevin | K25: 44838 | M25: =IF(AND(COUNTIF(#REF!, Returned_checkout!A134)=0, ISBLANK(K25)),"Yes", "No") -> #REF!
A26: 918831256 | B26: 44839 | C26: Michelle Toney | D26: =IF(ISBLANK(B26), "Email",IF(ISNA(VLOOKUP(A26,'Master List'!A:C,3,FALSE)), "Not Found", VLOOKUP(A26,'Master List'!A:C,3,FALSE))) -> mstoney@sfsu.edu | E26: VGA > HDMI Adapter Adapter | G26: VGAHD-4 | H26: end of semester | K26: 44839 | M26: =IF(AND(COUNTIF(#REF!, Returned_checkout!A97)=0, ISBLANK(K26)),"Yes", "No") -> #REF!
A27: 912222407 | B27: 44838 | C27: Sean Crouch | D27: =IF(ISBLANK(B27), "Email",IF(ISNA(VLOOKUP(A27,'Master List'!A:C,3,FALSE)), "Not Found", VLOOKUP(A27,'Master List'!A:C,3,FALSE))) -> scrouch3@sfsu.edu | E27: HDMI > MDP Adapter | H27: end of semester | K27: 44845 | M27: =IF(AND(COUNTIF(#REF!, Returned_checkout!A114)=0, ISBLANK(K27)),"Yes", "No") -> #REF!
A28: 900008426 | B28: 44844 | C28: Amy Kilgard | D28: =IF(ISBLANK(B28), "Email",IF(ISNA(VLOOKUP(A28,'Master List'!A:C,3,FALSE)), "Not Found", VLOOKUP(A28,'Master List'!A:C,3,FALSE))) -> akilgard@sfsu.edu | E28: VGA > USB-C Adapter Adapter | H28: Tomorrow | K28: 44845 | M28: =IF(AND(COUNTIF(#REF!, Returned_checkout!A5)=0, ISBLANK(K28)),"Yes", "No") -> #REF!
A29: 900000483 | B29: 44845 | C29: Susan Zieff | D29: =IF(ISBLANK(B29), "Email",IF(ISNA(VLOOKUP(A29,'Master List'!A:C,3,FALSE)), "Not Found", VLOOKUP(A29,'Master List'!A:C,3,FALSE))) -> susangz@sfsu.edu | E29: Blu-ray/DVD Player | H29: 44846 | K29: 44846 | M29: =IF(AND(COUNTIF(#REF!, Returned_checkout!A118)=0, ISBLANK(K29)),"Yes", "No") -> #REF!
A30: 900010415 | B30: 44830 | C30: Dane Johnson | D30: =IF(ISBLANK(B30), "Email",IF(ISNA(VLOOKUP(A30,'Master List'!A:C,3,FALSE)), "Not Found", VLOOKUP(A30,'Master List'!A:C,3,FALSE))) -> danej@sfsu.edu | E30: Blu-ray/DVD Player | H30: End of semester | K30: 44847 | M30: =IF(AND(COUNTIF(#REF!, Returned_checkout!A33)=0, ISBLANK(K30)),"Yes", "No") -> #REF!
A31: 906197869 | B31: 44851 | C31: Ja Ronn Thompson | D31: =IF(ISBLANK(B31), "Email",IF(ISNA(VLOOKUP(A31,'Master List'!A:C,3,FALSE)), "Not Found", VLOOKUP(A31,'Master List'!A:C,3,FALSE))) -> jaronn@mail.sfsu.edu | E31: Projector - Loose (CP-EX250N) | G31: LCD453 | H31: 6:30 today | J31: Kevin | K31: 44851 | M31: =IF(AND(COUNTIF(#REF!, Returned_checkout!A54)=0, ISBLANK(K31)),"Yes", "No") -> #REF!
A32: 904585453 | B32: 44851 | C32: Lucas Tobin | D32: =IF(ISBLANK(B32), "Email",IF(ISNA(VLOOKUP(A32,'Master List'!A:C,3,FALSE)), "Not Found", VLOOKUP(A32,'Master List'!A:C,3,FALSE))) -> tobin@sfsu.edu | E32: VHS Cart | H32: end of the day | J32: Kevin | K32: 44851 | M32: =IF(AND(COUNTIF(#REF!, Returned_checkout!A88)=0, ISBLANK(K32)),"Yes", "No") -> #REF!
A33: 907441085 | B33: 44847 | C33: Cathy Rath | D33: =IF(ISBLANK(B33), "Email",IF(ISNA(VLOOKUP(A33,'Master List'!A:C,3,FALSE)), "Not Found", VLOOKUP(A33,'Master List'!A:C,3,FALSE))) -> crath@sfsu.edu | E33: Blu-ray/DVD Player | H33: 1 week from date | K33: 44854 | M33: =IF(AND(COUNTIF(#REF!, Returned_checkout!A25)=0, ISBLANK(K33)),"Yes", "No") -> #REF!
A34: 915848432 | B34: 44858 | C34: Valerie Fernandez | D34: =IF(ISBLANK(B34), "Email",IF(ISNA(VLOOKUP(A34,'Master List'!A:C,3,FALSE)), "Not Found", VLOOKUP(A34,'Master List'!A:C,3,FALSE))) -> vfernandez3@sfsu.edu | E34: HDMI > USB-C Adapter | H34: end of day | K34: 44858 | M34: =IF(AND(COUNTIF(#REF!, Returned_checkout!A132)=0, ISBLANK(K34)),"Yes", "No") -> #REF!
A35: 918118557 | B35: 44854 | C35: Elizabeth Ramirez-Soto | D35: =IF(ISBLANK(B35), "Email",IF(ISNA(VLOOKUP(A35,'Master List'!A:C,3,FALSE)), "Not Found", VLOOKUP(A35,'Master List'!A:C,3,FALSE))) -> Eramirezsoto@sfsu.edu | E35: Mac Power Adapter (USB-C) | H35: End of Day | K35: 44861 | M35: =IF(AND(COUNTIF(#REF!, Returned_checkout!A42)=0, ISBLANK(K35)),"Yes", "No") -> #REF!
A36: 922230410 | B36: 44865 | C36: Kshitiz Sareen | D36: =IF(ISBLANK(B36), "Email",IF(ISNA(VLOOKUP(A36,'Master List'!A:C,3,FALSE)), "Not Found", VLOOKUP(A36,'Master List'!A:C,3,FALSE))) -> ksareen@sfsu.edu | E36: HDMI > USB-C Adapter | K36: 44865 | M36: =IF(AND(COUNTIF(#REF!, Returned_checkout!A82)=0, ISBLANK(K36)),"Yes", "No") -> #REF!
A37: 918833999 | B37: 44858 | C37: David Hurwich | D37: =IF(ISBLANK(B37), "Email",IF(ISNA(VLOOKUP(A37,'Master List'!A:C,3,FALSE)), "Not Found", VLOOKUP(A37,'Master List'!A:C,3,FALSE))) -> davidhurwich@sfsu.edu | E37: Projector - Loose (CP-EX250N) | G37: LCD-400 | H37: Will return it on 11/01 | J37: Kevin | K37: 44866 | L37: Projector was not checked back in | M37: =IF(AND(COUNTIF(#REF!, Returned_checkout!A36)=0, ISBLANK(K37)),"Yes", "No") -> #REF!
A38: 903114854 | B38: 44866 | C38: Gustavo Lopez | D38: =IF(ISBLANK(B38), "Email",IF(ISNA(VLOOKUP(A38,'Master List'!A:C,3,FALSE)), "Not Found", VLOOKUP(A38,'Master List'!A:C,3,FALSE))) -> gus1492@sfsu.edu | E38: External DVD Drive | G38: DVD- DR-9 | H38: 11/3 (Thursday) | K38: 44868 | M38: =IF(AND(COUNTIF(#REF!, Returned_checkout!A52)=0, ISBLANK(K38)),"Yes", "No") -> #REF!
A39: 900034920 | B39: 44868 | C39: Brigitte Davila | D39: =IF(ISBLANK(B39), "Email",IF(ISNA(VLOOKUP(A39,'Master List'!A:C,3,FALSE)), "Not Found", VLOOKUP(A39,'Master List'!A:C,3,FALSE))) -> davila@sfsu.edu | E39: HDMI > USB-C Adapter | K39: 44868 | M39: =IF(AND(COUNTIF(#REF!, Returned_checkout!A19)=0, ISBLANK(K39)),"Yes", "No") -> #REF!
A40: 911398493 | B40: 44867 | C40: Chris Finley | D40: =IF(ISBLANK(B40), "Email",IF(ISNA(VLOOKUP(A40,'Master List'!A:C,3,FALSE)), "Not Found", VLOOKUP(A40,'Master List'!A:C,3,FALSE))) -> cfinley@sfsu.edu | E40: HDMI > USB-C Adapter | H40: End of semester | K40: 44872 | M40: =IF(AND(COUNTIF(#REF!, Returned_checkout!A26)=0, ISBLANK(K40)),"Yes", "No") -> #REF!
A41: 922230410 | B41: 44872 | C41: Kshitiz Sareen | D41: =IF(ISBLANK(B41), "Email",IF(ISNA(VLOOKUP(A41,'Master List'!A:C,3,FALSE)), "Not Found", VLOOKUP(A41,'Master List'!A:C,3,FALSE))) -> ksareen@sfsu.edu | E41: HDMI > USB-C Adapter | H41: 44872 | K41: 44872 | M41: =IF(AND(COUNTIF(#REF!, Returned_checkout!A83)=0, ISBLANK(K41)),"Yes", "No") -> #REF!
A42: 918103087 | B42: 44872 | C42: Ryan Smith | D42: =IF(ISBLANK(B42), "Email",IF(ISNA(VLOOKUP(A42,'Master List'!A:C,3,FALSE)), "Not Found", VLOOKUP(A42,'Master List'!A:C,3,FALSE))) -> ryansmith@sfsu.edu | E42: PA - Small | G42: PA-10 | H42: 44873 | I42: Kevin | J42: Kevin | K42: 44873 | M42: =IF(AND(COUNTIF(#REF!, Returned_checkout!A110)=0, ISBLANK(K42)),"Yes", "No") -> #REF!
A43: 917243150 | B43: 44873 | C43: Ron Hayduk | D43: =IF(ISBLANK(B43), "Email",IF(ISNA(VLOOKUP(A43,'Master List'!A:C,3,FALSE)), "Not Found", VLOOKUP(A43,'Master List'!A:C,3,FALSE))) -> rhayduk@sfsu.edu | E43: HDMI > USB-C Adapter | H43: Today | I43: Ash | J43: Ash | K43: 44873 | M43: =IF(AND(COUNTIF(#REF!, Returned_checkout!A109)=0, ISBLANK(K43)),"Yes", "No") -> #REF!
A44: 900000249 | B44: 44867 | C44: T.Holton | D44: =IF(ISBLANK(B44), "Email",IF(ISNA(VLOOKUP(A44,'Master List'!A:C,3,FALSE)), "Not Found", VLOOKUP(A44,'Master List'!A:C,3,FALSE))) -> tholton@sfsu.edu | E44: Dell Power Adapter (legacy barrel plug) | H44: end of semester | K44: 44874 | M44: =IF(AND(COUNTIF(#REF!, Returned_checkout!A119)=0, ISBLANK(K44)),"Yes", "No") -> #REF!
A45: 918328884 | B45: 44874 | C45: Menaal Alowdi | D45: =IF(ISBLANK(B45), "Email",IF(ISNA(VLOOKUP(A45,'Master List'!A:C,3,FALSE)), "Not Found", VLOOKUP(A45,'Master List'!A:C,3,FALSE))) -> malowdi@mail.sfsu.edu | E45: HDMI > USB-C Adapter | H45: 44874 | K45: 44875 | M45: =IF(AND(COUNTIF(#REF!, Returned_checkout!A94)=0, ISBLANK(K45)),"Yes", "No") -> #REF!
A46: 900010415 | B46: 44872 | C46: Dane Johnson | D46: =IF(ISBLANK(B46), "Email",IF(ISNA(VLOOKUP(A46,'Master List'!A:C,3,FALSE)), "Not Found", VLOOKUP(A46,'Master List'!A:C,3,FALSE))) -> danej@sfsu.edu | E46: Blu-ray/DVD Player | G46: BR-1 | H46: 44874 | J46: Joey | K46: 44879 | M46: =IF(AND(COUNTIF(#REF!, Returned_checkout!A32)=0, ISBLANK(K46)),"Yes", "No") -> #REF!
A47: 900032307 | B47: 44874 | C47: Kirk Schaible | D47: =IF(ISBLANK(B47), "Email",IF(ISNA(VLOOKUP(A47,'Master List'!A:C,3,FALSE)), "Not Found", VLOOKUP(A47,'Master List'!A:C,3,FALSE))) -> kirks@sfsu.edu | E47: External DVD Drive | H47: Monday | I47: Dang | J47: Dang | K47: 44879 | M47: =IF(AND(COUNTIF(#REF!, Returned_checkout!A77)=0, ISBLANK(K47)),"Yes", "No") -> #REF!
A48: 906197869 | B48: 44879 | C48: Ja Ronn Thompson | D48: =IF(ISBLANK(B48), "Email",IF(ISNA(VLOOKUP(A48,'Master List'!A:C,3,FALSE)), "Not Found", VLOOKUP(A48,'Master List'!A:C,3,FALSE))) -> jaronn@mail.sfsu.edu | E48: VGA > USB-C Adapter Adapter | H48: end of the semester | I48: Ritu | J48: Ritu | K48: 44879 | M48: =IF(AND(COUNTIF(#REF!, Returned_checkout!A55)=0, ISBLANK(K48)),"Yes", "No") -> #REF!
A49: 915848432 | B49: 44879 | C49: Velerie Fernandez | D49: =IF(ISBLANK(B49), "Email",IF(ISNA(VLOOKUP(A49,'Master List'!A:C,3,FALSE)), "Not Found", VLOOKUP(A49,'Master List'!A:C,3,FALSE))) -> vfernandez3@sfsu.edu | E49: HDMI > USB-C Adapter | H49: Today (11/14) | I49: Marie | J49: Dang | K49: 44879 | M49: =IF(AND(COUNTIF(#REF!, Returned_checkout!A133)=0, ISBLANK(K49)),"Yes", "No") -> #REF!
A50: 905538964 | B50: 44879 | C50: April Phung | D50: =IF(ISBLANK(B50), "Email",IF(ISNA(VLOOKUP(A50,'Master List'!A:C,3,FALSE)), "Not Found", VLOOKUP(A50,'Master List'!A:C,3,FALSE))) -> wang@sfsu.edu | E50: HDMI > USB-C Adapter | H50: Today (11/14) | I50: Joey | J50: Joey | K50: 44879 | M50: =IF(AND(COUNTIF(#REF!, Returned_checkout!A8)=0, ISBLANK(K50)),"Yes", "No") -> #REF!
A51: 921406197 | B51: 44879 | C51: Christopher Pascua | D51: =IF(ISBLANK(B51), "Email",IF(ISNA(VLOOKUP(A51,'Master List'!A:C,3,FALSE)), "Not Found", VLOOKUP(A51,'Master List'!A:C,3,FALSE))) -> cpascua@sfsu.edu | E51: Mac Power Adapter (USB-C) | H51: Today (11/14) | I51: Joey | J51: Dylan | K51: 44879 | M51: =IF(AND(COUNTIF(#REF!, Returned_checkout!A28)=0, ISBLANK(K51)),"Yes", "No") -> #REF!
A52: 922230410 | B52: 44879 | C52: Kshitiz Sareen | D52: =IF(ISBLANK(B52), "Email",IF(ISNA(VLOOKUP(A52,'Master List'!A:C,3,FALSE)), "Not Found", VLOOKUP(A52,'Master List'!A:C,3,FALSE))) -> ksareen@sfsu.edu | E52: HDMI > USB-C Adapter | H52: Today (11/14) | I52: Marie | J52: Marie | K52: 44879 | M52: =IF(AND(COUNTIF(#REF!, Returned_checkout!A84)=0, ISBLANK(K52)),"Yes", "No") -> #REF!
A53: 900035518 | B53: 44868 | C53: Sanjit Sengupta | D53: =IF(ISBLANK(B53), "Email",IF(ISNA(VLOOKUP(A53,'Master List'!A:C,3,FALSE)), "Not Found", VLOOKUP(A53,'Master List'!A:C,3,FALSE))) -> sengupta@sfsu.edu | E53: Mouse (Mac) | H53: End of semester | K53: 44880 | M53: =IF(AND(COUNTIF(#REF!, Returned_checkout!A111)=0, ISBLANK(K53)),"Yes", "No") -> #REF!
A54: 908101043 | B54: 44880 | C54: Benjamin Black | D54: =IF(ISBLANK(B54), "Email",IF(ISNA(VLOOKUP(A54,'Master List'!A:C,3,FALSE)), "Not Found", VLOOKUP(A54,'Master List'!A:C,3,FALSE))) -> bblack@mail.sfsu.edu | E54: ? | G54: CHDMI-A72 | H54: Today | I54: Joey | J54: Marie | K54: 44880 | M54: =IF(AND(COUNTIF(#REF!, Returned_checkout!A16)=0, ISBLANK(K54)),"Yes", "No") -> #REF!
A55: 918841084 | B55: 44880 | C55: E Wes Bathel | D55: =IF(ISBLANK(B55), "Email",IF(ISNA(VLOOKUP(A55,'Master List'!A:C,3,FALSE)), "Not Found", VLOOKUP(A55,'Master List'!A:C,3,FALSE))) -> ewbethel@sfsu.edu | E55: HDMI > USB-C Adapter | H55: Today (11/15) | I55: Marie | J55: Marie | K55: 44880 | M55: =IF(AND(COUNTIF(#REF!, Returned_checkout!A41)=0, ISBLANK(K55)),"Yes", "No") -> #REF!
A56: 900046555 | B56: 44880 | C56: Tracy Thai | D56: =IF(ISBLANK(B56), "Email",IF(ISNA(VLOOKUP(A56,'Master List'!A:C,3,FALSE)), "Not Found", VLOOKUP(A56,'Master List'!A:C,3,FALSE))) -> tthai@sfsu.edu | E56: Dell Power Adapter (legacy barrel plug) | H56: Today | I56: Joey | J56: Ash | K56: 44880 | M56: =IF(AND(COUNTIF(#REF!, Returned_checkout!A125)=0, ISBLANK(K56)),"Yes", "No") -> #REF!
A57: 922230410 | B57: 44881 | C57: Kshitiz Sareen | D57: =IF(ISBLANK(B57), "Email",IF(ISNA(VLOOKUP(A57,'Master List'!A:C,3,FALSE)), "Not Found", VLOOKUP(A57,'Master List'!A:C,3,FALSE))) -> ksareen@sfsu.edu | E57: HDMI > USB-C Adapter | H57: Today | I57: Marie | K57: 44880 | M57: =IF(AND(COUNTIF(#REF!, Returned_checkout!A85)=0, ISBLANK(K57)),"Yes", "No") -> #REF!
A58: 913786515 | B58: 44880 | C58: Richard Ortiz | D58: =IF(ISBLANK(B58), "Email",IF(ISNA(VLOOKUP(A58,'Master List'!A:C,3,FALSE)), "Not Found", VLOOKUP(A58,'Master List'!A:C,3,FALSE))) -> gabe2ro@sfsu.edu | E58: Webcam (Logi C920s) | H58: Th or FR | J58: Kanisha | K58: 44880 | M58: =IF(AND(COUNTIF(#REF!, Returned_checkout!A108)=0, ISBLANK(K58)),"Yes", "No") -> #REF!
A59: 917241317 | B59: 44879 | C59: Nick Sousanis | D59: =IF(ISBLANK(B59), "Email",IF(ISNA(VLOOKUP(A59,'Master List'!A:C,3,FALSE)), "Not Found", VLOOKUP(A59,'Master List'!A:C,3,FALSE))) -> sousanis@sfsu.edu | E59: Surface Pro Charger | H59: End of the semenster | I59: Kevin, Joey | J59: Ritu | K59: 44881 | M59: =IF(AND(COUNTIF(#REF!, Returned_checkout!A100)=0, ISBLANK(K59)),"Yes", "No") -> #REF!
A60: 917241317 | B60: 44879 | C60: Nick Sousanis | D60: =IF(ISBLANK(B60), "Email",IF(ISNA(VLOOKUP(A60,'Master List'!A:C,3,FALSE)), "Not Found", VLOOKUP(A60,'Master List'!A:C,3,FALSE))) -> sousanis@sfsu.edu | E60: Surface Pro Charger | H60: Tomorrow | I60: Joey | J60: Ritu | K60: 44881 | M60: =IF(AND(COUNTIF(#REF!, Returned_checkout!A101)=0, ISBLANK(K60)),"Yes", "No") -> #REF!
A61: 921202929 | B61: 44881 | C61: Audrey Wong | D61: =IF(ISBLANK(B61), "Email",IF(ISNA(VLOOKUP(A61,'Master List'!A:C,3,FALSE)), "Not Found", VLOOKUP(A61,'Master List'!A:C,3,FALSE))) -> awong38@mail.sfsu.edu | E61: HDMI > USB-C Adapter | H61: today | I61: Chris | J61: Chris | K61: 44881 | M61: =IF(AND(COUNTIF(#REF!, Returned_checkout!A13)=0, ISBLANK(K61)),"Yes", "No") -> #REF!
A62: 918842436 | B62: 44883 | C62: Jessica Stone | D62: =IF(ISBLANK(B62), "Email",IF(ISNA(VLOOKUP(A62,'Master List'!A:C,3,FALSE)), "Not Found", VLOOKUP(A62,'Master List'!A:C,3,FALSE))) -> stonejh@sfsu.edu | E62: Webcam (Logi C920s) | H62: end of semester | I62: Desktop | J62: Kanisha | K62: 44883 | M62: =IF(AND(COUNTIF(#REF!, Returned_checkout!A57)=0, ISBLANK(K62)),"Yes", "No") -> #REF!
A63: 918842436 | B63: 44883 | C63: Jessica Stone | D63: =IF(ISBLANK(B63), "Email",IF(ISNA(VLOOKUP(A63,'Master List'!A:C,3,FALSE)), "Not Found", VLOOKUP(A63,'Master List'!A:C,3,FALSE))) -> stonejh@sfsu.edu | E63: Headset (Logi H390) | H63: end of semester | I63: Desktop | J63: Kanisha | K63: 44883 | M63: =IF(AND(COUNTIF(#REF!, Returned_checkout!A58)=0, ISBLANK(K63)),"Yes", "No") -> #REF!
A64: 918842436 | B64: 44883 | C64: Jessica Stone | D64: =IF(ISBLANK(B64), "Email",IF(ISNA(VLOOKUP(A64,'Master List'!A:C,3,FALSE)), "Not Found", VLOOKUP(A64,'Master List'!A:C,3,FALSE))) -> stonejh@sfsu.edu | E64: Ethernet > USB-A Adapter | H64: end of semester | I64: Desktop | J64: Kanisha | K64: 44883 | M64: =IF(AND(COUNTIF(#REF!, Returned_checkout!A59)=0, ISBLANK(K64)),"Yes", "No") -> #REF!
A65: 918842436 | B65: 44883 | C65: Jessica Stone | D65: =IF(ISBLANK(B65), "Email",IF(ISNA(VLOOKUP(A65,'Master List'!A:C,3,FALSE)), "Not Found", VLOOKUP(A65,'Master List'!A:C,3,FALSE))) -> stonejh@sfsu.edu | E65: Multiport adapter (USB-C hub) (USB-C hub) | H65: end of semester | I65: Desktop | J65: Kanisha | K65: 44883 | M65: =IF(AND(COUNTIF(#REF!, Returned_checkout!A60)=0, ISBLANK(K65)),"Yes", "No") -> #REF!
A66: 900388260 | B66: 44884 | C66: Susan Englander | D66: =IF(ISBLANK(B66), "Email",IF(ISNA(VLOOKUP(A66,'Master List'!A:C,3,FALSE)), "Not Found", VLOOKUP(A66,'Master List'!A:C,3,FALSE))) -> englande@sfsu.edu | E66: Mac Power Adapter (USB-C) | H66: ? | I66: ? | K66: 44883 | M66: =IF(AND(COUNTIF(#REF!, Returned_checkout!A117)=0, ISBLANK(K66)),"Yes", "No") -> #REF!
A67: 910589178 | B67: 44893 | C67: Dan Curtis Cummuns | D67: =IF(ISBLANK(B67), "Email",IF(ISNA(VLOOKUP(A67,'Master List'!A:C,3,FALSE)), "Not Found", VLOOKUP(A67,'Master List'!A:C,3,FALSE))) -> dcc123@sfsu.edu | E67: HDMI > USB-C Adapter | H67: Today | I67: Ritu | J67: Ritu | K67: 44893 | M67: =IF(AND(COUNTIF(#REF!, Returned_checkout!A31)=0, ISBLANK(K67)),"Yes", "No") -> #REF!
A68: 917457819 | B68: 44893 | C68: Seyedan Joseph | D68: =IF(ISBLANK(B68), "Email",IF(ISNA(VLOOKUP(A68,'Master List'!A:C,3,FALSE)), "Not Found", VLOOKUP(A68,'Master List'!A:C,3,FALSE))) -> jseyedan@sfsu.edu | E68: HDMI > USB-C Adapter | H68: Today 2pm | I68: Joey | J68: Ritu | K68: 44893 | M68: =IF(AND(COUNTIF(#REF!, Returned_checkout!A115)=0, ISBLANK(K68)),"Yes", "No") -> #REF!
A69: 915848432 | B69: 44893 | C69: Valeria Fernandez | D69: =IF(ISBLANK(B69), "Email",IF(ISNA(VLOOKUP(A69,'Master List'!A:C,3,FALSE)), "Not Found", VLOOKUP(A69,'Master List'!A:C,3,FALSE))) -> vfernandez3@sfsu.edu | E69: HDMI > USB-C Adapter | H69: Today 12.30 | I69: Kanisha, Joey | K69: 44893 | M69: =IF(AND(COUNTIF(#REF!, Returned_checkout!A131)=0, ISBLANK(K69)),"Yes", "No") -> #REF!
A70: 917281357 | B70: 44893 | D70: =IF(ISBLANK(B70), "Email",IF(ISNA(VLOOKUP(A70,'Master List'!A:C,3,FALSE)), "Not Found", VLOOKUP(A70,'Master List'!A:C,3,FALSE))) -> manely@sfsu.edu | E70: HDMI > USB-C Adapter | H70: 44893 | I70: Kevin | J70: Ritu | K70: 44893 | M70: =IF(AND(COUNTIF(#REF!, Returned_checkout!A136)=0, ISBLANK(K70)),"Yes", "No") -> #REF!
A71: 918119389 | B71: 44894 | C71: Katherine Mahalic | D71: =IF(ISBLANK(B71), "Email",IF(ISNA(VLOOKUP(A71,'Master List'!A:C,3,FALSE)), "Not Found", VLOOKUP(A71,'Master List'!A:C,3,FALSE))) -> kmahalic@sfsu.edu | E71: HDMI > USB-C Adapter | H71: Today | I71: Marie | J71: Joey | K71: 44894 | M71: =IF(AND(COUNTIF(#REF!, Returned_checkout!A71)=0, ISBLANK(K71)),"Yes", "No") -> #REF!
A72: 916408303 | B72: 44810 | C72: Crystal Anderson | D72: =IF(ISBLANK(B72), "Email",IF(ISNA(VLOOKUP(A72,'Master List'!A:C,3,FALSE)), "Not Found", VLOOKUP(A72,'Master List'!A:C,3,FALSE))) -> kanders2@sfsu.edu | E72: HDMI > MDP Adapter | H72: End of semester | J72: Larissa | K72: 44895 | M72: =IF(AND(COUNTIF(#REF!, Returned_checkout!A30)=0, ISBLANK(K72)),"Yes", "No") -> #REF!
A73: 915081692 | B73: 44893 | C73: Valdez Neriyda | D73: =IF(ISBLANK(B73), "Email",IF(ISNA(VLOOKUP(A73,'Master List'!A:C,3,FALSE)), "Not Found", VLOOKUP(A73,'Master List'!A:C,3,FALSE))) -> nmonteci@sfsu.edu | E73: HDMI > MDP Adapter | H73: end of semester | I73: Joey | K73: 44895 | M73: =IF(AND(COUNTIF(#REF!, Returned_checkout!A127)=0, ISBLANK(K73)),"Yes", "No") -> #REF!
A74: 917457819 | B74: 44895 | C74: Joseph Seyedan | D74: =IF(ISBLANK(B74), "Email",IF(ISNA(VLOOKUP(A74,'Master List'!A:C,3,FALSE)), "Not Found", VLOOKUP(A74,'Master List'!A:C,3,FALSE))) -> jseyedan@sfsu.edu | E74: HDMI > USB-C Adapter | H74: TODAY | I74: Ritu | J74: Ritu | K74: 44895 | M74: =IF(AND(COUNTIF(#REF!, Returned_checkout!A63)=0, ISBLANK(K74)),"Yes", "No") -> #REF!
A75: 922230410 | B75: 44895 | C75: Kshitiz Sareen | D75: =IF(ISBLANK(B75), "Email",IF(ISNA(VLOOKUP(A75,'Master List'!A:C,3,FALSE)), "Not Found", VLOOKUP(A75,'Master List'!A:C,3,FALSE))) -> ksareen@sfsu.edu | E75: HDMI > USB-C Adapter | H75: Today | I75: Marie | J75: Ritu | K75: 44895 | M75: =IF(AND(COUNTIF(#REF!, Returned_checkout!A86)=0, ISBLANK(K75)),"Yes", "No") -> #REF!
A76: 918328884 | B76: 44895 | C76: Menaal Alowdi | D76: =IF(ISBLANK(B76), "Email",IF(ISNA(VLOOKUP(A76,'Master List'!A:C,3,FALSE)), "Not Found", VLOOKUP(A76,'Master List'!A:C,3,FALSE))) -> malowdi@mail.sfsu.edu | E76: HDMI > USB-C Adapter | H76: 7:50pm today | I76: Kevin | J76: Larissa | K76: 44895 | M76: =IF(AND(COUNTIF(#REF!, Returned_checkout!A95)=0, ISBLANK(K76)),"Yes", "No") -> #REF!
A77: 900012001 | B77: 44894 | C77: Jim Halligen | D77: =IF(ISBLANK(B77), "Email",IF(ISNA(VLOOKUP(A77,'Master List'!A:C,3,FALSE)), "Not Found", VLOOKUP(A77,'Master List'!A:C,3,FALSE))) -> halligan@sfsu.edu | E77: External DVD Drive | H77: 44896 | I77: Ash | J77: Larissa | K77: 44896 | M77: =IF(AND(COUNTIF(#REF!, Returned_checkout!A61)=0, ISBLANK(K77)),"Yes", "No") -> #REF!
A78: 921662349 | B78: 44896 | C78: Codey Stevenson | D78: =IF(ISBLANK(B78), "Email",IF(ISNA(VLOOKUP(A78,'Master List'!A:C,3,FALSE)), "Not Found", VLOOKUP(A78,'Master List'!A:C,3,FALSE))) -> cstephenson@sfsu.edu | E78: HDMI Cable | H78: Today | I78: Joey | K78: 44896 | M78: =IF(AND(COUNTIF(#REF!, Returned_checkout!A29)=0, ISBLANK(K78)),"Yes", "No") -> #REF!
A79: 915081692 | B79: 44896 | C79: Valdez Neriyda | D79: =IF(ISBLANK(B79), "Email",IF(ISNA(VLOOKUP(A79,'Master List'!A:C,3,FALSE)), "Not Found", VLOOKUP(A79,'Master List'!A:C,3,FALSE))) -> nmonteci@sfsu.edu | E79: HDMI > USB-C Adapter | H79: Today 3.25pm | I79: Joey | J79: Chris | K79: 44896 | M79: =IF(AND(COUNTIF(#REF!, Returned_checkout!A128)=0, ISBLANK(K79)),"Yes", "No") -> #REF!
A80: 915081692 | B80: 44901 | C80: Valdez Neriyda | D80: =IF(ISBLANK(B80), "Email",IF(ISNA(VLOOKUP(A80,'Master List'!A:C,3,FALSE)), "Not Found", VLOOKUP(A80,'Master List'!A:C,3,FALSE))) -> nmonteci@sfsu.edu | E80: HDMI > USB-C Adapter | H80: Today 3.25pm | I80: Joey | J80: Dang | K80: 44897 | M80: =IF(AND(COUNTIF(#REF!, Returned_checkout!A130)=0, ISBLANK(K80)),"Yes", "No") -> #REF!
A81: 900058281 | B81: 44859 | C81: Kevin Conner | D81: =IF(ISBLANK(B81), "Email",IF(ISNA(VLOOKUP(A81,'Master List'!A:C,3,FALSE)), "Not Found", VLOOKUP(A81,'Master List'!A:C,3,FALSE))) -> kevin@sfsu.edu | E81: Webcam (Logi C920s) | H81: end of semester | J81: Joey | K81: 44900 | M81: =IF(AND(COUNTIF(#REF!, Returned_checkout!A73)=0, ISBLANK(K81)),"Yes", "No") -> #REF!
A82: 917457819 | B82: 44900 | C82: Joseph Seyedan | D82: =IF(ISBLANK(B82), "Email",IF(ISNA(VLOOKUP(A82,'Master List'!A:C,3,FALSE)), "Not Found", VLOOKUP(A82,'Master List'!A:C,3,FALSE))) -> jseyedan@sfsu.edu | E82: HDMI > USB-C Adapter | H82: Today 2pm | I82: Joey | J82: Joey | K82: 44900 | M82: =IF(AND(COUNTIF(#REF!, Returned_checkout!A64)=0, ISBLANK(K82)),"Yes", "No") -> #REF!
A83: 908333171 | B83: 44900 | C83: Kamal Ragbotra | D83: =IF(ISBLANK(B83), "Email",IF(ISNA(VLOOKUP(A83,'Master List'!A:C,3,FALSE)), "Not Found", VLOOKUP(A83,'Master List'!A:C,3,FALSE))) -> kamragz@sfsu.edu | E83: Document Camera (Lumens DC125) | J83: Larissa | K83: 44900 | M83: =IF(AND(COUNTIF(#REF!, Returned_checkout!A66)=0, ISBLANK(K83)),"Yes", "No") -> #REF!
A84: 915081692 | B84: 44900 | C84: Valdez Neriyda | D84: =IF(ISBLANK(B84), "Email",IF(ISNA(VLOOKUP(A84,'Master List'!A:C,3,FALSE)), "Not Found", VLOOKUP(A84,'Master List'!A:C,3,FALSE))) -> nmonteci@sfsu.edu | E84: HDMI > USB-C Adapter | H84: Today 3.25pm | I84: Joey | J84: Joey | K84: 44900 | M84: =IF(AND(COUNTIF(#REF!, Returned_checkout!A129)=0, ISBLANK(K84)),"Yes", "No") -> #REF!
A85: 916483521 | B85: 44833 | C85: Tomomi Kinukawa | D85: =IF(ISBLANK(B85), "Email",IF(ISNA(VLOOKUP(A85,'Master List'!A:C,3,FALSE)), "Not Found", VLOOKUP(A85,'Master List'!A:C,3,FALSE))) -> tkinukaw@sfsu.edu | E85: HDMI > USB-C Adapter | H85: end of semester | J85: Joey | K85: 44901 | M85: =IF(AND(COUNTIF(#REF!, Returned_checkout!A122)=0, ISBLANK(K85)),"Yes", "No") -> #REF!
A86: 900058281 | B86: 44861 | C86: Kevin Conner | D86: =IF(ISBLANK(B86), "Email",IF(ISNA(VLOOKUP(A86,'Master List'!A:C,3,FALSE)), "Not Found", VLOOKUP(A86,'Master List'!A:C,3,FALSE))) -> kevin@sfsu.edu | E86: Webcam Mounts (snake mount) | H86: end of semester | J86: Rithik | K86: 44901 | M86: =IF(AND(COUNTIF(#REF!, Returned_checkout!A74)=0, ISBLANK(K86)),"Yes", "No") -> #REF!
A87: 922230410 | B87: 44901 | C87: Kshitiz Sareen | D87: =IF(ISBLANK(B87), "Email",IF(ISNA(VLOOKUP(A87,'Master List'!A:C,3,FALSE)), "Not Found", VLOOKUP(A87,'Master List'!A:C,3,FALSE))) -> ksareen@sfsu.edu | E87: HDMI > USB-C Adapter | H87: Today | I87: Marie | J87: Ritu | K87: 44901 | M87: =IF(AND(COUNTIF(#REF!, Returned_checkout!A87)=0, ISBLANK(K87)),"Yes", "No") -> #REF!
A88: 916483521 | B88: 44901 | C88: Tomomi Kinukawa | D88: =IF(ISBLANK(B88), "Email",IF(ISNA(VLOOKUP(A88,'Master List'!A:C,3,FALSE)), "Not Found", VLOOKUP(A88,'Master List'!A:C,3,FALSE))) -> tkinukaw@sfsu.edu | E88: Microphone - Shotgun (Rode VideoMic Pro+) | H88: Today | I88: Ash | J88: Joey | K88: 44901 | M88: =IF(AND(COUNTIF(#REF!, Returned_checkout!A124)=0, ISBLANK(K88)),"Yes", "No") -> #REF!
A89: 922217774 | B89: 44813 | C89: Alexei Spindell | D89: =IF(ISBLANK(B89), "Email",IF(ISNA(VLOOKUP(A89,'Master List'!A:C,3,FALSE)), "Not Found", VLOOKUP(A89,'Master List'!A:C,3,FALSE))) -> aspindell@sfsu.edu | E89: HDMI > MDP Adapter | G89: NA | H89: End of semester | J89: Larissa | K89: 44902 | M89: =IF(AND(COUNTIF(#REF!, Returned_checkout!A4)=0, ISBLANK(K89)),"Yes", "No") -> #REF!
A90: 909009756 | B90: 44839 | C90: Sean Connelly | D90: =IF(ISBLANK(B90), "Email",IF(ISNA(VLOOKUP(A90,'Master List'!A:C,3,FALSE)), "Not Found", VLOOKUP(A90,'Master List'!A:C,3,FALSE))) -> connelly@sfsu.edu | E90: External DVD Drive | G90: 69197 | H90: End of semester | J90: Ritu | K90: 44902 | M90: =IF(AND(COUNTIF(#REF!, Returned_checkout!A112)=0, ISBLANK(K90)),"Yes", "No") -> #REF!
A91: 921530178 | B91: 44874 | C91: Mona Shaath | D91: =IF(ISBLANK(B91), "Email",IF(ISNA(VLOOKUP(A91,'Master List'!A:C,3,FALSE)), "Not Found", VLOOKUP(A91,'Master List'!A:C,3,FALSE))) -> mshaath@mail.sfsu.edu | E91: HDMI > USB-C Adapter | H91: end of semester | I91: Desktop | J91: Ethan | K91: 44902 | M91: =IF(AND(COUNTIF(#REF!, Returned_checkout!A98)=0, ISBLANK(K91)),"Yes", "No") -> #REF!
A92: 909009756 | B92: 44874 | C92: Sean Connelly | D92: =IF(ISBLANK(B92), "Email",IF(ISNA(VLOOKUP(A92,'Master List'!A:C,3,FALSE)), "Not Found", VLOOKUP(A92,'Master List'!A:C,3,FALSE))) -> connelly@sfsu.edu | E92: VGA > HDMI Adapter Adapter | H92: end of semester | I92: Desktop | J92: Ritu | K92: 44902 | M92: =IF(AND(COUNTIF(#REF!, Returned_checkout!A113)=0, ISBLANK(K92)),"Yes", "No") -> #REF!
A93: 904212782 | B93: 44883 | C93: David Olsher | D93: =IF(ISBLANK(B93), "Email",IF(ISNA(VLOOKUP(A93,'Master List'!A:C,3,FALSE)), "Not Found", VLOOKUP(A93,'Master List'!A:C,3,FALSE))) -> olsher@sfsu.edu | E93: Webcam (Logi 720p) | H93: end of semester | I93: Kanisha | J93: Ritu | K93: 44902 | M93: =IF(AND(COUNTIF(#REF!, Returned_checkout!A38)=0, ISBLANK(K93)),"Yes", "No") -> #REF!
A94: 918119389 | B94: 44902 | C94: Katherine Mahalic | D94: =IF(ISBLANK(B94), "Email",IF(ISNA(VLOOKUP(A94,'Master List'!A:C,3,FALSE)), "Not Found", VLOOKUP(A94,'Master List'!A:C,3,FALSE))) -> kmahalic@sfsu.edu | E94: HDMI > USB-C Adapter | H94: Today | I94: Larissa | J94: Larissa | K94: 44902 | M94: =IF(AND(COUNTIF(#REF!, Returned_checkout!A70)=0, ISBLANK(K94)),"Yes", "No") -> #REF!
A95: 922290002 | B95: 44859 | C95: Calvin Anderson-Kibler | D95: =IF(ISBLANK(B95), "Email",IF(ISNA(VLOOKUP(A95,'Master List'!A:C,3,FALSE)), "Not Found", VLOOKUP(A95,'Master List'!A:C,3,FALSE))) -> aandersonkibler@sfsu.edu | E95: HDMI > USB-C Adapter | H95: end of semester | J95: Larissa | K95: 44903 | M95: =IF(AND(COUNTIF(#REF!, Returned_checkout!A20)=0, ISBLANK(K95)),"Yes", "No") -> #REF!
A96: 906487509 | B96: 44903 | C96: Amy Skanieczuy | D96: =IF(ISBLANK(B96), "Email",IF(ISNA(VLOOKUP(A96,'Master List'!A:C,3,FALSE)), "Not Found", VLOOKUP(A96,'Master List'!A:C,3,FALSE))) -> askonie@sfsu.edu | E96: HDMI > USB-C Adapter | H96: Today | I96: Larissa | J96: Dylan | K96: 44903 | M96: =IF(AND(COUNTIF(#REF!, Returned_checkout!A6)=0, ISBLANK(K96)),"Yes", "No") -> #REF!
A97: 900023064 | B97: 44903 | C97: Karen Coopman | D97: =IF(ISBLANK(B97), "Email",IF(ISNA(VLOOKUP(A97,'Master List'!A:C,3,FALSE)), "Not Found", VLOOKUP(A97,'Master List'!A:C,3,FALSE))) -> coopman@sfsu.edu | E97: HDMI > USB-C Adapter | H97: Today | I97: Larissa | J97: a | K97: 44903 | M97: =IF(AND(COUNTIF(#REF!, Returned_checkout!A67)=0, ISBLANK(K97)),"Yes", "No") -> #REF!
A98: 900008491 | B98: 44903 | C98: Tom Thomas | D98: =IF(ISBLANK(B98), "Email",IF(ISNA(VLOOKUP(A98,'Master List'!A:C,3,FALSE)), "Not Found", VLOOKUP(A98,'Master List'!A:C,3,FALSE))) -> tethomas@sfsu.edu | E98: Dell Power Adapter (USB-C) | H98: Today | I98: Larissa | J98: Dylan | K98: 44903 | M98: =IF(AND(COUNTIF(#REF!, Returned_checkout!A121)=0, ISBLANK(K98)),"Yes", "No") -> #REF!
A99: 916538979 | B99: 44903 | C99: Marciana Flores | D99: =IF(ISBLANK(B99), "Email",IF(ISNA(VLOOKUP(A99,'Master List'!A:C,3,FALSE)), "Not Found", VLOOKUP(A99,'Master List'!A:C,3,FALSE))) -> mfloresa@sfsu.edu | E99: PA - Small | H99: 44904 | I99: Ash | J99: Kanisha | K99: 44904 | M99: =IF(AND(COUNTIF(#REF!, Returned_checkout!A92)=0, ISBLANK(K99)),"Yes", "No") -> #REF!
A100: 905965819 | B100: 44879 | C100: Emily Yu Ting Yu | D100: =IF(ISBLANK(B100), "Email",IF(ISNA(VLOOKUP(A100,'Master List'!A:C,3,FALSE)), "Not Found", VLOOKUP(A100,'Master List'!A:C,3,FALSE))) -> yukiyu@sfsu.edu | E100: Laptop Bag | H100: End of the semenster | I100: Ted, Kevin | J100: Joey | K100: 44907 | M100: =IF(AND(COUNTIF(#REF!, Returned_checkout!A43)=0, ISBLANK(K100)),"Yes", "No") -> #REF!
...

Sheet Inventory
A1: Inventory LIB-80 | Brand | B1: Equipment Description | C1: Tot Units | D1: Out | E1: On Hand | F1: Note | G1: 44943 | H1: 45082
B2: Aux Cable (RCA to 3.5mm) | D2: =COUNTIFS(Outstanding_checkout!E:E,B2) -> 0
A3: [Miscellaneous] | B3: Blu-ray/DVD Player | C3: 18 | D3: =COUNTIFS(Outstanding_checkout!E:E,B3) -> 3 | E3: =C3-D3 -> 15 | G3: 15
A4: DJI | B4: Camcorder (DJI Pocket 2) | C4: 10 | D4: =COUNTIFS(Outstanding_checkout!E:E,B4) -> 4 | E4: =C4-D4 -> 6 | G4: 9
A5: Sony | B5: Camcorder (Sony 1080) | C5: 2 | D5: =COUNTIFS(Outstanding_checkout!E:E,B5) -> 1 | E5: =C5-D5 -> 1 | G5: 4
A6: Sony | B6: Camcorder (Sony 4K) | C6: 2 | D6: =COUNTIFS(Outstanding_checkout!E:E,B6) -> 1 | E6: =C6-D6 -> 1 | G6: 2
A7: Logitech CONNECT | B7: Conference Cam (Logi CONNECT) | C7: 31 | D7: =COUNTIFS(Outstanding_checkout!E:E,B7) -> 3 | E7: =C7-D7 -> 28 | G7: 31
A8: Dell | B8: Dell Power Adapter (legacy barrel plug) | D8: =COUNTIFS(Outstanding_checkout!E:E,B8) -> 6
A9: Dell | B9: Dell Power Adapter (USB-C) | D9: =COUNTIFS(Outstanding_checkout!E:E,B9) -> 2
A10: [Miscellaneous] | B10: DisplayPort Cable | D10: =COUNTIFS(Outstanding_checkout!E:E,B10) -> 3
A11: Lumens | B11: Document Camera (Lumens DC125) | C11: 45 | D11: =COUNTIFS(Outstanding_checkout!E:E,B11) -> 4 | E11: =C11-D11 -> 41 | G11: 45
B12: DTEN Cart | C12: 1 | D12: =COUNTIFS(Outstanding_checkout!E:E,B12) -> 0
B13: DVD | C13: 0 | D13: =COUNTIFS(Outstanding_checkout!E:E,B13) -> 4
A14: [Miscellaneous] | B14: Ethernet > USB-A Adapter | D14: =COUNTIFS(Outstanding_checkout!E:E,B14) -> 3
A15: [Miscellaneous] | B15: Ethernet > USB-C Adapter | D15: =COUNTIFS(Outstanding_checkout!E:E,B15) -> 11
A16: [Miscellaneous] | B16: Extension Cord Power Outlet | C16: 5 | D16: =COUNTIFS(Outstanding_checkout!E:E,B16) -> 3 | E16: =C16-D16 -> 2 | G16: 2
A17: Dell | B17: External DVD Drive | C17: 25 | D17: =COUNTIFS(Outstanding_checkout!E:E,B17) -> 4 | E17: =C17-D17 -> 21 | G17: 23
A18: GoPro | B18: GoPro 4 w/ tripod | D18: =COUNTIFS(Outstanding_checkout!E:E,B18) -> 0 | E18: =C18-D18 -> 0
A19: GoPro | B19: GoPro (Hero 8) | C19: 8 | D19: =COUNTIFS(Outstanding_checkout!E:E,B19) -> 0 | E19: =C19-D19 -> 8 | G19: 8
A20: GoPro | B20: GoPro 11 w/ tripod | C20: 35 | D20: =COUNTIFS(Outstanding_checkout!E:E,B20) -> 0 | E20: =C20-D20 -> 35
A21: Azden WR-Pro | B21: GoPro Wireless Mic | C21: 6 | D21: =COUNTIFS(Outstanding_checkout!E:E,B21) -> 0 | E21: =C21-D21 -> 6
A22: Generic | B22: Green Screen | C22: 4 | D22: =COUNTIFS(Outstanding_checkout!E:E,B22) -> 1 | E22: =C22-D22 -> 3 | G22: 4
A23: [Miscellaneous] | B23: HDMI > MDP Adapter | C23: 61 | D23: =COUNTIFS(Outstanding_checkout!E:E,B23) -> 49 | E23: =C23-D23 -> 12 | G23: 50
A24: [Miscellaneous] | B24: HDMI > USB-C Adapter | C24: 240 | D24: =COUNTIFS(Outstanding_checkout!E:E,B24) -> 168 | E24: =C24-D24 -> 72 | G24: 36
A25: [Miscellaneous] | B25: HDMI Cable | C25: 3 | D25: =COUNTIFS(Outstanding_checkout!E:E,B25) -> 10 | E25: =C25-D25 -> -7 | G25: 1
A26: Sennheiser | B26: Headphones (Sennheiser HD 202) | C26: 2 | D26: =COUNTIFS(Outstanding_checkout!E:E,B26) -> 2 | E26: =C26-D26 -> 0 | G26: 1
A27: SHURE | B27: Headphones (Shure SRH240) | C27: 4 | D27: =COUNTIFS(Outstanding_checkout!E:E,B27) -> 3 | E27: =C27-D27 -> 1 | G27: x
A28: LOGITEC | B28: Headset (Logi H390) | C28: 31 | D28: =COUNTIFS(Outstanding_checkout!E:E,B28) -> 31 | E28: =C28-D28 -> 0 | G28: 17 | H28: 26
A29: iClicker | B29: iClicker (Big box) | C29: 2 | D29: =COUNTIFS(Outstanding_checkout!E:E,B29) -> 0 | E29: =C29-D29 -> 2 | G29: 2
A30: iClicker | B30: iClicker Base Kit | C30: 3 | D30: =COUNTIFS(Outstanding_checkout!E:E,B30) -> 0 | E30: =C30-D30 -> 3 | G30: 3
B31: Lightning > 3.5mm headphone jack | C31: 1 | E31: =C31-D31 -> 1
B32: iphone lightning cable | C32: 3 | D32: =COUNTIFS(Outstanding_checkout!E:E,B32) -> 1 | E32: =C32-D32 -> 2
A33: [Miscellaneous] | B33: Keyboard (Mac) | C33: 3 | D33: =COUNTIFS(Outstanding_checkout!E:E,B33) -> 7 | E33: =C33-D33 -> -4
A34: [Miscellaneous] | B34: Keyboard (PC) | C34: 3 | D34: =COUNTIFS(Outstanding_checkout!E:E,B34) -> 8 | E34: =C34-D34 -> -5
B35: Laptop (Mac) + bag and charger | C35: 1 | D35: =COUNTIFS(Outstanding_checkout!E:E,B35) -> 4 | E35: =C35-D35 -> -3
B36: Laptop (Dell) + bag and charger | C36: 3 | D36: =COUNTIFS(Outstanding_checkout!E:E,B36) -> 0 | E36: =C36-D36 -> 3
A37: [Miscellaneous] | B37: Laptop Bag | C37: 31 | D37: =COUNTIFS(Outstanding_checkout!E:E,B37) -> 0 | E37: =C37-D37 -> 31 | G37: 31
A38: LOGITEC | B38: Laser Clicker | C38: 8 | D38: =COUNTIFS(Outstanding_checkout!E:E,B38) -> 10 | E38: =C38-D38 -> -2 | G38: 6
A39: Apple | B39: Mac Power Adapter (MagSafe 1) | C39: 1 | D39: =COUNTIFS(Outstanding_checkout!E:E,B39) -> 0 | E39: =C39-D39 -> 1
A40: Apple | B40: Mac Power Adapter (MagSafe 2) | C40: 1 | D40: =COUNTIFS(Outstanding_checkout!E:E,B40) -> 2 | E40: =C40-D40 -> -1
A41: Apple | B41: Mac Power Adapter (MagSafe 3) | C41: 1 | D41: =COUNTIFS(Outstanding_checkout!E:E,B41) -> 1 | E41: =C41-D41 -> 0
A42: Apple | B42: Mac Power Adapter (USB-C) | D42: =COUNTIFS(Outstanding_checkout!E:E,B42) -> 21 | E42: =C42-D42 -> -21
A43: Rode | B43: Microphone - Shotgun (Rode VideoMic Pro+) | C43: 6 | D43: =COUNTIFS(Outstanding_checkout!E:E,B43) -> 1 | E43: =C43-D43 -> 5 | G43: 5
A44: Blue | B44: Microphone - USB (Blue Yeti) | C44: 15 | D44: =COUNTIFS(Outstanding_checkout!E:E,B44) -> 5 | E44: =C44-D44 -> 10 | G44: 15
A45: Rode | B45: Microphone - USB (Rode NT) | C45: 34 | D45: =COUNTIFS(Outstanding_checkout!E:E,B45) -> 4 | E45: =C45-D45 -> 30 | G45: 32
A46: Misc | B46: Microphone - XLR | C46: 7 | D46: =COUNTIFS(Outstanding_checkout!E:E,B46) -> 2 | E46: =C46-D46 -> 5 | G46: 7
A47: MXL | B47: Microphone (MXL AC-406 USB) | C47: 4 | D47: =COUNTIFS(Outstanding_checkout!E:E,B47) -> 0 | E47: =C47-D47 -> 4 | G47: 4
A48: Zoom | B48: Microphone (Zoom H1 DAR) | C48: 8 | D48: =COUNTIFS(Outstanding_checkout!E:E,B48) -> 2 | E48: =C48-D48 -> 6 | G48: 8
A49: Generic | B49: Microphone Cable - XLR | C49: 4 | D49: =COUNTIFS(Outstanding_checkout!E:E,B49) -> 2 | E49: =C49-D49 -> 2 | G49: 4
A50: Generic | B50: Microphone Stands - XLR (Short) | C50: 8 | D50: =COUNTIFS(Outstanding_checkout!E:E,B50) -> 0 | E50: =C50-D50 -> 8 | G50: 8
A51: Generic | B51: Microphone Stands - XLR (Tall) | C51: 4 | D51: =COUNTIFS(Outstanding_checkout!E:E,B51) -> 0 | E51: =C51-D51 -> 4 | G51: 4
A52: Apple | B52: Mouse (Mac) | D52: =COUNTIFS(Outstanding_checkout!E:E,B52) -> 5
A53: [Miscellaneous] | B53: Mouse (PC) | D53: =COUNTIFS(Outstanding_checkout!E:E,B53) -> 10
A54: Anker | B54: Multiport adapter (USB-C hub) | D54: =COUNTIFS(Outstanding_checkout!E:E,B54) -> 0
A55: Behringer | B55: PA - Large (Europort) | C55: 3 | D55: =COUNTIFS(Outstanding_checkout!E:E,B55) -> 1 | E55: =C55-D55 -> 2 | G55: 3
A56: [Miscellaneous] | B56: PA - Small | C56: 52 | D56: =COUNTIFS(Outstanding_checkout!E:E,B56) -> 28 | E56: =C56-D56 -> 24 | G56: 39
A57: WACOM | B57: Pen Display (Wacom One) | C57: 7 | D57: =COUNTIFS(Outstanding_checkout!E:E,B57) -> 4 | E57: =C57-D57 -> 3 | G57: 6
A58: WACOM | B58: Pen Tablet (Wacom Intous Pro) | C58: 34 | D58: =COUNTIFS(Outstanding_checkout!E:E,B58) -> 2 | E58: =C58-D58 -> 32 | G58: 34
A59: WACOM | B59: Pen Tablet (Wacom Intuos) | C59: 18 | D59: =COUNTIFS(Outstanding_checkout!E:E,B59) -> 8 | E59: =C59-D59 -> 10 | G59: 16
B60: Power Cable (D-Plug) | D60: =COUNTIFS(Outstanding_checkout!E:E,B60) -> 2
A61: Hitachi | B61: Projector - Loose (CP-EX250N) | C61: 4 | D61: =COUNTIFS(Outstanding_checkout!E:E,B61) -> 1 | E61: =C61-D61 -> 3 | F61: (1 in LIB 80); get these back | G61: 3
A62: [Miscellaneous] | B62: Projector Cart | C62: 1 | D62: =COUNTIFS(Outstanding_checkout!E:E,B62) -> 0 | E62: =C62-D62 -> 1 | G62: 1
A63: Generic | B63: Projector Screen | C63: 5 | D63: =COUNTIFS(Outstanding_checkout!E:E,B63) -> 0 | E63: =C63-D63 -> 5 | G63: 5
A64: Neewer | B64: Ring Light - Large | C64: 24 | D64: =COUNTIFS(Outstanding_checkout!E:E,B64) -> 2 | E64: =C64-D64 -> 22 | G64: 24
A65: Trigyn | B65: Ring Light - Small | C65: 38 | D65: =COUNTIFS(Outstanding_checkout!E:E,B65) -> 2 | E65: =C65-D65 -> 36 | G65: 37
B66: Slide Projector | C66: 2 | D66: =COUNTIFS(Outstanding_checkout!E:E,B66) -> 0 | F66: Inventory record carried over from WCO - Greta Snider has had two checked out since 2021, had to return both in WCO in order to check in a DVD on 2/17/23
A67: Anker | B67: Speaker (Anker Soundcore Bluetooth) | C67: 1 | D67: =COUNTIFS(Outstanding_checkout!E:E,B67) -> 1 | E67: =C67-D67 -> 0 | G67: 1
A68: Generic | B68: Speaker Stands (Large PA) | C68: 6 | D68: =COUNTIFS(Outstanding_checkout!E:E,B68) -> 0 | E68: =C68-D68 -> 6 | G68: 6
A69: Logitech | B69: Speakers (Logitech Z200) | C69: 5 | D69: =COUNTIFS(Outstanding_checkout!E:E,B69) -> 0 | E69: =C69-D69 -> 5 | G69: 5
A70: Microsoft | B70: Surface Pro Charger | D70: =COUNTIFS(Outstanding_checkout!E:E,B70) -> 2
A71: WACOM | B71: Tablet Pen (Wacom Pen 4K) | C71: 119 | D71: =COUNTIFS(Outstanding_checkout!E:E,B71) -> 1 | E71: =C71-D71 -> 118 | G71: 118
A72: TRYONE | B72: Tablet stand (snake mount) | C72: 7 | D72: =COUNTIFS(Outstanding_checkout!E:E,B72) -> 0 | E72: =C72-D72 -> 7 | F72: Ash using one for 3D printer | G72: 7
A73: Generic | B73: Tripod - Large | C73: 9 | D73: =COUNTIFS(Outstanding_checkout!E:E,B73) -> 3 | E73: =C73-D73 -> 6 | G73: 9
A74: Generic | B74: Tripod - Small | C74: 13 | D74: =COUNTIFS(Outstanding_checkout!E:E,B74) -> 10 | E74: =C74-D74 -> 3 | G74: 9
B75: TV + VHS Cart | C75: 1
A76: [Miscellaneous] | B76: USB-A > USB-C Adapter | C76: 1 | D76: =COUNTIFS(Outstanding_checkout!E:E,B76) -> 15 | E76: =C76-D76 -> -14
B77: USB-A > USB-C Cable
B78: USB-C > USB-C Cable | C78: 1 | D78: =COUNTIFS(Outstanding_checkout!E:E,B78) -> 10 | E78: =C78-D78 -> -9
A79: [Miscellaneous] | B79: VGA > HDMI Adapter | C79: 29 | D79: =COUNTIFS(Outstanding_checkout!E:E,B79) -> 8 | E79: =C79-D79 -> 21 | G79: 24
A80: [Miscellaneous] | B80: VGA > MDP Adapter | C80: 55 | D80: =COUNTIFS(Outstanding_checkout!E:E,B80) -> 0 | E80: =C80-D80 -> 55 | G80: 50
A81: [Miscellaneous] | B81: VGA > USB-C Adapter | C81: 42 | D81: =COUNTIFS(Outstanding_checkout!E:E,B81) -> 26 | E81: =C81-D81 -> 16 | G81: 41
B82: VGA Cable | C82: 1 | D82: =COUNTIFS(Outstanding_checkout!E:E,B82) -> 2
B83: VHS | C83: 100 | D83: =COUNTIFS(Outstanding_checkout!E:E,B83) -> 0 | E83: 100
A84: [Miscellaneous] | B84: VHS Cart | C84: 2 | D84: =COUNTIFS(Outstanding_checkout!E:E,B84) -> 0 | E84: =C84-D84 -> 2 | G84: 2
A85: Logitech HD 720p Webcam | B85: Webcam (Logi 720p) | C85: 7 | D85: =COUNTIFS(Outstanding_checkout!E:E,B85) -> 7 | E85: =C85-D85 -> 0 | G85: 5
A86: Logitech C920s Pro HD Webcam | B86: Webcam (Logi C920s) | C86: 49 | D86: =COUNTIFS(Outstanding_checkout!E:E,B86) -> 48 | E86: =C86-D86 -> 1 | G86: 33 | H86: 18
A87: CamStand | B87: Webcam Mounts (bar mount) | C87: 9 | D87: =COUNTIFS(Outstanding_checkout!E:E,B87) -> 0 | E87: =C87-D87 -> 9 | G87: 8 box
A88: PIPISHELL | B88: Webcam Mounts (snake mount) | C88: 11 | D88: =COUNTIFS(Outstanding_checkout!E:E,B88) -> 1 | E88: =C88-D88 -> 10 | G88: 10 | H88: 5
B89: Lightning > USB-C/HDMI | C89: 5 | D89: =COUNTIFS(Outstanding_checkout!E:E,B89) -> 0 | E89: =C89-D89 -> 5
B90: Ethernet Cable | C90: 0 | D90: =COUNTIFS(Outstanding_checkout!E:E,B90) -> 4 | E90: =C90-D90 -> -4
A91: Cannon | B91: DSLR Camera (Cannon 5D) | C91: 2 | D91: =COUNTIFS(Outstanding_checkout!E:E,B91) -> 3 | E91: =C91-D91 -> -1
A92: Godox | B92: Light Reflector | C92: 2 | D92: =COUNTIFS(Outstanding_checkout!E:E,B92) -> 0 | E92: =C92-D92 -> 2
A93: Razer | B93: Bluetooth Mic (Seiren BT) | C93: 5 | D93: =COUNTIFS(Outstanding_checkout!E:E,B93) -> 6 | E93: =C93-D93 -> -1
B94: SD Card | D94: =COUNTIFS(Outstanding_checkout!E:E,B94) -> 1 | E94: =C94-D94 -> -1
B95: Projector Remote (Hitachi) | D95: =COUNTIFS(Outstanding_checkout!E:E,B95) -> 1 | E95: =C95-D95 -> -1
B96: USB-A > USB-A cable | C96: 1 | D96: =COUNTIFS(Outstanding_checkout!E:E,B96) -> 1 | E96: =C96-D96 -> 0
B97: GoPro 4 and Tripod | C97: 100 | D97: =COUNTIFS(Outstanding_checkout!E:E,B97) -> 0 | E97: =C97-D97 -> 100
B98: DUO Token | D98: =COUNTIFS(Outstanding_checkout!E:E,B98) -> 1 | E98: =C98-D98 -> -1
C99: 4 | D99: =COUNTIFS(Outstanding_checkout!E:E,B99) -> 0 | E99: =C99-D99 -> 4
D100: =COUNTIFS(Outstanding_checkout!E:E,B100) -> 0 | E100: =C100-D100 -> 0
...

Sheet Log
A1: Date | B1: Equipment | C1: How many | D1: Added or Removed? | E1: New Total | F1: Notes
A2: 44939 | B2: HDMI > USB-C | C2: 37 | D2: added | E2: 125 | F2: New Anker adapters for SP23 via Jonathan
A3: 44939 | B3: HDMI > MDP | C3: 23 | D3: removed | E3: 60 | F3: Obsolete & we have too many to fit in bin > e-waste
A4: 44939 | B4: VGA > MDP | C4: 28 | D4: removed | E4: 51 | F4: Obsolete & we have too many to fit in bin > e-waste
A5: 44958 | B5: HDMI > USB-C | C5: 10 | D5: added | E5: 140 | F5: Extra new Anker adapters for SP23 via Healy
A6: 44963 | B6: HDMI > USB-C | C6: 100 | D6: added | E6: 200 | F6: Extra new Anker adapters for SP23 via Cristian

Sheet Overdue
A1: 918848078 | B1: 45266 | C1: =IF(ISBLANK(A1),"Name",IF(ISNA(VLOOKUP(A1,'Master List'!A:C,2,FALSE)), "Not Found", VLOOKUP(A1,'Master List'!A:C,2,FALSE))) -> Jaclyn Wolf | D1: =IF(ISBLANK(A1), "Email",IF(ISNA(VLOOKUP(A1,'Master List'!A:C,3,FALSE)), "Not Found", VLOOKUP(A1,'Master List'!A:C,3,FALSE))) -> jaclynwolf@sfsu.edu | E1: Bluetooth Mic (Seiren BT) | F1: =IF(OR(A1="",E1="","",A1="?",E1="?"),"duplicate?",IF(COUNTIFS($A:A,A1,E:E,E1)>1,"yes","no")) -> no | J1: Row #
A2: 900040926 | B2: 45233 | C2: =IF(ISBLANK(A2),"Name",IF(ISNA(VLOOKUP(A2,'Master List'!A:C,2,FALSE)), "Not Found", VLOOKUP(A2,'Master List'!A:C,2,FALSE))) -> Wesley Ueunten | D2: =IF(ISBLANK(A2), "Email",IF(ISNA(VLOOKUP(A2,'Master List'!A:C,3,FALSE)), "Not Found", VLOOKUP(A2,'Master List'!A:C,3,FALSE))) -> wesueu@sfsu.edu | E2: Bluetooth Mic (Seiren BT) | F2: =IF(OR(A2="",E2="","",A2="?",E2="?"),"duplicate?",IF(COUNTIFS($A:A,A2,E:E,E2)>1,"yes","no")) -> no | H2: 45275 | I2: Ethan | J2: 511
A3: 913444134 | B3: 44852 | C3: =IF(ISBLANK(A3),"Name",IF(ISNA(VLOOKUP(A3,'Master List'!A:C,2,FALSE)), "Not Found", VLOOKUP(A3,'Master List'!A:C,2,FALSE))) -> Gary Straub | D3: =IF(ISBLANK(A3), "Email",IF(ISNA(VLOOKUP(A3,'Master List'!A:C,3,FALSE)), "Not Found", VLOOKUP(A3,'Master List'!A:C,3,FALSE))) -> gstraub@sfsu.edu | E3: Camcorder (DJI Pocket 2) | F3: =IF(OR(A3="",E3="","",A3="?",E3="?"),"duplicate?",IF(COUNTIFS($A:A,A3,E:E,E3)>1,"yes","no")) -> no | H3: end of semester | I3: Joey | J3: 460
A4: 918847454 | B4: 45001 | C4: =IF(ISBLANK(A4),"Name",IF(ISNA(VLOOKUP(A4,'Master List'!A:C,2,FALSE)), "Not Found", VLOOKUP(A4,'Master List'!A:C,2,FALSE))) -> Tiffany Caesar | D4: =IF(ISBLANK(A4), "Email",IF(ISNA(VLOOKUP(A4,'Master List'!A:C,3,FALSE)), "Not Found", VLOOKUP(A4,'Master List'!A:C,3,FALSE))) -> tiffanycaesar@sfsu.edu | E4: Camcorder (DJI Pocket 2) | F4: =IF(OR(A4="",E4="","",A4="?",E4="?"),"duplicate?",IF(COUNTIFS($A:A,A4,E:E,E4)>1,"yes","no")) -> no | H4: end of semester | I4: ethan | J4: 450
A5: 916483521 | B5: 45161 | C5: =IF(ISBLANK(A5),"Name",IF(ISNA(VLOOKUP(A5,'Master List'!A:C,2,FALSE)), "Not Found", VLOOKUP(A5,'Master List'!A:C,2,FALSE))) -> Tomomi Kinukawa | D5: =IF(ISBLANK(A5), "Email",IF(ISNA(VLOOKUP(A5,'Master List'!A:C,3,FALSE)), "Not Found", VLOOKUP(A5,'Master List'!A:C,3,FALSE))) -> tkinukaw@sfsu.edu | E5: Microphone - XLR | F5: =IF(OR(A5="",E5="","",A5="?",E5="?"),"duplicate?",IF(COUNTIFS($A:A,A5,E:E,E5)>1,"yes","no")) -> no | H5: 45282 | I5: Cristian | J5: 80 | K5: Has note: "email sent, 1/20/23"
A6: 916483521 | B6: 45161 | C6: =IF(ISBLANK(A6),"Name",IF(ISNA(VLOOKUP(A6,'Master List'!A:C,2,FALSE)), "Not Found", VLOOKUP(A6,'Master List'!A:C,2,FALSE))) -> Tomomi Kinukawa | D6: =IF(ISBLANK(A6), "Email",IF(ISNA(VLOOKUP(A6,'Master List'!A:C,3,FALSE)), "Not Found", VLOOKUP(A6,'Master List'!A:C,3,FALSE))) -> tkinukaw@sfsu.edu | E6: Microphone Cable - XLR | F6: =IF(OR(A6="",E6="","",A6="?",E6="?"),"duplicate?",IF(COUNTIFS($A:A,A6,E:E,E6)>1,"yes","no")) -> no | H6: 45078 | I6: Larissa | J6: 321
A7: 901596090 | B7: 45163 | C7: =IF(ISBLANK(A7),"Name",IF(ISNA(VLOOKUP(A7,'Master List'!A:C,2,FALSE)), "Not Found", VLOOKUP(A7,'Master List'!A:C,2,FALSE))) -> Savita Malik | D7: =IF(ISBLANK(A7), "Email",IF(ISNA(VLOOKUP(A7,'Master List'!A:C,3,FALSE)), "Not Found", VLOOKUP(A7,'Master List'!A:C,3,FALSE))) -> smalik@sfsu.edu | E7: Projector - Loose (CP-EX250N) | F7: =IF(OR(A7="",E7="","",A7="?",E7="?"),"duplicate?",IF(COUNTIFS($A:A,A7,E:E,E7)>1,"yes","no")) -> no | H7: 45078 | I7: Jeremy | J7: 254

Sheet Temp
A1: Article Name | B1: Check out Max Time | C1: Notes
A2: Aux Cable (RCA to 3.5mm)
A3: Blu-ray/DVD Player | B3: 2 Weeks
A4: Camcorder (DJI Pocket 2) | B4: 2 Weeks
A5: Camcorder (Sony 1080) | B5: 2 Weeks
A6: Camcorder (Sony 4K) | B6: 2 Weeks
A7: Conference Cam (Logi CONNECT) | B7: Indefinitely
A8: Dell Power Adapter (legacy barrel plug) | B8: 1 Day
A9: Dell Power Adapter (USB-C) | B9: 1 Day
A10: DisplayPort Cable | B10: Indefinitely
A11: Document Camera (Lumens DC125) | B11: 2 weeks
A12: DTEN Cart | B12: 1-2 Days
A13: DVD | B13: 2 Weeks
A14: Ethernet > USB-A Adapter | B14: Indefinitely
... A60: Power Cable (D-Plug) | B60: 1-2 Day
A61: Projector - Loose (CP-EX250N)
A62: Projector Cart
A63: Projector Screen
A64: Ring Light - Large | B64: 2 Weeks
A65: Ring Light - Small | B65: Indefinitely
A66: Slide Projector
A67: Speaker (Anker Soundcore Bluetooth) | B67: 2 Weeks
A68: Speaker Stands (Large PA) | B68: 1 week
A69: Speakers (Logitech Z200)
A70: Surface Pro Charger | B70: 1-2 Days
A71: Tablet Pen (Wacom Pen 4K) | B71: Indefinitely
A72: Tablet stand (snake mount)
A73: Tripod - Large
A74: Tripod - Small | B74: Indefinitely
A75: TV + VHS Cart | B75: 2 weeks
A76: USB-A > USB-C Adapter | B76: Indefinitely
A77: USB-A > USB-C Cable | B77: Indefinitely
A78: USB-C > USB-C Cable | B78: Indefinitely
A79: VGA > HDMI Adapter | B79: Indefinitely
A80: VGA > MDP Adapter | B80: Indefinitely
A81: VGA > USB-C Adapter | B81: Indefinitely
A82: VGA Cable | B82: Indefinitely
A83: VHS | B83: 2 weeks
A84: VHS Cart | B84: 2 weeks
A85: Webcam (Logi 720p) | B85: Indefinitely
... A88: Webcam Mounts (snake mount) | B88: Indefinitely
A89: Lightning > USB-C/HDMI
A90: Ethernet Cable | B90: Indefinitely
A91: DSLR Camera (Cannon 5D) | B91: 2 weeks
A92: Light Reflector
A93: Bluetooth Mic (Seiren BT)
A94: SD Card | B94: 2 weeks
A95: Projector Remote (Hitachi)
A96: USB-A > USB-A cable
A97: GoPro 4 and Tripod | B97: 2 weeks
A98: DUO Token
